Workbook

Sheet mastered-10-26mar-dirty
A1: student | B1: third_party_level_id | C1: app | D1: date | E1: activity_units_attempted | F1: activity_units_correct | G1: level | H1: order
A2: Alessandra Green | B2: 3.2.FRAGMENT_OR_SENTENCE | C2: Alphawrite | D2: 45742 | E2: 38 | F2: 30 | G2: =LEFT(B2) -> 3 | H2: =VLOOKUP(B2,#REF!,5,FALSE) -> #REF!
A3: Arjun Caberwal | B3: 4.2.IDENTIFY_APPOSITIVES | C3: Alphawrite | D3: 45742 | E3: 19 | F3: 13 | G3: =LEFT(B3) -> 4 | H3: =VLOOKUP(B3,#REF!,5,FALSE) -> #REF!
A4: Arman Caberwal | B4: 4.2.WRITE_SENTENCE_ABOUT_PICTURE | C4: Alphawrite | D4: 45742 | E4: 12 | F4: 12 | G4: =LEFT(B4) -> 4 | H4: =VLOOKUP(B4,#REF!,5,FALSE) -> #REF!
A5: Arman Caberwal | B5: 4.2.WRITE_SENTENCE_TYPE | C5: Alphawrite | D5: 45742 | E5: 7 | F5: 7 | G5: =LEFT(B5) -> 4 | H5: =VLOOKUP(B5,#REF!,5,FALSE) -> #REF!
A6: Blake Flores | B6: 5.2.CHANGE_SENTENCE_TYPE | C6: Alphawrite | D6: 45742 | E6: 6 | F6: 2 | G6: =LEFT(B6) -> 5 | H6: =VLOOKUP(B6,#REF!,5,FALSE) -> #REF!
A7: Brady York | B7: 3.2.CHANGE_SENTENCE_TYPE | C7: Alphawrite | D7: 45742 | E7: 11 | F7: 5 | G7: =LEFT(B7) -> 3 | H7: =VLOOKUP(B7,#REF!,5,FALSE) -> #REF!
A8: Brady York | B8: 3.2.IDENTIFY_SENTENCE_TYPE | C8: Alphawrite | D8: 45742 | E8: 16 | F8: 14 | G8: =LEFT(B8) -> 3 | H8: =VLOOKUP(B8,#REF!,5,FALSE) -> #REF!
A9: David Paul | B9: 3.2.CHANGE_SENTENCE_TYPE | C9: Alphawrite | D9: 45742 | E9: 73 | F9: 44 | G9: =LEFT(B9) -> 3 | H9: =VLOOKUP(B9,#REF!,5,FALSE) -> #REF!
A10: David Paul | B10: 3.2.WRITE_SENTENCE_TYPE | C10: Alphawrite | D10: 45742 | E10: 4 | F10: 4 | G10: =LEFT(B10) -> 3 | H10: =VLOOKUP(B10,#REF!,5,FALSE) -> #REF!
A11: David Paul | B11: 4.2.FRAGMENT_OR_SENTENCE | C11: Alphawrite | D11: 45742 | E11: 2 | F11: 0 | G11: =LEFT(B11) -> 4 | H11: =VLOOKUP(B11,#REF!,5,FALSE) -> #REF!
A12: Elaina Robertson | B12: 4.2.UNSCRAMBLE_SENTENCES | C12: Alphawrite | D12: 45742 | E12: 13 | F12: 12 | G12: =LEFT(B12) -> 4 | H12: =VLOOKUP(B12,#REF!,5,FALSE) -> #REF!
A13: Evelyn Gabler | B13: 4.2.BASIC_CONJUNCTIONS | C13: Alphawrite | D13: 45742 | E13: 8 | F13: 8 | G13: =LEFT(B13) -> 4 | H13: =VLOOKUP(B13,#REF!,5,FALSE) -> #REF!
A14: Evelyn Gabler | B14: 4.2.KERNEL_EXPANSION | C14: Alphawrite | D14: 45742 | G14: =LEFT(B14) -> 4 | H14: =VLOOKUP(B14,#REF!,5,FALSE) -> #REF!
A15: Evelyn Gabler | B15: 5.2.FRAGMENT_OR_SENTENCE | C15: Alphawrite | D15: 45742 | G15: =LEFT(B15) -> 5 | H15: =VLOOKUP(B15,#REF!,5,FALSE) -> #REF!
A16: Hazel Salton | B16: 3.2.CHANGE_SENTENCE_TYPE | C16: Alphawrite | D16: 45742 | G16: =LEFT(B16) -> 3 | H16: =VLOOKUP(B16,#REF!,5,FALSE) -> #REF!
A17: Hazel Salton | B17: 3.2.UNSCRAMBLE_SENTENCES | C17: Alphawrite | D17: 45742 | E17: 11 | F17: 7 | G17: =LEFT(B17) -> 3 | H17: =VLOOKUP(B17,#REF!,5,FALSE) -> #REF!
A18: Hazel Salton | B18: 3.2.WRITE_SENTENCE_ABOUT_PICTURE | C18: Alphawrite | D18: 45742 | E18: 15 | F18: 11 | G18: =LEFT(B18) -> 3 | H18: =VLOOKUP(B18,#REF!,5,FALSE) -> #REF!
A19: Hazel Salton | B19: 4.2.FRAGMENT_OR_SENTENCE | C19: Alphawrite | D19: 45742 | G19: =LEFT(B19) -> 4 | H19: =VLOOKUP(B19,#REF!,5,FALSE) -> #REF!
A20: Helio Ortiz | B20: 3.2.FRAGMENT_OR_SENTENCE | C20: Alphawrite | D20: 45742 | E20: 49 | F20: 20 | G20: =LEFT(B20) -> 3 | H20: =VLOOKUP(B20,#REF!,5,FALSE) -> #REF!
A21: Ian Mentgen | B21: 3.2.UNSCRAMBLE_SENTENCES | C21: Alphawrite | D21: 45742 | G21: =LEFT(B21) -> 3 | H21: =VLOOKUP(B21,#REF!,5,FALSE) -> #REF!
A22: Ian Mentgen | B22: 3.2.WRITE_SENTENCE_TYPE | C22: Alphawrite | D22: 45742 | E22: 16 | F22: 14 | G22: =LEFT(B22) -> 3 | H22: =VLOOKUP(B22,#REF!,5,FALSE) -> #REF!
A23: Jaxon Siers | B23: 3.2.IDENTIFY_APPOSITIVES | C23: Alphawrite | D23: 45742 | E23: 26 | F23: 16 | G23: =LEFT(B23) -> 3 | H23: =VLOOKUP(B23,#REF!,5,FALSE) -> #REF!
A24: Jaxon Siers | B24: 3.2.WRITE_APPOSITIVES | C24: Alphawrite | D24: 45742 | E24: 26 | F24: 20 | G24: =LEFT(B24) -> 3 | H24: =VLOOKUP(B24,#REF!,5,FALSE) -> #REF!
A25: Jaxon Siers | B25: 4.2.FRAGMENT_OR_SENTENCE | C25: Alphawrite | D25: 45742 | G25: =LEFT(B25) -> 4 | H25: =VLOOKUP(B25,#REF!,5,FALSE) -> #REF!
A26: Lavender Marrero | B26: 4.2.CHANGE_SENTENCE_TYPE | C26: Alphawrite | D26: 45742 | E26: 6 | F26: 2 | G26: =LEFT(B26) -> 4 | H26: =VLOOKUP(B26,#REF!,5,FALSE) -> #REF!
A27: Lily Gray | B27: 5.2.FRAGMENT_OR_SENTENCE | C27: Alphawrite | D27: 45742 | G27: =LEFT(B27) -> 5 | H27: =VLOOKUP(B27,#REF!,5,FALSE) -> #REF!
A28: Logan Campbell | B28: 4.2.COMBINE_SENTENCES | C28: Alphawrite | D28: 45742 | G28: =LEFT(B28) -> 4 | H28: =VLOOKUP(B28,#REF!,5,FALSE) -> #REF!
A29: Marcus Fuentes | B29: 3.2.WRITE_APPOSITIVES | C29: Alphawrite | D29: 45742 | E29: 17 | F29: 13 | G29: =LEFT(B29) -> 3 | H29: =VLOOKUP(B29,#REF!,5,FALSE) -> #REF!
A30: Max Vaughan | B30: 3.2.UNSCRAMBLE_SENTENCES | C30: Alphawrite | D30: 45742 | E30: 12 | F30: 12 | G30: =LEFT(B30) -> 3 | H30: =VLOOKUP(B30,#REF!,5,FALSE) -> #REF!
A31: Mila Atamas | B31: 5.2.FRAGMENT_OR_SENTENCE | C31: Alphawrite | D31: 45742 | E31: 20 | F31: 16 | G31: =LEFT(B31) -> 5 | H31: =VLOOKUP(B31,#REF!,5,FALSE) -> #REF!
A32: Omar Ibarra | B32: 4.2.FRAGMENT_OR_SENTENCE | C32: Alphawrite | D32: 45742 | E32: 10 | F32: 4 | G32: =LEFT(B32) -> 4 | H32: =VLOOKUP(B32,#REF!,5,FALSE) -> #REF!
A33: Orion Campbell | B33: 5.2.CHANGE_SENTENCE_TYPE | C33: Alphawrite | D33: 45742 | E33: 2 | F33: 0 | G33: =LEFT(B33) -> 5 | H33: =VLOOKUP(B33,#REF!,5,FALSE) -> #REF!
A34: Orion Campbell | B34: 5.2.FRAGMENT_OR_SENTENCE | C34: Alphawrite | D34: 45742 | G34: =LEFT(B34) -> 5 | H34: =VLOOKUP(B34,#REF!,5,FALSE) -> #REF!
A35: Raegan Middleton | B35: 3.2.UNSCRAMBLE_SENTENCES | C35: Alphawrite | D35: 45742 | E35: 28 | F35: 26 | G35: =LEFT(B35) -> 3 | H35: =VLOOKUP(B35,#REF!,5,FALSE) -> #REF!
A36: Ramsey Levin | B36: 4.2.BASIC_CONJUNCTIONS | C36: Alphawrite | D36: 45742 | G36: =LEFT(B36) -> 4 | H36: =VLOOKUP(B36,#REF!,5,FALSE) -> #REF!
A37: Ramsey Levin | B37: 4.2.COMBINE_SENTENCES | C37: Alphawrite | D37: 45742 | G37: =LEFT(B37) -> 4 | H37: =VLOOKUP(B37,#REF!,5,FALSE) -> #REF!
A38: Ramsey Levin | B38: 4.2.WRITE_APPOSITIVES | C38: Alphawrite | D38: 45742 | E38: 4 | F38: 2 | G38: =LEFT(B38) -> 4 | H38: =VLOOKUP(B38,#REF!,5,FALSE) -> #REF!
A39: Ramsey Levin | B39: 4.2.WRITE_SENTENCE_TYPE | C39: Alphawrite | D39: 45742 | G39: =LEFT(B39) -> 4 | H39: =VLOOKUP(B39,#REF!,5,FALSE) -> #REF!
A40: Rocco Benetti | B40: 5.2.COMBINE_SENTENCES | C40: Alphawrite | D40: 45742 | E40: 2 | F40: 0 | G40: =LEFT(B40) -> 5 | H40: =VLOOKUP(B40,#REF!,5,FALSE) -> #REF!
A41: Rocco Benetti | B41: 5.2.IDENTIFY_APPOSITIVES | C41: Alphawrite | D41: 45742 | E41: 18 | F41: 14 | G41: =LEFT(B41) -> 5 | H41: =VLOOKUP(B41,#REF!,5,FALSE) -> #REF!
A42: Rocco Benetti | B42: 5.2.WRITE_APPOSITIVES | C42: Alphawrite | D42: 45742 | G42: =LEFT(B42) -> 5 | H42: =VLOOKUP(B42,#REF!,5,FALSE) -> #REF!
A43: Rocco Benetti | B43: 5.2.WRITE_SENTENCE_ABOUT_PICTURE | C43: Alphawrite | D43: 45742 | E43: 19 | F43: 17 | G43: =LEFT(B43) -> 5 | H43: =VLOOKUP(B43,#REF!,5,FALSE) -> #REF!
A44: Rocco Benetti | B44: 5.2.WRITE_SENTENCE_TYPE | C44: Alphawrite | D44: 45742 | E44: 22 | F44: 16 | G44: =LEFT(B44) -> 5 | H44: =VLOOKUP(B44,#REF!,5,FALSE) -> #REF!
A45: Sarah Hunter | B45: 3.2.IDENTIFY_TOPIC_SENTENCE | C45: Alphawrite | D45: 45742 | E45: 4 | F45: 2 | G45: =LEFT(B45) -> 3 | H45: =VLOOKUP(B45,#REF!,5,FALSE) -> #REF!
A46: Sophia Reicher | B46: 5.2.FRAGMENT_OR_SENTENCE | C46: Alphawrite | D46: 45742 | E46: 4 | F46: 4 | G46: =LEFT(B46) -> 5 | H46: =VLOOKUP(B46,#REF!,5,FALSE) -> #REF!
A47: Tate Price | B47: 3.2.FRAGMENT_OR_SENTENCE | C47: Alphawrite | D47: 45742 | G47: =LEFT(B47) -> 3 | H47: =VLOOKUP(B47,#REF!,5,FALSE) -> #REF!
A48: Tate Price | B48: 5.2.FRAGMENT_OR_SENTENCE | C48: Alphawrite | D48: 45742 | E48: 29 | F48: 19 | G48: =LEFT(B48) -> 5 | H48: =VLOOKUP(B48,#REF!,5,FALSE) -> #REF!
A49: Xavier Siddall | B49: 3.2.FRAGMENT_OR_SENTENCE | C49: Alphawrite | D49: 45742 | E49: 33 | F49: 23 | G49: =LEFT(B49) -> 3 | H49: =VLOOKUP(B49,#REF!,5,FALSE) -> #REF!
A50: Anaya Lenington | B50: 4.2.UNSCRAMBLE_SENTENCES | C50: Alphawrite | D50: 45741 | E50: 22 | F50: 16 | G50: =LEFT(B50) -> 4 | H50: =VLOOKUP(B50,#REF!,5,FALSE) -> #REF!
A51: Arjun Caberwal | B51: 4.2.CHANGE_SENTENCE_TYPE | C51: Alphawrite | D51: 45741 | E51: 4 | F51: 0 | G51: =LEFT(B51) -> 4 | H51: =VLOOKUP(B51,#REF!,5,FALSE) -> #REF!
A52: Arjun Caberwal | B52: 4.2.IDENTIFY_SENTENCE_TYPE | C52: Alphawrite | D52: 45741 | E52: 2 | F52: 2 | G52: =LEFT(B52) -> 4 | H52: =VLOOKUP(B52,#REF!,5,FALSE) -> #REF!
A53: Arjun Caberwal | B53: 4.2.WRITE_SENTENCE_ABOUT_PICTURE | C53: Alphawrite | D53: 45741 | E53: 13 | F53: 11 | G53: =LEFT(B53) -> 4 | H53: =VLOOKUP(B53,#REF!,5,FALSE) -> #REF!
A54: Arman Caberwal | B54: 4.2.CHANGE_SENTENCE_TYPE | C54: Alphawrite | D54: 45741 | E54: 20 | F54: 14 | G54: =LEFT(B54) -> 4 | H54: =VLOOKUP(B54,#REF!,5,FALSE) -> #REF!
A55: Arman Caberwal | B55: 4.2.USE_SENTENCE_TYPES | C55: Alphawrite | D55: 45741 | E55: 18 | F55: 10 | G55: =LEFT(B55) -> 4 | H55: =VLOOKUP(B55,#REF!,5,FALSE) -> #REF!
A56: Asha Nagar | B56: 5.2.FRAGMENT_OR_SENTENCE | C56: Alphawrite | D56: 45741 | G56: =LEFT(B56) -> 5 | H56: =VLOOKUP(B56,#REF!,5,FALSE) -> #REF!
A57: Aubrey Curtis | B57: 4.2.FRAGMENT_OR_SENTENCE | C57: Alphawrite | D57: 45741 | E57: 25 | F57: 15 | G57: =LEFT(B57) -> 4 | H57: =VLOOKUP(B57,#REF!,5,FALSE) -> #REF!
A58: Bella Barba | B58: 5.2.CHANGE_SENTENCE_TYPE | C58: Alphawrite | D58: 45741 | E58: 8 | F58: 2 | G58: =LEFT(B58) -> 5 | H58: =VLOOKUP(B58,#REF!,5,FALSE) -> #REF!
A59: Bella Barba | B59: 5.2.FRAGMENT_OR_SENTENCE | C59: Alphawrite | D59: 45741 | E59: 20 | F59: 12 | G59: =LEFT(B59) -> 5 | H59: =VLOOKUP(B59,#REF!,5,FALSE) -> #REF!
A60: Bella Barba | B60: 5.2.IDENTIFY_SENTENCE_TYPE | C60: Alphawrite | D60: 45741 | E60: 22 | F60: 18 | G60: =LEFT(B60) -> 5 | H60: =VLOOKUP(B60,#REF!,5,FALSE) -> #REF!
A61: Bella Barba | B61: 5.2.UNSCRAMBLE_SENTENCES | C61: Alphawrite | D61: 45741 | E61: 14 | F61: 14 | G61: =LEFT(B61) -> 5 | H61: =VLOOKUP(B61,#REF!,5,FALSE) -> #REF!
A62: Bennett Morris | B62: 5.2.USE_SENTENCE_TYPES | C62: Alphawrite | D62: 45741 | E62: 44 | F62: 32 | G62: =LEFT(B62) -> 5 | H62: =VLOOKUP(B62,#REF!,5,FALSE) -> #REF!
A63: Blake Flores | B63: 4.2.WRITE_FREEFORM_PARAGRAPH | C63: Alphawrite | D63: 45741 | G63: =LEFT(B63) -> 4 | H63: =VLOOKUP(B63,#REF!,5,FALSE) -> #REF!
A64: Blake Flores | B64: 5.2.CHANGE_SENTENCE_TYPE | C64: Alphawrite | D64: 45741 | G64: =LEFT(B64) -> 5 | H64: =VLOOKUP(B64,#REF!,5,FALSE) -> #REF!
A65: Blake Flores | B65: 5.2.IDENTIFY_SENTENCE_TYPE | C65: Alphawrite | D65: 45741 | E65: 2 | F65: 2 | G65: =LEFT(B65) -> 5 | H65: =VLOOKUP(B65,#REF!,5,FALSE) -> #REF!
A66: Blake Flores | B66: 5.2.UNSCRAMBLE_SENTENCES | C66: Alphawrite | D66: 45741 | E66: 8 | F66: 6 | G66: =LEFT(B66) -> 5 | H66: =VLOOKUP(B66,#REF!,5,FALSE) -> #REF!
A67: Blake Flores | B67: 5.2.WRITE_SENTENCE_ABOUT_PICTURE | C67: Alphawrite | D67: 45741 | E67: 3 | F67: 3 | G67: =LEFT(B67) -> 5 | H67: =VLOOKUP(B67,#REF!,5,FALSE) -> #REF!
A68: Brady York | B68: 3.2.UNSCRAMBLE_SENTENCES | C68: Alphawrite | D68: 45741 | E68: 15 | F68: 15 | G68: =LEFT(B68) -> 3 | H68: =VLOOKUP(B68,#REF!,5,FALSE) -> #REF!
A69: Brooklyn Allred | B69: 4.2.UNSCRAMBLE_SENTENCES | C69: Alphawrite | D69: 45741 | E69: 4 | F69: 2 | G69: =LEFT(B69) -> 4 | H69: =VLOOKUP(B69,#REF!,5,FALSE) -> #REF!
A70: Connor Cason | B70: 3.2.FRAGMENT_OR_SENTENCE | C70: Alphawrite | D70: 45741 | E70: 6 | F70: 6 | G70: =LEFT(B70) -> 3 | H70: =VLOOKUP(B70,#REF!,5,FALSE) -> #REF!
A71: Connor Cason | B71: 4.2.BASIC_CONJUNCTIONS | C71: Alphawrite | D71: 45741 | G71: =LEFT(B71) -> 4 | H71: =VLOOKUP(B71,#REF!,5,FALSE) -> #REF!
A72: David Paul | B72: 3.2.CHANGE_SENTENCE_TYPE | C72: Alphawrite | D72: 45741 | E72: 2 | F72: 0 | G72: =LEFT(B72) -> 3 | H72: =VLOOKUP(B72,#REF!,5,FALSE) -> #REF!
A73: David Paul | B73: 3.2.IDENTIFY_SENTENCE_TYPE | C73: Alphawrite | D73: 45741 | E73: 57 | F73: 34 | G73: =LEFT(B73) -> 3 | H73: =VLOOKUP(B73,#REF!,5,FALSE) -> #REF!
A74: Donnie Moore | B74: 3.2.UNSCRAMBLE_SENTENCES | C74: Alphawrite | D74: 45741 | E74: 16 | F74: 16 | G74: =LEFT(B74) -> 3 | H74: =VLOOKUP(B74,#REF!,5,FALSE) -> #REF!
A75: Elaina Robertson | B75: 4.2.FRAGMENT_OR_SENTENCE | C75: Alphawrite | D75: 45741 | E75: 84 | F75: 58 | G75: =LEFT(B75) -> 4 | H75: =VLOOKUP(B75,#REF!,5,FALSE) -> #REF!
A76: Elena Mentgen | B76: 3.2.FRAGMENT_OR_SENTENCE | C76: Alphawrite | D76: 45741 | E76: 2 | F76: 2 | G76: =LEFT(B76) -> 3 | H76: =VLOOKUP(B76,#REF!,5,FALSE) -> #REF!
A77: Elena Mentgen | B77: 3.2.UNSCRAMBLE_SENTENCES | C77: Alphawrite | D77: 45741 | E77: 2 | F77: 2 | G77: =LEFT(B77) -> 3 | H77: =VLOOKUP(B77,#REF!,5,FALSE) -> #REF!
A78: Elena Mentgen | B78: 3.2.USE_SENTENCE_TYPES | C78: Alphawrite | D78: 45741 | E78: 2 | F78: 2 | G78: =LEFT(B78) -> 3 | H78: =VLOOKUP(B78,#REF!,5,FALSE) -> #REF!
A79: Elena Mentgen | B79: 5.2.CHANGE_SENTENCE_TYPE | C79: Alphawrite | D79: 45741 | E79: 24 | F79: 22 | G79: =LEFT(B79) -> 5 | H79: =VLOOKUP(B79,#REF!,5,FALSE) -> #REF!
A80: Elena Mentgen | B80: 5.2.IDENTIFY_SENTENCE_TYPE | C80: Alphawrite | D80: 45741 | E80: 16 | F80: 14 | G80: =LEFT(B80) -> 5 | H80: =VLOOKUP(B80,#REF!,5,FALSE) -> #REF!
A81: Evelyn Gabler | B81: 4.2.BASIC_CONJUNCTIONS | C81: Alphawrite | D81: 45741 | E81: 6 | F81: 6 | G81: =LEFT(B81) -> 4 | H81: =VLOOKUP(B81,#REF!,5,FALSE) -> #REF!
A82: Evelyn Gabler | B82: 4.2.COMBINE_SENTENCES | C82: Alphawrite | D82: 45741 | E82: 16 | F82: 14 | G82: =LEFT(B82) -> 4 | H82: =VLOOKUP(B82,#REF!,5,FALSE) -> #REF!
A83: Evelyn Gabler | B83: 4.2.USE_SENTENCE_TYPES | C83: Alphawrite | D83: 45741 | E83: 43 | F83: 30 | G83: =LEFT(B83) -> 4 | H83: =VLOOKUP(B83,#REF!,5,FALSE) -> #REF!
A84: Evelyn Gabler | B84: 5.2.FRAGMENT_OR_SENTENCE | C84: Alphawrite | D84: 45741 | G84: =LEFT(B84) -> 5 | H84: =VLOOKUP(B84,#REF!,5,FALSE) -> #REF!
A85: Hazel Salton | B85: 3.2.IDENTIFY_APPOSITIVES | C85: Alphawrite | D85: 45741 | G85: =LEFT(B85) -> 3 | H85: =VLOOKUP(B85,#REF!,5,FALSE) -> #REF!
A86: Hazel Salton | B86: 3.2.IDENTIFY_SENTENCE_TYPE | C86: Alphawrite | D86: 45741 | E86: 28 | F86: 18 | G86: =LEFT(B86) -> 3 | H86: =VLOOKUP(B86,#REF!,5,FALSE) -> #REF!
A87: Hazel Salton | B87: 3.2.TURN_OUTLINE_INTO_DRAFT | C87: Alphawrite | D87: 45741 | G87: =LEFT(B87) -> 3 | H87: =VLOOKUP(B87,#REF!,5,FALSE) -> #REF!
A88: Hazel Salton | B88: 3.2.WRITE_APPOSITIVES | C88: Alphawrite | D88: 45741 | E88: 8 | F88: 0 | G88: =LEFT(B88) -> 3 | H88: =VLOOKUP(B88,#REF!,5,FALSE) -> #REF!
A89: Hazel Salton | B89: 4.2.FRAGMENT_OR_SENTENCE | C89: Alphawrite | D89: 45741 | E89: 4 | F89: 2 | G89: =LEFT(B89) -> 4 | H89: =VLOOKUP(B89,#REF!,5,FALSE) -> #REF!
A90: Ian Mentgen | B90: 3.2.CHANGE_SENTENCE_TYPE | C90: Alphawrite | D90: 45741 | E90: 24 | F90: 18 | G90: =LEFT(B90) -> 3 | H90: =VLOOKUP(B90,#REF!,5,FALSE) -> #REF!
A91: Ian Mentgen | B91: 3.2.USE_SENTENCE_TYPES | C91: Alphawrite | D91: 45741 | E91: 16 | F91: 12 | G91: =LEFT(B91) -> 3 | H91: =VLOOKUP(B91,#REF!,5,FALSE) -> #REF!
A92: Jason Montagna | B92: 4.2.FRAGMENT_OR_SENTENCE | C92: Alphawrite | D92: 45741 | E92: 28 | F92: 14 | G92: =LEFT(B92) -> 4 | H92: =VLOOKUP(B92,#REF!,5,FALSE) -> #REF!
A93: Jaxon Siers | B93: 3.2.WRITE_SENTENCE_ABOUT_PICTURE | C93: Alphawrite | D93: 45741 | E93: 18 | F93: 14 | G93: =LEFT(B93) -> 3 | H93: =VLOOKUP(B93,#REF!,5,FALSE) -> #REF!
A94: Jaxon Siers | B94: 4.2.FRAGMENT_OR_SENTENCE | C94: Alphawrite | D94: 45741 | E94: 13 | F94: 9 | G94: =LEFT(B94) -> 4 | H94: =VLOOKUP(B94,#REF!,5,FALSE) -> #REF!
A95: Jaxon Siers | B95: 4.2.IDENTIFY_SENTENCE_TYPE | C95: Alphawrite | D95: 45741 | E95: 4 | F95: 4 | G95: =LEFT(B95) -> 4 | H95: =VLOOKUP(B95,#REF!,5,FALSE) -> #REF!
A96: Kai Sticker | B96: 4.2.TURN_PARAGRAPH_INTO_SPO | C96: Alphawrite | D96: 45741 | G96: =LEFT(B96) -> 4 | H96: =VLOOKUP(B96,#REF!,5,FALSE) -> #REF!
A97: Kai Sticker | B97: 4.2.WRITE_APPOSITIVES | C97: Alphawrite | D97: 45741 | E97: 2 | F97: 2 | G97: =LEFT(B97) -> 4 | H97: =VLOOKUP(B97,#REF!,5,FALSE) -> #REF!
A98: Kai Sticker | B98: 8.2.IDENTIFY_TS_AND_SEQUENCE_DETAILS | C98: Alphawrite | D98: 45741 | E98: 28 | F98: 24 | G98: =LEFT(B98) -> 8 | H98: =VLOOKUP(B98,#REF!,5,FALSE) -> #REF!
A99: Lavender Marrero | B99: 4.2.CHANGE_SENTENCE_TYPE | C99: Alphawrite | D99: 45741 | E99: 14 | F99: 4 | G99: =LEFT(B99) -> 4 | H99: =VLOOKUP(B99,#REF!,5,FALSE) -> #REF!
A100: Lily Gray | B100: 5.2.FRAGMENT_OR_SENTENCE | C100: Alphawrite | D100: 45741 | E100: 6 | F100: 2 | G100: =LEFT(B100) -> 5 | H100: =VLOOKUP(B100,#REF!,5,FALSE) -> #REF!
...

Sheet student-list-vs-mastered-lesson
A1: =IFERROR(__xludf.DUMMYFUNCTION("importrange(""https://docs.google.com/spreadsheets/d/1wBLO22hSTrKfDDXCrHIEZ1WCYIgyc-J2krKizrpx500/edit?gid=0#gid=0"",""Master!P:Q"")"),"Full Name") -> Full Name | B1: =IFERROR(__xludf.DUMMYFUNCTION("""COMPUTED_VALUE"""),"Level") -> Level | C1: Mastered a Lesson? | D1: Lessons Mastered
A2: =IFERROR(__xludf.DUMMYFUNCTION("""COMPUTED_VALUE"""),"Atlas Kloiber") -> Atlas Kloiber | B2: =IFERROR(__xludf.DUMMYFUNCTION("""COMPUTED_VALUE"""),"L2") -> L2 | C2: =IF(D2>0,"Yes","No") -> No | D2: 0
A3: =IFERROR(__xludf.DUMMYFUNCTION("""COMPUTED_VALUE"""),"Scotty Noel") -> Scotty Noel | B3: =IFERROR(__xludf.DUMMYFUNCTION("""COMPUTED_VALUE"""),"L2") -> L2 | C3: =IF(D3>0,"Yes","No") -> No | D3: 0
A4: =IFERROR(__xludf.DUMMYFUNCTION("""COMPUTED_VALUE"""),"Gray Duffy") -> Gray Duffy | B4: =IFERROR(__xludf.DUMMYFUNCTION("""COMPUTED_VALUE"""),"L2") -> L2 | C4: =IF(D4>0,"Yes","No") -> No | D4: 0
A5: =IFERROR(__xludf.DUMMYFUNCTION("""COMPUTED_VALUE"""),"Knox Martin Wheeler") -> Knox Martin Wheeler | B5: =IFERROR(__xludf.DUMMYFUNCTION("""COMPUTED_VALUE"""),"L2") -> L2 | C5: =IF(D5>0,"Yes","No") -> No | D5: 0
A6: =IFERROR(__xludf.DUMMYFUNCTION("""COMPUTED_VALUE"""),"Roman-Parker Davis") -> Roman-Parker Davis | B6: =IFERROR(__xludf.DUMMYFUNCTION("""COMPUTED_VALUE"""),"L2") -> L2 | C6: =IF(D6>0,"Yes","No") -> No | D6: 0
A7: =IFERROR(__xludf.DUMMYFUNCTION("""COMPUTED_VALUE"""),"Amelia Catherine Lucas") -> Amelia Catherine Lucas | B7: =IFERROR(__xludf.DUMMYFUNCTION("""COMPUTED_VALUE"""),"MS") -> MS | C7: =IF(D7>0,"Yes","No") -> No | D7: 0
A8: =IFERROR(__xludf.DUMMYFUNCTION("""COMPUTED_VALUE"""),"Joanna Victorian") -> Joanna Victorian | B8: =IFERROR(__xludf.DUMMYFUNCTION("""COMPUTED_VALUE"""),"L2") -> L2 | C8: =IF(D8>0,"Yes","No") -> No | D8: 0
A9: =IFERROR(__xludf.DUMMYFUNCTION("""COMPUTED_VALUE"""),"Tatiana Lynn Carrion") -> Tatiana Lynn Carrion | B9: =IFERROR(__xludf.DUMMYFUNCTION("""COMPUTED_VALUE"""),"MS") -> MS | C9: =IF(D9>0,"Yes","No") -> No | D9: 0
A10: =IFERROR(__xludf.DUMMYFUNCTION("""COMPUTED_VALUE"""),"Alannah Brie Carrion") -> Alannah Brie Carrion | B10: =IFERROR(__xludf.DUMMYFUNCTION("""COMPUTED_VALUE"""),"L2") -> L2 | C10: =IF(D10>0,"Yes","No") -> No | D10: 0
A11: =IFERROR(__xludf.DUMMYFUNCTION("""COMPUTED_VALUE"""),"Diana Kostov") -> Diana Kostov | B11: =IFERROR(__xludf.DUMMYFUNCTION("""COMPUTED_VALUE"""),"L2") -> L2 | C11: =IF(D11>0,"Yes","No") -> No | D11: 0
A12: =IFERROR(__xludf.DUMMYFUNCTION("""COMPUTED_VALUE"""),"Shepherd Rogers Mora") -> Shepherd Rogers Mora | B12: =IFERROR(__xludf.DUMMYFUNCTION("""COMPUTED_VALUE"""),"L2") -> L2 | C12: =IF(D12>0,"Yes","No") -> No | D12: 0
A13: =IFERROR(__xludf.DUMMYFUNCTION("""COMPUTED_VALUE"""),"Airi Elliott") -> Airi Elliott | B13: =IFERROR(__xludf.DUMMYFUNCTION("""COMPUTED_VALUE"""),"L2") -> L2 | C13: =IF(D13>0,"Yes","No") -> No | D13: 0
A14: =IFERROR(__xludf.DUMMYFUNCTION("""COMPUTED_VALUE"""),"Alexander Wiebeck") -> Alexander Wiebeck | B14: =IFERROR(__xludf.DUMMYFUNCTION("""COMPUTED_VALUE"""),"L1") -> L1 | C14: =IF(D14>0,"Yes","No") -> No | D14: 0
A15: =IFERROR(__xludf.DUMMYFUNCTION("""COMPUTED_VALUE"""),"Lenora Lovell") -> Lenora Lovell | B15: =IFERROR(__xludf.DUMMYFUNCTION("""COMPUTED_VALUE"""),"L2") -> L2 | C15: =IF(D15>0,"Yes","No") -> No | D15: 0
A16: =IFERROR(__xludf.DUMMYFUNCTION("""COMPUTED_VALUE"""),"Jordan Boyer") -> Jordan Boyer | B16: =IFERROR(__xludf.DUMMYFUNCTION("""COMPUTED_VALUE"""),"L2") -> L2 | C16: =IF(D16>0,"Yes","No") -> No | D16: 0
A17: =IFERROR(__xludf.DUMMYFUNCTION("""COMPUTED_VALUE"""),"Alex Boyer") -> Alex Boyer | B17: =IFERROR(__xludf.DUMMYFUNCTION("""COMPUTED_VALUE"""),"L2") -> L2 | C17: =IF(D17>0,"Yes","No") -> No | D17: 0
A18: =IFERROR(__xludf.DUMMYFUNCTION("""COMPUTED_VALUE"""),"Kal Goodman") -> Kal Goodman | B18: =IFERROR(__xludf.DUMMYFUNCTION("""COMPUTED_VALUE"""),"LL") -> LL | C18: =IF(D18>0,"Yes","No") -> No | D18: 0
A19: =IFERROR(__xludf.DUMMYFUNCTION("""COMPUTED_VALUE"""),"Quinn Kirby") -> Quinn Kirby | B19: =IFERROR(__xludf.DUMMYFUNCTION("""COMPUTED_VALUE"""),"L2") -> L2 | C19: =IF(D19>0,"Yes","No") -> No | D19: 0
A20: =IFERROR(__xludf.DUMMYFUNCTION("""COMPUTED_VALUE"""),"Vera Carver") -> Vera Carver | B20: =IFERROR(__xludf.DUMMYFUNCTION("""COMPUTED_VALUE"""),"MS") -> MS | C20: =IF(D20>0,"Yes","No") -> No | D20: 0
A21: =IFERROR(__xludf.DUMMYFUNCTION("""COMPUTED_VALUE"""),"Alexander Schutt") -> Alexander Schutt | B21: =IFERROR(__xludf.DUMMYFUNCTION("""COMPUTED_VALUE"""),"L1") -> L1 | C21: =IF(D21>0,"Yes","No") -> No | D21: 0
A22: =IFERROR(__xludf.DUMMYFUNCTION("""COMPUTED_VALUE"""),"Joy Odunowo") -> Joy Odunowo | B22: =IFERROR(__xludf.DUMMYFUNCTION("""COMPUTED_VALUE"""),"MS") -> MS | C22: =IF(D22>0,"Yes","No") -> No | D22: 0
A23: =IFERROR(__xludf.DUMMYFUNCTION("""COMPUTED_VALUE"""),"Collin Keith") -> Collin Keith | B23: =IFERROR(__xludf.DUMMYFUNCTION("""COMPUTED_VALUE"""),"L2") -> L2 | C23: =IF(D23>0,"Yes","No") -> No | D23: 0
A24: =IFERROR(__xludf.DUMMYFUNCTION("""COMPUTED_VALUE"""),"Jameson Keith") -> Jameson Keith | B24: =IFERROR(__xludf.DUMMYFUNCTION("""COMPUTED_VALUE"""),"L1") -> L1 | C24: =IF(D24>0,"Yes","No") -> No | D24: 0
A25: =IFERROR(__xludf.DUMMYFUNCTION("""COMPUTED_VALUE"""),"Emma Mercer") -> Emma Mercer | B25: =IFERROR(__xludf.DUMMYFUNCTION("""COMPUTED_VALUE"""),"L1") -> L1 | C25: =IF(D25>0,"Yes","No") -> No | D25: 0
A26: =IFERROR(__xludf.DUMMYFUNCTION("""COMPUTED_VALUE"""),"Baltasar Andia") -> Baltasar Andia | B26: =IFERROR(__xludf.DUMMYFUNCTION("""COMPUTED_VALUE"""),"L2") -> L2 | C26: =IF(D26>0,"Yes","No") -> No | D26: 0
A27: =IFERROR(__xludf.DUMMYFUNCTION("""COMPUTED_VALUE"""),"Taysen Stoker") -> Taysen Stoker | B27: =IFERROR(__xludf.DUMMYFUNCTION("""COMPUTED_VALUE"""),"MS") -> MS | C27: =IF(D27>0,"Yes","No") -> No | D27: 0
A28: =IFERROR(__xludf.DUMMYFUNCTION("""COMPUTED_VALUE"""),"Sullavan Sutton") -> Sullavan Sutton | B28: =IFERROR(__xludf.DUMMYFUNCTION("""COMPUTED_VALUE"""),"MS") -> MS | C28: =IF(D28>0,"Yes","No") -> No | D28: 0
A29: =IFERROR(__xludf.DUMMYFUNCTION("""COMPUTED_VALUE"""),"Tanner Stoker") -> Tanner Stoker | B29: =IFERROR(__xludf.DUMMYFUNCTION("""COMPUTED_VALUE"""),"L2") -> L2 | C29: =IF(D29>0,"Yes","No") -> No | D29: 0
A30: =IFERROR(__xludf.DUMMYFUNCTION("""COMPUTED_VALUE"""),"Sawyer Sutton") -> Sawyer Sutton | B30: =IFERROR(__xludf.DUMMYFUNCTION("""COMPUTED_VALUE"""),"L2") -> L2 | C30: =IF(D30>0,"Yes","No") -> No | D30: 0
A31: =IFERROR(__xludf.DUMMYFUNCTION("""COMPUTED_VALUE"""),"Vaughn Stoker") -> Vaughn Stoker | B31: =IFERROR(__xludf.DUMMYFUNCTION("""COMPUTED_VALUE"""),"L1") -> L1 | C31: =IF(D31>0,"Yes","No") -> No | D31: 0
A32: =IFERROR(__xludf.DUMMYFUNCTION("""COMPUTED_VALUE"""),"Truett Sutton") -> Truett Sutton | B32: =IFERROR(__xludf.DUMMYFUNCTION("""COMPUTED_VALUE"""),"L1") -> L1 | C32: =IF(D32>0,"Yes","No") -> No | D32: 0
A33: =IFERROR(__xludf.DUMMYFUNCTION("""COMPUTED_VALUE"""),"Owen Lombard") -> Owen Lombard | B33: =IFERROR(__xludf.DUMMYFUNCTION("""COMPUTED_VALUE"""),"L2") -> L2 | C33: =IF(D33>0,"Yes","No") -> No | D33: 0
A34: =IFERROR(__xludf.DUMMYFUNCTION("""COMPUTED_VALUE"""),"Emma Ibarra") -> Emma Ibarra | B34: =IFERROR(__xludf.DUMMYFUNCTION("""COMPUTED_VALUE"""),"L1") -> L1 | C34: =IF(D34>0,"Yes","No") -> No | D34: 0
A35: =IFERROR(__xludf.DUMMYFUNCTION("""COMPUTED_VALUE"""),"Charles Scoma Johnson") -> Charles Scoma Johnson | B35: =IFERROR(__xludf.DUMMYFUNCTION("""COMPUTED_VALUE"""),"L2") -> L2 | C35: =IF(D35>0,"Yes","No") -> No | D35: 0
A36: =IFERROR(__xludf.DUMMYFUNCTION("""COMPUTED_VALUE"""),"Remi Dustin") -> Remi Dustin | B36: =IFERROR(__xludf.DUMMYFUNCTION("""COMPUTED_VALUE"""),"MS") -> MS | C36: =IF(D36>0,"Yes","No") -> No | D36: 0
A37: =IFERROR(__xludf.DUMMYFUNCTION("""COMPUTED_VALUE"""),"Reece Dustin") -> Reece Dustin | B37: =IFERROR(__xludf.DUMMYFUNCTION("""COMPUTED_VALUE"""),"MS") -> MS | C37: =IF(D37>0,"Yes","No") -> No | D37: 0
A38: =IFERROR(__xludf.DUMMYFUNCTION("""COMPUTED_VALUE"""),"L K") -> L K | B38: =IFERROR(__xludf.DUMMYFUNCTION("""COMPUTED_VALUE"""),"MS") -> MS | C38: =IF(D38>0,"Yes","No") -> No | D38: 0
A39: =IFERROR(__xludf.DUMMYFUNCTION("""COMPUTED_VALUE"""),"adria fuchs") -> adria fuchs | B39: =IFERROR(__xludf.DUMMYFUNCTION("""COMPUTED_VALUE"""),"L1") -> L1 | C39: =IF(D39>0,"Yes","No") -> No | D39: 0
A40: =IFERROR(__xludf.DUMMYFUNCTION("""COMPUTED_VALUE"""),"ari fuchs") -> ari fuchs | B40: =IFERROR(__xludf.DUMMYFUNCTION("""COMPUTED_VALUE"""),"MS") -> MS | C40: =IF(D40>0,"Yes","No") -> No | D40: 0
A41: =IFERROR(__xludf.DUMMYFUNCTION("""COMPUTED_VALUE"""),"Linley Kunz") -> Linley Kunz | B41: =IFERROR(__xludf.DUMMYFUNCTION("""COMPUTED_VALUE"""),"L2") -> L2 | C41: =IF(D41>0,"Yes","No") -> No | D41: 0
A42: =IFERROR(__xludf.DUMMYFUNCTION("""COMPUTED_VALUE"""),"Alea Adams") -> Alea Adams | B42: =IFERROR(__xludf.DUMMYFUNCTION("""COMPUTED_VALUE"""),"L2") -> L2 | C42: =IF(D42>0,"Yes","No") -> No | D42: 0
A43: =IFERROR(__xludf.DUMMYFUNCTION("""COMPUTED_VALUE"""),"Aubree Adams") -> Aubree Adams | B43: =IFERROR(__xludf.DUMMYFUNCTION("""COMPUTED_VALUE"""),"MS") -> MS | C43: =IF(D43>0,"Yes","No") -> No | D43: 0
A44: =IFERROR(__xludf.DUMMYFUNCTION("""COMPUTED_VALUE"""),"Griffin Roberts") -> Griffin Roberts | B44: =IFERROR(__xludf.DUMMYFUNCTION("""COMPUTED_VALUE"""),"HS") -> HS | C44: =IF(D44>0,"Yes","No") -> No | D44: 0
A45: =IFERROR(__xludf.DUMMYFUNCTION("""COMPUTED_VALUE"""),"Piper Roberts") -> Piper Roberts | B45: =IFERROR(__xludf.DUMMYFUNCTION("""COMPUTED_VALUE"""),"MS") -> MS | C45: =IF(D45>0,"Yes","No") -> No | D45: 0
A46: =IFERROR(__xludf.DUMMYFUNCTION("""COMPUTED_VALUE"""),"Parker Heyd") -> Parker Heyd | B46: =IFERROR(__xludf.DUMMYFUNCTION("""COMPUTED_VALUE"""),"L2") -> L2 | C46: =IF(D46>0,"Yes","No") -> No | D46: 0
A47: =IFERROR(__xludf.DUMMYFUNCTION("""COMPUTED_VALUE"""),"Gregory Lukashin") -> Gregory Lukashin | B47: =IFERROR(__xludf.DUMMYFUNCTION("""COMPUTED_VALUE"""),"MS") -> MS | C47: =IF(D47>0,"Yes","No") -> No | D47: 0
A48: =IFERROR(__xludf.DUMMYFUNCTION("""COMPUTED_VALUE"""),"Anna Smith") -> Anna Smith | B48: =IFERROR(__xludf.DUMMYFUNCTION("""COMPUTED_VALUE"""),"MS") -> MS | C48: =IF(D48>0,"Yes","No") -> No | D48: 0
A49: =IFERROR(__xludf.DUMMYFUNCTION("""COMPUTED_VALUE"""),"Claire Smith") -> Claire Smith | B49: =IFERROR(__xludf.DUMMYFUNCTION("""COMPUTED_VALUE"""),"L1") -> L1 | C49: =IF(D49>0,"Yes","No") -> No | D49: 0
A50: =IFERROR(__xludf.DUMMYFUNCTION("""COMPUTED_VALUE"""),"Reagan Mickens") -> Reagan Mickens | B50: =IFERROR(__xludf.DUMMYFUNCTION("""COMPUTED_VALUE"""),"MS") -> MS | C50: =IF(D50>0,"Yes","No") -> No | D50: 0
A51: =IFERROR(__xludf.DUMMYFUNCTION("""COMPUTED_VALUE"""),"Kennedy Mickens") -> Kennedy Mickens | B51: =IFERROR(__xludf.DUMMYFUNCTION("""COMPUTED_VALUE"""),"L2") -> L2 | C51: =IF(D51>0,"Yes","No") -> No | D51: 0
A52: =IFERROR(__xludf.DUMMYFUNCTION("""COMPUTED_VALUE"""),"Juliette Price") -> Juliette Price | B52: =IFERROR(__xludf.DUMMYFUNCTION("""COMPUTED_VALUE"""),"MS") -> MS | C52: =IF(D52>0,"Yes","No") -> No | D52: 0
A53: =IFERROR(__xludf.DUMMYFUNCTION("""COMPUTED_VALUE"""),"Tanner Lohse") -> Tanner Lohse | B53: =IFERROR(__xludf.DUMMYFUNCTION("""COMPUTED_VALUE"""),"MS") -> MS | C53: =IF(D53>0,"Yes","No") -> No | D53: 0
A54: =IFERROR(__xludf.DUMMYFUNCTION("""COMPUTED_VALUE"""),"Akalya Lohse") -> Akalya Lohse | B54: =IFERROR(__xludf.DUMMYFUNCTION("""COMPUTED_VALUE"""),"L2") -> L2 | C54: =IF(D54>0,"Yes","No") -> No | D54: 0
A55: =IFERROR(__xludf.DUMMYFUNCTION("""COMPUTED_VALUE"""),"Makari Lohse") -> Makari Lohse | B55: =IFERROR(__xludf.DUMMYFUNCTION("""COMPUTED_VALUE"""),"LL") -> LL | C55: =IF(D55>0,"Yes","No") -> No | D55: 0
A56: =IFERROR(__xludf.DUMMYFUNCTION("""COMPUTED_VALUE"""),"Connor Cheung") -> Connor Cheung | B56: =IFERROR(__xludf.DUMMYFUNCTION("""COMPUTED_VALUE"""),"L2") -> L2 | C56: =IF(D56>0,"Yes","No") -> No | D56: 0
A57: =IFERROR(__xludf.DUMMYFUNCTION("""COMPUTED_VALUE"""),"Maddox Cheung") -> Maddox Cheung | B57: =IFERROR(__xludf.DUMMYFUNCTION("""COMPUTED_VALUE"""),"L2") -> L2 | C57: =IF(D57>0,"Yes","No") -> No | D57: 0
A58: =IFERROR(__xludf.DUMMYFUNCTION("""COMPUTED_VALUE"""),"Sophia Schmid") -> Sophia Schmid | B58: =IFERROR(__xludf.DUMMYFUNCTION("""COMPUTED_VALUE"""),"L1") -> L1 | C58: =IF(D58>0,"Yes","No") -> No | D58: 0
A59: =IFERROR(__xludf.DUMMYFUNCTION("""COMPUTED_VALUE"""),"Bob Schmid") -> Bob Schmid | B59: =IFERROR(__xludf.DUMMYFUNCTION("""COMPUTED_VALUE"""),"L1") -> L1 | C59: =IF(D59>0,"Yes","No") -> No | D59: 0
A60: =IFERROR(__xludf.DUMMYFUNCTION("""COMPUTED_VALUE"""),"Bristol Bates") -> Bristol Bates | B60: =IFERROR(__xludf.DUMMYFUNCTION("""COMPUTED_VALUE"""),"MS") -> MS | C60: =IF(D60>0,"Yes","No") -> No | D60: 0
A61: =IFERROR(__xludf.DUMMYFUNCTION("""COMPUTED_VALUE"""),"Zach B") -> Zach B | B61: =IFERROR(__xludf.DUMMYFUNCTION("""COMPUTED_VALUE"""),"L1") -> L1 | C61: =IF(D61>0,"Yes","No") -> No | D61: 0
A62: =IFERROR(__xludf.DUMMYFUNCTION("""COMPUTED_VALUE"""),"Greyson Duncombe") -> Greyson Duncombe | B62: =IFERROR(__xludf.DUMMYFUNCTION("""COMPUTED_VALUE"""),"L1") -> L1 | C62: =IF(D62>0,"Yes","No") -> No | D62: 0
A63: =IFERROR(__xludf.DUMMYFUNCTION("""COMPUTED_VALUE"""),"Tucker Duncombe") -> Tucker Duncombe | B63: =IFERROR(__xludf.DUMMYFUNCTION("""COMPUTED_VALUE"""),"L2") -> L2 | C63: =IF(D63>0,"Yes","No") -> No | D63: 0
A64: =IFERROR(__xludf.DUMMYFUNCTION("""COMPUTED_VALUE"""),"Manah Jembar Membumi") -> Manah Jembar Membumi | B64: =IFERROR(__xludf.DUMMYFUNCTION("""COMPUTED_VALUE"""),"L2") -> L2 | C64: =IF(D64>0,"Yes","No") -> No | D64: 0
A65: =IFERROR(__xludf.DUMMYFUNCTION("""COMPUTED_VALUE"""),"Luke Vine") -> Luke Vine | B65: =IFERROR(__xludf.DUMMYFUNCTION("""COMPUTED_VALUE"""),"MS") -> MS | C65: =IF(D65>0,"Yes","No") -> No | D65: 0
A66: =IFERROR(__xludf.DUMMYFUNCTION("""COMPUTED_VALUE"""),"Prayan Vine") -> Prayan Vine | B66: =IFERROR(__xludf.DUMMYFUNCTION("""COMPUTED_VALUE"""),"L2") -> L2 | C66: =IF(D66>0,"Yes","No") -> No | D66: 0
A67: =IFERROR(__xludf.DUMMYFUNCTION("""COMPUTED_VALUE"""),"Aaron Vine") -> Aaron Vine | B67: =IFERROR(__xludf.DUMMYFUNCTION("""COMPUTED_VALUE"""),"LL") -> LL | C67: =IF(D67>0,"Yes","No") -> No | D67: 0
A68: =IFERROR(__xludf.DUMMYFUNCTION("""COMPUTED_VALUE"""),"Daniel Ham") -> Daniel Ham | B68: =IFERROR(__xludf.DUMMYFUNCTION("""COMPUTED_VALUE"""),"L1") -> L1 | C68: =IF(D68>0,"Yes","No") -> No | D68: 0
A69: =IFERROR(__xludf.DUMMYFUNCTION("""COMPUTED_VALUE"""),"Danier H") -> Danier H | B69: =IFERROR(__xludf.DUMMYFUNCTION("""COMPUTED_VALUE"""),"L1") -> L1 | C69: =IF(D69>0,"Yes","No") -> No | D69: 0
A70: =IFERROR(__xludf.DUMMYFUNCTION("""COMPUTED_VALUE"""),"Sofia Seretny-Mharakurwa") -> Sofia Seretny-Mharakurwa | B70: =IFERROR(__xludf.DUMMYFUNCTION("""COMPUTED_VALUE"""),"L2") -> L2 | C70: =IF(D70>0,"Yes","No") -> No | D70: 0
A71: =IFERROR(__xludf.DUMMYFUNCTION("""COMPUTED_VALUE"""),"Grey Grassadonia") -> Grey Grassadonia | B71: =IFERROR(__xludf.DUMMYFUNCTION("""COMPUTED_VALUE"""),"L1") -> L1 | C71: =IF(D71>0,"Yes","No") -> No | D71: 0
A72: =IFERROR(__xludf.DUMMYFUNCTION("""COMPUTED_VALUE"""),"Marco Wozniak") -> Marco Wozniak | B72: =IFERROR(__xludf.DUMMYFUNCTION("""COMPUTED_VALUE"""),"L2") -> L2 | C72: =IF(D72>0,"Yes","No") -> No | D72: 0
A73: =IFERROR(__xludf.DUMMYFUNCTION("""COMPUTED_VALUE"""),"Rose Tindall") -> Rose Tindall | B73: =IFERROR(__xludf.DUMMYFUNCTION("""COMPUTED_VALUE"""),"L1") -> L1 | C73: =IF(D73>0,"Yes","No") -> No | D73: 0
A74: =IFERROR(__xludf.DUMMYFUNCTION("""COMPUTED_VALUE"""),"Kai Wozniak") -> Kai Wozniak | B74: =IFERROR(__xludf.DUMMYFUNCTION("""COMPUTED_VALUE"""),"L1") -> L1 | C74: =IF(D74>0,"Yes","No") -> No | D74: 0
A75: =IFERROR(__xludf.DUMMYFUNCTION("""COMPUTED_VALUE"""),"Jack Tindall") -> Jack Tindall | B75: =IFERROR(__xludf.DUMMYFUNCTION("""COMPUTED_VALUE"""),"L1") -> L1 | C75: =IF(D75>0,"Yes","No") -> No | D75: 0
A76: =IFERROR(__xludf.DUMMYFUNCTION("""COMPUTED_VALUE"""),"Bobby Tafoya") -> Bobby Tafoya | B76: =IFERROR(__xludf.DUMMYFUNCTION("""COMPUTED_VALUE"""),"L2") -> L2 | C76: =IF(D76>0,"Yes","No") -> No | D76: 0
A77: =IFERROR(__xludf.DUMMYFUNCTION("""COMPUTED_VALUE"""),"Christian Sanguinetti") -> Christian Sanguinetti | B77: =IFERROR(__xludf.DUMMYFUNCTION("""COMPUTED_VALUE"""),"MS") -> MS | C77: =IF(D77>0,"Yes","No") -> No | D77: 0
A78: =IFERROR(__xludf.DUMMYFUNCTION("""COMPUTED_VALUE"""),"Mateo Rodriguez") -> Mateo Rodriguez | B78: =IFERROR(__xludf.DUMMYFUNCTION("""COMPUTED_VALUE"""),"LL") -> LL | C78: =IF(D78>0,"Yes","No") -> No | D78: 0
A79: =IFERROR(__xludf.DUMMYFUNCTION("""COMPUTED_VALUE"""),"Toby Vacek") -> Toby Vacek | B79: =IFERROR(__xludf.DUMMYFUNCTION("""COMPUTED_VALUE"""),"L2") -> L2 | C79: =IF(D79>0,"Yes","No") -> No | D79: 0
A80: =IFERROR(__xludf.DUMMYFUNCTION("""COMPUTED_VALUE"""),"Desmond Millard") -> Desmond Millard | B80: =IFERROR(__xludf.DUMMYFUNCTION("""COMPUTED_VALUE"""),"L2") -> L2 | C80: =IF(D80>0,"Yes","No") -> No | D80: 0
A81: =IFERROR(__xludf.DUMMYFUNCTION("""COMPUTED_VALUE"""),"George Gibbs") -> George Gibbs | B81: =IFERROR(__xludf.DUMMYFUNCTION("""COMPUTED_VALUE"""),"MS") -> MS | C81: =IF(D81>0,"Yes","No") -> No | D81: 0
A82: =IFERROR(__xludf.DUMMYFUNCTION("""COMPUTED_VALUE"""),"Matthew Mercille") -> Matthew Mercille | B82: =IFERROR(__xludf.DUMMYFUNCTION("""COMPUTED_VALUE"""),"L2") -> L2 | C82: =IF(D82>0,"Yes","No") -> No | D82: 0
A83: =IFERROR(__xludf.DUMMYFUNCTION("""COMPUTED_VALUE"""),"Peyton Romney") -> Peyton Romney | B83: =IFERROR(__xludf.DUMMYFUNCTION("""COMPUTED_VALUE"""),"L2") -> L2 | C83: =IF(D83>0,"Yes","No") -> No | D83: 0
A84: =IFERROR(__xludf.DUMMYFUNCTION("""COMPUTED_VALUE"""),"Preslyn Romney") -> Preslyn Romney | B84: =IFERROR(__xludf.DUMMYFUNCTION("""COMPUTED_VALUE"""),"L1") -> L1 | C84: =IF(D84>0,"Yes","No") -> No | D84: 0
A85: =IFERROR(__xludf.DUMMYFUNCTION("""COMPUTED_VALUE"""),"Bishop Max") -> Bishop Max | B85: =IFERROR(__xludf.DUMMYFUNCTION("""COMPUTED_VALUE"""),"MS") -> MS | C85: =IF(D85>0,"Yes","No") -> No | D85: 0
A86: =IFERROR(__xludf.DUMMYFUNCTION("""COMPUTED_VALUE"""),"Eliem Ross") -> Eliem Ross | B86: =IFERROR(__xludf.DUMMYFUNCTION("""COMPUTED_VALUE"""),"L1") -> L1 | C86: =IF(D86>0,"Yes","No") -> No | D86: 0
A87: =IFERROR(__xludf.DUMMYFUNCTION("""COMPUTED_VALUE"""),"Xehni Martin") -> Xehni Martin | B87: =IFERROR(__xludf.DUMMYFUNCTION("""COMPUTED_VALUE"""),"L1") -> L1 | C87: =IF(D87>0,"Yes","No") -> No | D87: 0
A88: =IFERROR(__xludf.DUMMYFUNCTION("""COMPUTED_VALUE"""),"Zack Hendricks") -> Zack Hendricks | B88: =IFERROR(__xludf.DUMMYFUNCTION("""COMPUTED_VALUE"""),"MS") -> MS | C88: =IF(D88>0,"Yes","No") -> No | D88: 0
A89: =IFERROR(__xludf.DUMMYFUNCTION("""COMPUTED_VALUE"""),"Evelyn Franck") -> Evelyn Franck | B89: =IFERROR(__xludf.DUMMYFUNCTION("""COMPUTED_VALUE"""),"L2") -> L2 | C89: =IF(D89>0,"Yes","No") -> No | D89: 0
A90: =IFERROR(__xludf.DUMMYFUNCTION("""COMPUTED_VALUE"""),"Isabella Baker") -> Isabella Baker | B90: =IFERROR(__xludf.DUMMYFUNCTION("""COMPUTED_VALUE"""),"MS") -> MS | C90: =IF(D90>0,"Yes","No") -> No | D90: 0
A91: =IFERROR(__xludf.DUMMYFUNCTION("""COMPUTED_VALUE"""),"Zoe Baker") -> Zoe Baker | B91: =IFERROR(__xludf.DUMMYFUNCTION("""COMPUTED_VALUE"""),"L2") -> L2 | C91: =IF(D91>0,"Yes","No") -> No | D91: 0
A92: =IFERROR(__xludf.DUMMYFUNCTION("""COMPUTED_VALUE"""),"McCoy Baker") -> McCoy Baker | B92: =IFERROR(__xludf.DUMMYFUNCTION("""COMPUTED_VALUE"""),"L1") -> L1 | C92: =IF(D92>0,"Yes","No") -> No | D92: 0
A93: =IFERROR(__xludf.DUMMYFUNCTION("""COMPUTED_VALUE"""),"Waverly Mitchell") -> Waverly Mitchell | B93: =IFERROR(__xludf.DUMMYFUNCTION("""COMPUTED_VALUE"""),"L2") -> L2 | C93: =IF(D93>0,"Yes","No") -> No | D93: 0
A94: =IFERROR(__xludf.DUMMYFUNCTION("""COMPUTED_VALUE"""),"William Mitchell") -> William Mitchell | B94: =IFERROR(__xludf.DUMMYFUNCTION("""COMPUTED_VALUE"""),"L1") -> L1 | C94: =IF(D94>0,"Yes","No") -> No | D94: 0
A95: =IFERROR(__xludf.DUMMYFUNCTION("""COMPUTED_VALUE"""),"Jesus Macias") -> Jesus Macias | B95: =IFERROR(__xludf.DUMMYFUNCTION("""COMPUTED_VALUE"""),"L1") -> L1 | C95: =IF(D95>0,"Yes","No") -> No | D95: 0
A96: =IFERROR(__xludf.DUMMYFUNCTION("""COMPUTED_VALUE"""),"Adrian Macias") -> Adrian Macias | B96: =IFERROR(__xludf.DUMMYFUNCTION("""COMPUTED_VALUE"""),"L1") -> L1 | C96: =IF(D96>0,"Yes","No") -> No | D96: 0
A97: =IFERROR(__xludf.DUMMYFUNCTION("""COMPUTED_VALUE"""),"Abigail Ramsey") -> Abigail Ramsey | B97: =IFERROR(__xludf.DUMMYFUNCTION("""COMPUTED_VALUE"""),"L1") -> L1 | C97: =IF(D97>0,"Yes","No") -> No | D97: 0
A98: =IFERROR(__xludf.DUMMYFUNCTION("""COMPUTED_VALUE"""),"Francesca Wallace") -> Francesca Wallace | B98: =IFERROR(__xludf.DUMMYFUNCTION("""COMPUTED_VALUE"""),"L1") -> L1 | C98: =IF(D98>0,"Yes","No") -> No | D98: 0
A99: =IFERROR(__xludf.DUMMYFUNCTION("""COMPUTED_VALUE"""),"Viaan Agrawal") -> Viaan Agrawal | B99: =IFERROR(__xludf.DUMMYFUNCTION("""COMPUTED_VALUE"""),"MS") -> MS | C99: =IF(D99>0,"Yes","No") -> No | D99: 0
A100: =IFERROR(__xludf.DUMMYFUNCTION("""COMPUTED_VALUE"""),"London Wallace") -> London Wallace | B100: =IFERROR(__xludf.DUMMYFUNCTION("""COMPUTED_VALUE"""),"MS") -> MS | C100: =IF(D100>0,"Yes","No") -> No | D100: 0
...

Sheet raw-20240814-20250309
A1: Level | B1: Student | C1: Date | D1: Subject | E1: App | F1: Course | G1: Anti-patterns | H1: Anti-pattern count | I1: Lessons mastered | J1: Essential Lessons Mastered | K1: Correct Questions | L1: Total Questions | M1: Accuracy | N1: Minutes
A2: L1 | B2: Logan Campbell | C2: 45723 | D2: Writing | E2: Alphawrite | H2: 0 | J2: 0 | N2: 0.029999999
A3: L1 | B3: Scotty Noel | C3: 45723 | D3: Writing | E3: Alphawrite | F3: Grade 4, Easy | G3: ANTI | Working on non-recommended skills | H3: 1 | I3: 0 | J3: 0 | K3: 16 | L3: 29 | M3: 0.55172414 | N3: 36.27
A4: L2 | B4: Blake Flores | C4: 45723 | D4: Writing | E4: Alphawrite | H4: 0 | J4: 0 | N4: 3.49
A5: L2 | B5: Connor Cason | C5: 45723 | D5: Writing | E5: Alphawrite | F5: Grade 3, Easy | G5: ANTI | Working on non-recommended skills | H5: 1 | I5: 0 | J5: 0 | K5: 6 | L5: 13 | M5: 0.46153846 | N5: 16.65
A6: L2 | B6: Ellen Meegan | C6: 45723 | D6: Writing | E6: Alphawrite | F6: Grade 5, Easy | G6: ANTI | Working on non-recommended skills | H6: 1 | I6: 0 | J6: 0 | K6: 2 | L6: 4 | M6: 0.5 | N6: 8.1899996
A7: L2 | B7: Kai Sticker | C7: 45723 | D7: Writing | E7: Alphawrite | F7: Grade 3, Medium | G7: ANTI | Working on non-recommended skills | H7: 1 | I7: 0 | J7: 0 | K7: 7 | L7: 7 | M7: 1 | N7: 3.9300001
A8: L2 | B8: Kai Sticker | C8: 45723 | D8: Writing | E8: Alphawrite | F8: Grade 4, Medium | G8: ANTI | Working on non-recommended skills | H8: 1 | I8: 0 | J8: 0 | K8: 0 | L8: 0 | N8: 0
A9: L2 | B9: Kai Sticker | C9: 45723 | D9: Writing | E9: Alphawrite | F9: Grade 5, Medium | G9: ANTI | Working on non-recommended skills | H9: 1 | I9: 0 | J9: 0 | K9: 0 | L9: 0 | N9: 0
A10: L2 | B10: Raegan Middleton | C10: 45723 | D10: Writing | E10: Alphawrite | H10: 0 | J10: 0 | N10: 0.02
A11: L2 | B11: Rocco Benetti | C11: 45723 | D11: Writing | E11: Alphawrite | F11: Grade 12, Medium | G11: ANTI | Working on non-recommended skills | H11: 1 | I11: 0 | J11: 0 | K11: 0 | L11: 2 | M11: 0 | N11: 18.6
A12: L2 | B12: Rocco Benetti | C12: 45723 | D12: Writing | E12: Alphawrite | F12: Grade 5, Easy | G12: ANTI | Working on non-recommended skills | H12: 1 | I12: 0 | J12: 0 | K12: 1 | L12: 1 | M12: 1 | N12: 0
A13: L2 | B13: Rocco Benetti | C13: 45723 | D13: Writing | E13: Alphawrite | F13: Grade 5, Hard | G13: ANTI | Working on non-recommended skills | H13: 1 | I13: 0 | J13: 0 | K13: 0 | L13: 1 | M13: 0 | N13: 0
A14: L2 | B14: Rocco Benetti | C14: 45723 | D14: Writing | E14: Alphawrite | F14: Grade 5, Medium | G14: ANTI | Working on non-recommended skills | H14: 1 | I14: 0 | J14: 0 | K14: 0 | L14: 1 | M14: 0 | N14: 0
A15: L1 | B15: Arjun Caberwal | C15: 45722 | D15: Writing | E15: Alphawrite | F15: Grade 4, Easy | H15: 0 | I15: 0 | J15: 0 | K15: 1 | L15: 3 | M15: 0.33333333 | N15: 3.55
A16: L1 | B16: Evelyn Gabler | C16: 45722 | D16: Writing | E16: Alphawrite | F16: Grade 4, Easy | H16: 0 | I16: 0 | J16: 0 | K16: 1 | L16: 3 | M16: 0.33333333 | N16: 15.07
A17: L1 | B17: Logan Campbell | C17: 45722 | D17: Writing | E17: Alphawrite | F17: Grade 4, Easy | H17: 0 | I17: 0 | J17: 0 | K17: 1 | L17: 1 | M17: 1 | N17: 4
A18: L1 | B18: Ramsey Levin | C18: 45722 | D18: Writing | E18: Alphawrite | F18: Grade 4, Easy | G18: ANTI | Working on non-recommended skills | H18: 1 | I18: 0 | J18: 0 | K18: 2 | L18: 2 | M18: 1 | N18: 9.29
A19: L1 | B19: Sarah Hunter | C19: 45722 | D19: Writing | E19: Alphawrite | F19: Grade 3, Easy | G19: POSI | Reading the question carefully before answering correctly | H19: 1 | I19: 0 | J19: 0 | K19: 11 | L19: 16 | M19: 0.6875 | N19: 15.52
A20: L2 | B20: Blake Flores | C20: 45722 | D20: Writing | E20: Alphawrite | F20: Grade 5, Easy | G20: ANTI | Working on non-recommended skills | H20: 1 | I20: 0 | J20: 0 | K20: 1 | L20: 4 | M20: 0.25 | N20: 7.8000002
A21: L2 | B21: Ellen Meegan | C21: 45722 | D21: Writing | E21: Alphawrite | F21: Grade 5, Easy | G21: ANTI | Working on non-recommended skills | H21: 1 | I21: 0 | J21: 0 | K21: 1 | L21: 10 | M21: 0.1 | N21: 13.19
A22: L2 | B22: Lavender Marrero | C22: 45722 | D22: Writing | E22: Alphawrite | F22: Grade 5, Easy | H22: 0 | I22: 0 | J22: 0 | K22: 0 | L22: 4 | M22: 0 | N22: 11.34
A23: L2 | B23: Lily Gray | C23: 45722 | D23: Writing | E23: Alphawrite | H23: 0 | J23: 0 | N23: 18.440001
A24: L2 | B24: Marcus Fuentes | C24: 45722 | D24: Writing | E24: Alphawrite | F24: Grade 3, Easy | H24: 0 | I24: 0 | J24: 0 | K24: 5 | L24: 7 | M24: 0.71428571 | N24: 13.61
A25: L2 | B25: Orion Campbell | C25: 45722 | D25: Writing | E25: Alphawrite | H25: 0 | J25: 0 | N25: 5.9000001
A26: L2 | B26: Raegan Middleton | C26: 45722 | D26: Writing | E26: Alphawrite | F26: Grade 3, Easy | H26: 0 | I26: 0 | J26: 0 | K26: 0 | L26: 9 | M26: 0 | N26: 16.129999
A27: L2 | B27: Rocco Benetti | C27: 45722 | D27: Writing | E27: Alphawrite | F27: Grade 12, Hard | G27: ANTI | Working on non-recommended skills | H27: 1 | I27: 0 | J27: 0 | K27: 0 | L27: 0 | N27: 0
A28: L2 | B28: Rocco Benetti | C28: 45722 | D28: Writing | E28: Alphawrite | F28: Grade 12, Medium | G28: ANTI | Working on non-recommended skills | H28: 1 | I28: 0 | J28: 0 | K28: 2 | L28: 3 | M28: 0.66666667 | N28: 0
A29: L2 | B29: Rocco Benetti | C29: 45722 | D29: Writing | E29: Alphawrite | F29: Grade 5, Easy | G29: ANTI | Working on non-recommended skills | H29: 1 | I29: 1 | J29: 0 | K29: 18 | L29: 25 | M29: 0.72 | N29: 27.049999
A30: L1 | B30: Arman Caberwal | C30: 45721 | D30: Writing | E30: Alphawrite | F30: Grade 4, Easy | G30: ANTI | Working on non-recommended skills | H30: 1 | I30: 0 | J30: 0 | K30: 7 | L30: 17 | M30: 0.41176471 | N30: 13.25
A31: L1 | B31: Brady York | C31: 45721 | D31: Writing | E31: Alphawrite | H31: 0 | J31: 0 | N31: 0.46000001
A32: L1 | B32: David Paul | C32: 45721 | D32: Writing | E32: Alphawrite | H32: 0 | J32: 0 | N32: 0.25
A33: L1 | B33: Jaxon Siers | C33: 45721 | D33: Writing | E33: Alphawrite | H33: 0 | J33: 0 | N33: 0.43000001
A34: L1 | B34: Marco Iorgulescu | C34: 45721 | D34: Writing | E34: Alphawrite | F34: Grade 3, Easy | H34: 0 | I34: 0 | J34: 0 | K34: 6 | L34: 8 | M34: 0.75 | N34: 13.11
A35: L1 | B35: Zane Rogers | C35: 45721 | D35: Writing | E35: Alphawrite | F35: Grade 4, Easy | H35: 0 | I35: 0 | J35: 0 | K35: 0 | L35: 0 | N35: 0
A36: L2 | B36: Archer Traff | C36: 45721 | D36: Writing | E36: Alphawrite | F36: Grade 5, Easy | H36: 0 | I36: 0 | J36: 0 | K36: 0 | L36: 0 | N36: 0.57999998
A37: L2 | B37: Blake Flores | C37: 45721 | D37: Writing | E37: Alphawrite | F37: Grade 5, Easy | H37: 0 | I37: 0 | J37: 0 | K37: 0 | L37: 1 | M37: 0 | N37: 3.2
A38: L2 | B38: Ellen Meegan | C38: 45721 | D38: Writing | E38: Alphawrite | F38: Grade 5, Easy | G38: ANTI | Working on non-recommended skills | H38: 1 | I38: 0 | J38: 0 | K38: 2 | L38: 4 | M38: 0.5 | N38: 8.7600002
A39: L2 | B39: Kai Sticker | C39: 45721 | D39: Writing | E39: Alphawrite | F39: Grade 12, Easy | G39: ANTI | Working on non-recommended skills | H39: 1 | I39: 0 | J39: 0 | K39: 0 | L39: 1 | M39: 0 | N39: 0
A40: L2 | B40: Kai Sticker | C40: 45721 | D40: Writing | E40: Alphawrite | F40: Grade 4, Hard | G40: ANTI | Working on non-recommended skills | H40: 1 | I40: 0 | J40: 0 | K40: 0 | L40: 1 | M40: 0 | N40: 0
A41: L2 | B41: Kai Sticker | C41: 45721 | D41: Writing | E41: Alphawrite | F41: Grade 5, Easy | G41: ANTI | Working on non-recommended skills | H41: 1 | I41: 0 | J41: 0 | K41: 16 | L41: 27 | M41: 0.59259259 | N41: 18.889999
A42: L2 | B42: Rocco Benetti | C42: 45721 | D42: Writing | E42: Alphawrite | F42: Grade 12, Easy | G42: ANTI | Working on non-recommended skills | H42: 1 | I42: 0 | J42: 0 | K42: 0 | L42: 0 | N42: 0
A43: L2 | B43: Rocco Benetti | C43: 45721 | D43: Writing | E43: Alphawrite | F43: Grade 12, Hard | G43: ANTI | Working on non-recommended skills | H43: 1 | I43: 0 | J43: 0 | K43: 0 | L43: 0 | N43: 0
A44: L2 | B44: Rocco Benetti | C44: 45721 | D44: Writing | E44: Alphawrite | F44: Grade 12, Medium | G44: ANTI | Working on non-recommended skills | H44: 1 | I44: 0 | J44: 0 | K44: 4 | L44: 11 | M44: 0.36363636 | N44: 24.42
A45: L2 | B45: Rocco Benetti | C45: 45721 | D45: Writing | E45: Alphawrite | F45: Grade 4, Easy | G45: ANTI | Working on non-recommended skills | H45: 1 | I45: 0 | J45: 0 | K45: 0 | L45: 1 | M45: 0 | N45: 0
A46: L1 | B46: Arjun Caberwal | C46: 45720 | D46: Writing | E46: Alphawrite | F46: Grade 4, Easy | G46: ANTI | Working on non-recommended skills | H46: 1 | I46: 0 | J46: 0 | K46: 1 | L46: 4 | M46: 0.25 | N46: 5.7600002
A47: L1 | B47: Arman Caberwal | C47: 45720 | D47: Writing | E47: Alphawrite | F47: Grade 4, Easy | G47: ANTI | Working on non-recommended skills | H47: 1 | I47: 1 | J47: 0 | K47: 24 | L47: 40 | M47: 0.6 | N47: 12.35
A48: L1 | B48: Elliott Howe | C48: 45720 | D48: Writing | E48: Alphawrite | H48: 0 | J48: 0 | N48: 1.3
A49: L1 | B49: Evelyn Gabler | C49: 45720 | D49: Writing | E49: Alphawrite | F49: Grade 4, Easy | H49: 0 | I49: 0 | J49: 0 | K49: 5 | L49: 9 | M49: 0.55555556 | N49: 6.9000001
A50: L1 | B50: Evelyn Gabler | C50: 45720 | D50: Writing | E50: Alphawrite | F50: Grade 5, Easy | H50: 0 | I50: 0 | J50: 0 | K50: 0 | L50: 0 | N50: 0
A51: L1 | B51: Hazel Salton | C51: 45720 | D51: Writing | E51: Alphawrite | F51: Grade 4, Easy | H51: 0 | I51: 0 | J51: 0 | K51: 15 | L51: 22 | M51: 0.68181818 | N51: 26.75
A52: L1 | B52: Logan Campbell | C52: 45720 | D52: Writing | E52: Alphawrite | F52: Grade 4, Easy | H52: 0 | I52: 0 | J52: 0 | K52: 1 | L52: 6 | M52: 0.16666667 | N52: 10.19
A53: L1 | B53: Ramsey Levin | C53: 45720 | D53: Writing | E53: Alphawrite | F53: Grade 4, Easy | H53: 0 | I53: 0 | J53: 0 | K53: 4 | L53: 5 | M53: 0.8 | N53: 5.5900002
A54: L1 | B54: Sarah Hunter | C54: 45720 | D54: Writing | E54: Alphawrite | F54: Grade 3, Easy | G54: ANTI | Working on non-recommended skills | H54: 1 | I54: 0 | J54: 0 | K54: 2 | L54: 4 | M54: 0.5 | N54: 4.9000001
A55: L2 | B55: Blake Flores | C55: 45720 | D55: Writing | E55: Alphawrite | F55: Grade 5, Easy | G55: ANTI | Working on non-recommended skills | H55: 1 | I55: 0 | J55: 0 | K55: 3 | L55: 8 | M55: 0.375 | N55: 9.3199997
A56: L2 | B56: Ellen Meegan | C56: 45720 | D56: Writing | E56: Alphawrite | F56: Grade 5, Easy | G56: ANTI | Working on non-recommended skills | H56: 1 | I56: 0 | J56: 0 | K56: 4 | L56: 6 | M56: 0.66666667 | N56: 12.35
A57: L2 | B57: Kai Sticker | C57: 45720 | D57: Writing | E57: Alphawrite | F57: Grade 4, Easy | G57: ANTI | Working on non-recommended skills | H57: 1 | I57: 0 | J57: 0 | K57: 8 | L57: 8 | M57: 1 | N57: 0
A58: L2 | B58: Kai Sticker | C58: 45720 | D58: Writing | E58: Alphawrite | F58: Grade 4, Medium | G58: ANTI | Working on non-recommended skills | H58: 1 | I58: 0 | J58: 0 | K58: 1 | L58: 8 | M58: 0.125 | N58: 10.12
A59: L2 | B59: Krish Bhakta | C59: 45720 | D59: Writing | E59: Alphawrite | F59: Grade 5, Easy | G59: ANTI | Working on non-recommended skills | H59: 1 | I59: 0 | J59: 0 | K59: 1 | L59: 3 | M59: 0.33333333 | N59: 1.79
A60: L2 | B60: Lavender Marrero | C60: 45720 | D60: Writing | E60: Alphawrite | F60: Grade 5, Easy | G60: ANTI | Working on non-recommended skills | H60: 1 | I60: 0 | J60: 0 | K60: 3 | L60: 5 | M60: 0.6 | N60: 6.5900002
A61: L2 | B61: Lily Gray | C61: 45720 | D61: Writing | E61: Alphawrite | F61: Grade 5, Easy | G61: ANTI | Working on non-recommended skills | H61: 1 | I61: 0 | J61: 0 | K61: 4 | L61: 8 | M61: 0.5 | N61: 7.0100002
A62: L2 | B62: Marcus Fuentes | C62: 45720 | D62: Writing | E62: Alphawrite | F62: Grade 3, Easy | G62: ANTI | Working on non-recommended skills | H62: 1 | I62: 0 | J62: 0 | K62: 9 | L62: 12 | M62: 0.75 | N62: 7.5300002
A63: L2 | B63: Orion Campbell | C63: 45720 | D63: Writing | E63: Alphawrite | H63: 0 | J63: 0 | N63: 8.6599998
A64: L2 | B64: Raegan Middleton | C64: 45720 | D64: Writing | E64: Alphawrite | F64: Grade 3, Easy | H64: 0 | I64: 0 | J64: 0 | K64: 0 | L64: 1 | M64: 0 | N64: 6.75
A65: L2 | B65: Rocco Benetti | C65: 45720 | D65: Writing | E65: Alphawrite | F65: Grade 12, Easy | G65: ANTI | Working on non-recommended skills | H65: 1 | I65: 1 | J65: 0 | K65: 34 | L65: 43 | M65: 0.79069767 | N65: 24.66
A66: L2 | B66: Rocco Benetti | C66: 45720 | D66: Writing | E66: Alphawrite | F66: Grade 3, Easy | G66: ANTI | Working on non-recommended skills | H66: 1 | I66: 0 | J66: 0 | K66: 0 | L66: 0 | N66: 0
A67: L2 | B67: Rocco Benetti | C67: 45720 | D67: Writing | E67: Alphawrite | F67: Grade 5, Easy | G67: ANTI | Working on non-recommended skills | H67: 1 | I67: 0 | J67: 0 | K67: 0 | L67: 1 | M67: 0 | N67: 0
A68: L3 | B68: Parker Pesek | C68: 45720 | D68: Writing | E68: Alphawrite | F68: Grade 5, Easy | G68: ANTI | Working on non-recommended skills,POSI | Reading the question carefully before answering correctly | H68: 2 | I68: 0 | J68: 0 | K68: 11 | L68: 21 | M68: 0.52380952 | N68: 20.629999
A69: L1 | B69: Alexander Wiebeck | C69: 45719 | D69: Writing | E69: Alphawrite | F69: Grade 3, Easy | H69: 0 | I69: 0 | J69: 0 | K69: 0 | L69: 2 | M69: 0 | N69: 6.9000001
A70: L2 | B70: Lavender Marrero | C70: 45719 | D70: Writing | E70: Alphawrite | F70: Grade 5, Easy | H70: 0 | I70: 0 | J70: 0 | K70: 0 | L70: 0 | N70: 0.80000001
A71: L2 | B71: Love Lalla-Pagan | C71: 45719 | D71: Writing | E71: Alphawrite | F71: Grade 5, Easy | G71: ANTI | Working on non-recommended skills | H71: 1 | I71: 0 | J71: 0 | K71: 0 | L71: 1 | M71: 0 | N71: 1.12
A72: L2 | B72: Marcus Fuentes | C72: 45719 | D72: Writing | E72: Alphawrite | H72: 0 | J72: 0 | N72: 2.8699999
A73: L2 | B73: Raegan Middleton | C73: 45719 | D73: Writing | E73: Alphawrite | H73: 0 | J73: 0 | N73: 2.3099999
A74: L2 | B74: Rocco Benetti | C74: 45719 | D74: Writing | E74: Alphawrite | H74: 0 | J74: 0 | N74: 0.67000002
A75: L1 | B75: Juan Diego Ortega | C75: 45718 | D75: Writing | E75: Alphawrite | H75: 0 | J75: 0 | N75: 0.17
A76: L1 | B76: Alexander Wiebeck | C76: 45716 | D76: Writing | E76: Alphawrite | H76: 0 | J76: 0 | N76: 0.72000003
A77: L1 | B77: Alexander Wiebeck | C77: 45715 | D77: Writing | E77: Alphawrite | F77: Grade 3, Easy | H77: 0 | I77: 0 | J77: 0 | K77: 1 | L77: 2 | M77: 0.5 | N77: 3.3699999
A78: L1 | B78: Alexander Wiebeck | C78: 45714 | D78: Writing | E78: Alphawrite | F78: Grade 3, Easy | H78: 0 | I78: 1 | J78: 0 | K78: 15 | L78: 19 | M78: 0.78947368 | N78: 12.03
A79: L1 | B79: Alexander Wiebeck | C79: 45713 | D79: Writing | E79: Alphawrite | F79: Grade 3, Easy | H79: 0 | I79: 0 | J79: 0 | K79: 5 | L79: 9 | M79: 0.55555556 | N79: 6.8699999
A80: L1 | B80: Scotty Noel | C80: 45712 | D80: Writing | E80: Alphawrite | F80: Grade 4, Easy | G80: ANTI | Working on non-recommended skills | H80: 1 | I80: 0 | J80: 0 | K80: 0 | L80: 2 | M80: 0 | N80: 3.4200001
A81: L1 | B81: Alexander Wiebeck | C81: 45711 | D81: Writing | E81: Alphawrite | F81: Grade 3, Easy | H81: 0 | I81: 0 | J81: 0 | K81: 0 | L81: 0 | N81: 2.26
A82: L1 | B82: Alexander Wiebeck | C82: 45709 | D82: Writing | E82: Alphawrite | F82: Grade 3, Easy | H82: 0 | I82: 0 | J82: 0 | K82: 0 | L82: 8 | M82: 0 | N82: 3.02
A83: L1 | B83: Ezel Perez Nellar | C83: 45709 | D83: Writing | E83: Alphawrite | H83: 0 | J83: 0 | N83: 0.07
A84: L2 | B84: Krish Bhakta | C84: 45709 | D84: Writing | E84: Alphawrite | F84: Grade 5, Easy | G84: ANTI | Working on non-recommended skills | H84: 1 | I84: 0 | J84: 0 | K84: 0 | L84: 4 | M84: 0 | N84: 6.0900002
A85: L2 | B85: Rania Caberwal | C85: 45709 | D85: Writing | E85: Alphawrite | F85: Grade 5, Hard | H85: 0 | I85: 0 | J85: 0 | K85: 0 | L85: 0 | N85: 2.9000001
A86: L3 | B86: Jaiden Bhakta | C86: 45709 | D86: Writing | E86: Alphawrite | H86: 0 | J86: 0 | N86: 0.44
A87: L1 | B87: Alex Lekic Brajovic | C87: 45708 | D87: Writing | E87: Alphawrite | F87: Grade 4, Easy | H87: 0 | I87: 0 | J87: 0 | K87: 5 | L87: 9 | M87: 0.55555556 | N87: 10.97
A88: L1 | B88: Alexander Wiebeck | C88: 45708 | D88: Writing | E88: Alphawrite | F88: Grade 3, Easy | G88: POSI | Reading the question carefully before answering correctly | H88: 1 | I88: 2 | J88: 0 | K88: 24 | L88: 25 | M88: 0.96 | N88: 4.3499999
A89: L1 | B89: Marshall Jensen | C89: 45708 | D89: Writing | E89: Alphawrite | F89: Grade 3, Easy | G89: ANTI | Working on non-recommended skills | H89: 1 | I89: 0 | J89: 0 | K89: 1 | L89: 3 | M89: 0.33333333 | N89: 3.46
A90: L1 | B90: Scotty Noel | C90: 45708 | D90: Writing | E90: Alphawrite | F90: Grade 4, Easy | H90: 0 | I90: 0 | J90: 0 | K90: 0 | L90: 0 | N90: 0.77999997
A91: L2 | B91: Ellen Meegan | C91: 45708 | D91: Writing | E91: Alphawrite | F91: Grade 5, Easy | G91: ANTI | Working on non-recommended skills | H91: 1 | I91: 0 | J91: 0 | K91: 1 | L91: 1 | M91: 1 | N91: 6.5500002
A92: L2 | B92: Lavender Marrero | C92: 45708 | D92: Writing | E92: Alphawrite | H92: 0 | J92: 0 | N92: 0.02
A93: L2 | B93: Rania Caberwal | C93: 45708 | D93: Writing | E93: Alphawrite | F93: Grade 5, Hard | G93: ANTI | Working on non-recommended skills | H93: 1 | I93: 0 | J93: 0 | K93: 0 | L93: 1 | M93: 0 | N93: 2.5599999
A94: L1 | B94: Alexander Wiebeck | C94: 45707 | D94: Writing | E94: Alphawrite | F94: Grade 3, Easy | G94: POSI | Reading the question carefully before answering correctly | H94: 1 | I94: 0 | J94: 0 | K94: 2 | L94: 8 | M94: 0.25 | N94: 33.459999
A95: L1 | B95: Logan Campbell | C95: 45707 | D95: Writing | E95: Alphawrite | F95: Grade 4, Easy | G95: ANTI | Working on non-recommended skills | H95: 1 | I95: 0 | J95: 0 | K95: 1 | L95: 4 | M95: 0.25 | N95: 17.360001
A96: L1 | B96: Ramsey Levin | C96: 45707 | D96: Writing | E96: Alphawrite | F96: Grade 4, Easy | H96: 0 | I96: 0 | J96: 0 | K96: 1 | L96: 2 | M96: 0.5 | N96: 18.959999
A97: L1 | B97: Sarah Hunter | C97: 45707 | D97: Writing | E97: Alphawrite | F97: Grade 3, Easy | H97: 0 | I97: 0 | J97: 0 | K97: 1 | L97: 3 | M97: 0.33333333 | N97: 0.12
A98: L2 | B98: Lavender Marrero | C98: 45707 | D98: Writing | E98: Alphawrite | F98: Grade 5, Easy | H98: 0 | I98: 0 | J98: 0 | K98: 1 | L98: 3 | M98: 0.33333333 | N98: 16.92
A99: L2 | B99: Lily Gray | C99: 45707 | D99: Writing | E99: Alphawrite | F99: Grade 5, Easy | H99: 0 | I99: 0 | J99: 0 | K99: 0 | L99: 1 | M99: 0 | N99: 19.16
A100: L2 | B100: Marcus Fuentes | C100: 45707 | D100: Writing | E100: Alphawrite | F100: Grade 3, Easy | H100: 0 | I100: 0 | J100: 0 | K100: 2 | L100: 2 | M100: 1 | N100: 10.12
...

Sheet add-20250310-26
A1: Level | B1: Student | C1: Date | D1: Subject | E1: App | F1: Course | G1: Anti-patterns | H1: Anti-pattern count | I1: Lessons mastered | J1: Essential Lessons Mastered | K1: Correct Questions | L1: Total Questions | M1: Accuracy | N1: Minutes | O1: Mastered at least 1 lesson? | P1: Spent time in the lesson? | Q1: Spent <30 min? | R1: Minutes per lesson mastered | U1: Average time taken to master 1 lesson
A2: L1 | B2: Alessandra Green | C2: 45742 | D2: Writing | E2: Alphawrite | F2: Grade 3, Easy | H2: 0 | I2: 1 | J2: 0 | K2: 30 | L2: 38 | M2: 0.78947368 | N2: 17.25 | O2: =IF(I2>0,"Yes","No") -> Yes | P2: =IF(N2>0,"Yes","No") -> Yes | Q2: =IF(N2<=30,"Yes","No") -> Yes | R2: =N2/I2 -> 17.25
A3: L1 | B3: Anaya Lenington | C3: 45742 | D3: Writing | E3: Alphawrite | H3: 0 | J3: 0 | N3: 0.02 | O3: =IF(I3>0,"Yes","No") -> No | P3: =IF(N3>0,"Yes","No") -> Yes | Q3: =IF(N3<=30,"Yes","No") -> Yes | R3: =N3/I3 -> #DIV/0!
A4: L1 | B4: Arjun Caberwal | C4: 45742 | D4: Writing | E4: Alphawrite | F4: Grade 4, Easy | H4: 0 | I4: 1 | J4: 0 | K4: 14 | L4: 20 | M4: 0.7 | N4: 7.77 | O4: =IF(I4>0,"Yes","No") -> Yes | P4: =IF(N4>0,"Yes","No") -> Yes | Q4: =IF(N4<=30,"Yes","No") -> Yes | R4: =N4/I4 -> 7.77
A5: L1 | B5: Arman Caberwal | C5: 45742 | D5: Writing | E5: Alphawrite | F5: Grade 4, Easy | H5: 0 | I5: 1 | J5: 0 | K5: 19 | L5: 19 | M5: 1 | N5: 12.51 | O5: =IF(I5>0,"Yes","No") -> Yes | P5: =IF(N5>0,"Yes","No") -> Yes | Q5: =IF(N5<=30,"Yes","No") -> Yes | R5: =N5/I5 -> 12.51
A6: L1 | B6: Brady York | C6: 45742 | D6: Writing | E6: Alphawrite | F6: Grade 3, Easy | H6: 0 | I6: 1 | J6: 0 | K6: 19 | L6: 27 | M6: 0.7037037 | N6: 12.46 | O6: =IF(I6>0,"Yes","No") -> Yes | P6: =IF(N6>0,"Yes","No") -> Yes | Q6: =IF(N6<=30,"Yes","No") -> Yes | R6: =N6/I6 -> 12.46
A7: L1 | B7: David Paul | C7: 45742 | D7: Writing | E7: Alphawrite | F7: Grade 3, Easy | H7: 0 | I7: 1 | J7: 0 | K7: 48 | L7: 77 | M7: 0.62337662 | N7: 49.119999 | O7: =IF(I7>0,"Yes","No") -> Yes | P7: =IF(N7>0,"Yes","No") -> Yes | Q7: =IF(N7<=30,"Yes","No") -> No | R7: =N7/I7 -> 49.119999
A8: L1 | B8: David Paul | C8: 45742 | D8: Writing | E8: Alphawrite | F8: Grade 4, Easy | H8: 0 | I8: 0 | J8: 0 | K8: 0 | L8: 2 | M8: 0 | N8: 0 | O8: =IF(I8>0,"Yes","No") -> No | P8: =IF(N8>0,"Yes","No") -> No | Q8: =IF(N8<=30,"Yes","No") -> Yes | R8: =N8/I8 -> #DIV/0!
A9: L1 | B9: Elaina Robertson | C9: 45742 | D9: Writing | E9: Alphawrite | F9: Grade 4, Easy | H9: 0 | I9: 1 | J9: 0 | K9: 12 | L9: 13 | M9: 0.92307692 | N9: 0 | O9: =IF(I9>0,"Yes","No") -> Yes | P9: =IF(N9>0,"Yes","No") -> No | Q9: =IF(N9<=30,"Yes","No") -> Yes | R9: =N9/I9 -> 0
A10: L1 | B10: Evelyn Gabler | C10: 45742 | D10: Writing | E10: Alphawrite | F10: Grade 4, Easy | H10: 0 | I10: 1 | J10: 0 | K10: 8 | L10: 8 | M10: 1 | N10: 8.0100002 | O10: =IF(I10>0,"Yes","No") -> Yes | P10: =IF(N10>0,"Yes","No") -> Yes | Q10: =IF(N10<=30,"Yes","No") -> Yes | R10: =N10/I10 -> 8.0100002
A11: L1 | B11: Evelyn Gabler | C11: 45742 | D11: Writing | E11: Alphawrite | F11: Grade 5, Easy | H11: 0 | I11: 0 | J11: 0 | K11: 0 | L11: 0 | N11: 0 | O11: =IF(I11>0,"Yes","No") -> No | P11: =IF(N11>0,"Yes","No") -> No | Q11: =IF(N11<=30,"Yes","No") -> Yes | R11: =N11/I11 -> #DIV/0!
A12: L1 | B12: Hazel Salton | C12: 45742 | D12: Writing | E12: Alphawrite | F12: Grade 3, Easy | H12: 0 | I12: 0 | J12: 0 | K12: 18 | L12: 26 | M12: 0.69230769 | N12: 11.88 | O12: =IF(I12>0,"Yes","No") -> No | P12: =IF(N12>0,"Yes","No") -> Yes | Q12: =IF(N12<=30,"Yes","No") -> Yes | R12: =N12/I12 -> #DIV/0! | Y12: Exclude instances of students spending >30 min (they may have left their laptops on without any action)
A13: L1 | B13: Hazel Salton | C13: 45742 | D13: Writing | E13: Alphawrite | F13: Grade 4, Easy | H13: 0 | I13: 0 | J13: 0 | K13: 0 | L13: 0 | N13: 0 | O13: =IF(I13>0,"Yes","No") -> No | P13: =IF(N13>0,"Yes","No") -> No | Q13: =IF(N13<=30,"Yes","No") -> Yes | R13: =N13/I13 -> #DIV/0!
A14: L1 | B14: Ian Mentgen | C14: 45742 | D14: Writing | E14: Alphawrite | F14: Grade 3, Easy | H14: 0 | I14: 1 | J14: 0 | K14: 14 | L14: 16 | M14: 0.875 | N14: 6.8000002 | O14: =IF(I14>0,"Yes","No") -> Yes | P14: =IF(N14>0,"Yes","No") -> Yes | Q14: =IF(N14<=30,"Yes","No") -> Yes | R14: =N14/I14 -> 6.8000002
A15: L1 | B15: Jaxon Siers | C15: 45742 | D15: Writing | E15: Alphawrite | F15: Grade 3, Easy | H15: 0 | I15: 2 | J15: 0 | K15: 36 | L15: 52 | M15: 0.69230769 | N15: 15.5 | O15: =IF(I15>0,"Yes","No") -> Yes | P15: =IF(N15>0,"Yes","No") -> Yes | Q15: =IF(N15<=30,"Yes","No") -> Yes | R15: =N15/I15 -> 7.75
A16: L1 | B16: Jaxon Siers | C16: 45742 | D16: Writing | E16: Alphawrite | F16: Grade 4, Easy | H16: 0 | I16: 0 | J16: 0 | K16: 0 | L16: 0 | N16: 0 | O16: =IF(I16>0,"Yes","No") -> No | P16: =IF(N16>0,"Yes","No") -> No | Q16: =IF(N16<=30,"Yes","No") -> Yes | R16: =N16/I16 -> #DIV/0!
A17: L1 | B17: Logan Campbell | C17: 45742 | D17: Writing | E17: Alphawrite | F17: Grade 4, Easy | H17: 0 | I17: 0 | J17: 0 | K17: 0 | L17: 0 | N17: 7.9299998 | O17: =IF(I17>0,"Yes","No") -> No | P17: =IF(N17>0,"Yes","No") -> Yes | Q17: =IF(N17<=30,"Yes","No") -> Yes | R17: =N17/I17 -> #DIV/0!
A18: L1 | B18: Max Vaughan | C18: 45742 | D18: Writing | E18: Alphawrite | F18: Grade 3, Easy | H18: 0 | I18: 1 | J18: 0 | K18: 12 | L18: 12 | M18: 1 | N18: 10.01 | O18: =IF(I18>0,"Yes","No") -> Yes | P18: =IF(N18>0,"Yes","No") -> Yes | Q18: =IF(N18<=30,"Yes","No") -> Yes | R18: =N18/I18 -> 10.01 | U18: Average accuracy for mastered lessons:
A19: L1 | B19: Omar Ibarra | C19: 45742 | D19: Writing | E19: Alphawrite | F19: Grade 4, Easy | H19: 0 | I19: 0 | J19: 0 | K19: 4 | L19: 10 | M19: 0.4 | N19: 9.5600004 | O19: =IF(I19>0,"Yes","No") -> No | P19: =IF(N19>0,"Yes","No") -> Yes | Q19: =IF(N19<=30,"Yes","No") -> Yes | R19: =N19/I19 -> #DIV/0!
A20: L1 | B20: Ramsey Levin | C20: 45742 | D20: Writing | E20: Alphawrite | F20: Grade 4, Easy | H20: 0 | I20: 0 | J20: 0 | K20: 2 | L20: 4 | M20: 0.5 | N20: 7.3600001 | O20: =IF(I20>0,"Yes","No") -> No | P20: =IF(N20>0,"Yes","No") -> Yes | Q20: =IF(N20<=30,"Yes","No") -> Yes | R20: =N20/I20 -> #DIV/0!
A21: L1 | B21: Sarah Hunter | C21: 45742 | D21: Writing | E21: Alphawrite | F21: Grade 3, Easy | H21: 0 | I21: 0 | J21: 0 | K21: 2 | L21: 4 | M21: 0.5 | N21: 3.78 | O21: =IF(I21>0,"Yes","No") -> No | P21: =IF(N21>0,"Yes","No") -> Yes | Q21: =IF(N21<=30,"Yes","No") -> Yes | R21: =N21/I21 -> #DIV/0!
A22: L1 | B22: Sophia Reicher | C22: 45742 | D22: Writing | E22: Alphawrite | F22: Grade 5, Easy | H22: 0 | I22: 0 | J22: 0 | K22: 4 | L22: 4 | M22: 1 | N22: 0 | O22: =IF(I22>0,"Yes","No") -> No | P22: =IF(N22>0,"Yes","No") -> No | Q22: =IF(N22<=30,"Yes","No") -> Yes | R22: =N22/I22 -> #DIV/0!
A23: L1 | B23: Tate Price | C23: 45742 | D23: Writing | E23: Alphawrite | F23: Grade 3, Easy | H23: 0 | I23: 0 | J23: 0 | K23: 0 | L23: 0 | N23: 0 | O23: =IF(I23>0,"Yes","No") -> No | P23: =IF(N23>0,"Yes","No") -> No | Q23: =IF(N23<=30,"Yes","No") -> Yes | R23: =N23/I23 -> #DIV/0!
A24: L1 | B24: Tate Price | C24: 45742 | D24: Writing | E24: Alphawrite | F24: Grade 5, Easy | H24: 0 | I24: 0 | J24: 0 | K24: 19 | L24: 29 | M24: 0.65517241 | N24: 7.23 | O24: =IF(I24>0,"Yes","No") -> No | P24: =IF(N24>0,"Yes","No") -> Yes | Q24: =IF(N24<=30,"Yes","No") -> Yes | R24: =N24/I24 -> #DIV/0!
A25: L2 | B25: Blake Flores | C25: 45742 | D25: Writing | E25: Alphawrite | F25: Grade 5, Easy | H25: 0 | I25: 0 | J25: 0 | K25: 2 | L25: 6 | M25: 0.33333333 | N25: 8.4499998 | O25: =IF(I25>0,"Yes","No") -> No | P25: =IF(N25>0,"Yes","No") -> Yes | Q25: =IF(N25<=30,"Yes","No") -> Yes | R25: =N25/I25 -> #DIV/0!
A26: L2 | B26: Connor Cason | C26: 45742 | D26: Writing | E26: Alphawrite | H26: 0 | J26: 0 | N26: 0.92000002 | O26: =IF(I26>0,"Yes","No") -> No | P26: =IF(N26>0,"Yes","No") -> Yes | Q26: =IF(N26<=30,"Yes","No") -> Yes | R26: =N26/I26 -> #DIV/0!
A27: L2 | B27: Helio Ortiz | C27: 45742 | D27: Writing | E27: Alphawrite | F27: Grade 3, Easy | H27: 0 | I27: 0 | J27: 0 | K27: 20 | L27: 49 | M27: 0.40816326 | N27: 42.18 | O27: =IF(I27>0,"Yes","No") -> No | P27: =IF(N27>0,"Yes","No") -> Yes | Q27: =IF(N27<=30,"Yes","No") -> No | R27: =N27/I27 -> #DIV/0!
A28: L2 | B28: Jack Bromberg | C28: 45742 | D28: Writing | E28: Alphawrite | H28: 0 | J28: 0 | N28: 0.02 | O28: =IF(I28>0,"Yes","No") -> No | P28: =IF(N28>0,"Yes","No") -> Yes | Q28: =IF(N28<=30,"Yes","No") -> Yes | R28: =N28/I28 -> #DIV/0! | Y28: Exclude instances of students spending >30 min (they may have left their laptops on without any action)
A29: L2 | B29: Jacob Atamas | C29: 45742 | D29: Writing | E29: Alphawrite | H29: 0 | J29: 0 | N29: 2.28 | O29: =IF(I29>0,"Yes","No") -> No | P29: =IF(N29>0,"Yes","No") -> Yes | Q29: =IF(N29<=30,"Yes","No") -> Yes | R29: =N29/I29 -> #DIV/0!
A30: L2 | B30: Lavender Marrero | C30: 45742 | D30: Writing | E30: Alphawrite | F30: Grade 4, Easy | H30: 0 | I30: 0 | J30: 0 | K30: 2 | L30: 6 | M30: 0.33333333 | N30: 7.0300002 | O30: =IF(I30>0,"Yes","No") -> No | P30: =IF(N30>0,"Yes","No") -> Yes | Q30: =IF(N30<=30,"Yes","No") -> Yes | R30: =N30/I30 -> #DIV/0!
A31: L2 | B31: Lily Gray | C31: 45742 | D31: Writing | E31: Alphawrite | F31: Grade 5, Easy | H31: 0 | I31: 0 | J31: 0 | K31: 0 | L31: 0 | N31: 6.5999999 | O31: =IF(I31>0,"Yes","No") -> No | P31: =IF(N31>0,"Yes","No") -> Yes | Q31: =IF(N31<=30,"Yes","No") -> Yes | R31: =N31/I31 -> #DIV/0!
A32: L2 | B32: Marcus Fuentes | C32: 45742 | D32: Writing | E32: Alphawrite | F32: Grade 3, Easy | H32: 0 | I32: 1 | J32: 0 | K32: 13 | L32: 17 | M32: 0.76470588 | N32: 6.6900001 | O32: =IF(I32>0,"Yes","No") -> Yes | P32: =IF(N32>0,"Yes","No") -> Yes | Q32: =IF(N32<=30,"Yes","No") -> Yes | R32: =N32/I32 -> 6.6900001
A33: L2 | B33: Mila Atamas | C33: 45742 | D33: Writing | E33: Alphawrite | F33: Grade 5, Easy | H33: 0 | I33: 0 | J33: 0 | K33: 16 | L33: 20 | M33: 0.8 | N33: 12.36 | O33: =IF(I33>0,"Yes","No") -> No | P33: =IF(N33>0,"Yes","No") -> Yes | Q33: =IF(N33<=30,"Yes","No") -> Yes | R33: =N33/I33 -> #DIV/0!
A34: L2 | B34: Orion Campbell | C34: 45742 | D34: Writing | E34: Alphawrite | F34: Grade 5, Easy | H34: 0 | I34: 0 | J34: 0 | K34: 0 | L34: 2 | M34: 0 | N34: 8.79 | O34: =IF(I34>0,"Yes","No") -> No | P34: =IF(N34>0,"Yes","No") -> Yes | Q34: =IF(N34<=30,"Yes","No") -> Yes | R34: =N34/I34 -> #DIV/0!
A35: L2 | B35: Raegan Middleton | C35: 45742 | D35: Writing | E35: Alphawrite | F35: Grade 3, Easy | H35: 0 | I35: 0 | J35: 0 | K35: 26 | L35: 28 | M35: 0.92857143 | N35: 7.21 | O35: =IF(I35>0,"Yes","No") -> No | P35: =IF(N35>0,"Yes","No") -> Yes | Q35: =IF(N35<=30,"Yes","No") -> Yes | R35: =N35/I35 -> #DIV/0!
A36: L2 | B36: Rocco Benetti | C36: 45742 | D36: Writing | E36: Alphawrite | F36: Grade 5, Easy | H36: 0 | I36: 2 | J36: 0 | K36: 47 | L36: 61 | M36: 0.7704918 | N36: 25.35 | O36: =IF(I36>0,"Yes","No") -> Yes | P36: =IF(N36>0,"Yes","No") -> Yes | Q36: =IF(N36<=30,"Yes","No") -> Yes | R36: =N36/I36 -> 12.675
A37: L2 | B37: Xavier Siddall | C37: 45742 | D37: Writing | E37: Alphawrite | F37: Grade 3, Easy | H37: 0 | I37: 0 | J37: 0 | K37: 23 | L37: 33 | M37: 0.6969697 | N37: 44.529999 | O37: =IF(I37>0,"Yes","No") -> No | P37: =IF(N37>0,"Yes","No") -> Yes | Q37: =IF(N37<=30,"Yes","No") -> No | R37: =N37/I37 -> #DIV/0!
A38: L1 | B38: Anaya Lenington | C38: 45741 | D38: Writing | E38: Alphawrite | F38: Grade 4, Easy | H38: 0 | I38: 1 | J38: 0 | K38: 16 | L38: 22 | M38: 0.72727273 | N38: 5.7199998 | O38: =IF(I38>0,"Yes","No") -> Yes | P38: =IF(N38>0,"Yes","No") -> Yes | Q38: =IF(N38<=30,"Yes","No") -> Yes | R38: =N38/I38 -> 5.7199998
A39: L1 | B39: Arjun Caberwal | C39: 45741 | D39: Writing | E39: Alphawrite | F39: Grade 4, Easy | H39: 0 | I39: 1 | J39: 0 | K39: 13 | L39: 19 | M39: 0.68421053 | N39: 0 | O39: =IF(I39>0,"Yes","No") -> Yes | P39: =IF(N39>0,"Yes","No") -> No | Q39: =IF(N39<=30,"Yes","No") -> Yes | R39: =N39/I39 -> 0
A40: L1 | B40: Arman Caberwal | C40: 45741 | D40: Writing | E40: Alphawrite | F40: Grade 4, Easy | H40: 0 | I40: 1 | J40: 0 | K40: 24 | L40: 38 | M40: 0.63157895 | N40: 12.41 | O40: =IF(I40>0,"Yes","No") -> Yes | P40: =IF(N40>0,"Yes","No") -> Yes | Q40: =IF(N40<=30,"Yes","No") -> Yes | R40: =N40/I40 -> 12.41
A41: L1 | B41: Aubrey Curtis | C41: 45741 | D41: Writing | E41: Alphawrite | F41: Grade 4, Easy | H41: 0 | I41: 1 | J41: 0 | K41: 15 | L41: 25 | M41: 0.6 | N41: 0 | O41: =IF(I41>0,"Yes","No") -> Yes | P41: =IF(N41>0,"Yes","No") -> No | Q41: =IF(N41<=30,"Yes","No") -> Yes | R41: =N41/I41 -> 0
A42: L1 | B42: Brady York | C42: 45741 | D42: Writing | E42: Alphawrite | F42: Grade 3, Easy | H42: 0 | I42: 1 | J42: 0 | K42: 15 | L42: 15 | M42: 1 | N42: 4 | O42: =IF(I42>0,"Yes","No") -> Yes | P42: =IF(N42>0,"Yes","No") -> Yes | Q42: =IF(N42<=30,"Yes","No") -> Yes | R42: =N42/I42 -> 4
A43: L1 | B43: David Paul | C43: 45741 | D43: Writing | E43: Alphawrite | F43: Grade 3, Easy | H43: 0 | I43: 1 | J43: 0 | K43: 34 | L43: 59 | M43: 0.57627119 | N43: 8.2799997 | O43: =IF(I43>0,"Yes","No") -> Yes | P43: =IF(N43>0,"Yes","No") -> Yes | Q43: =IF(N43<=30,"Yes","No") -> Yes | R43: =N43/I43 -> 8.2799997
... A46: L1 | B46: Evelyn Gabler | C46: 45741 | D46: Writing | E46: Alphawrite | F46: Grade 4, Easy | H46: 0 | I46: 1 | J46: 0 | K46: 50 | L46: 65 | M46: 0.76923077 | N46: 0 | O46: =IF(I46>0,"Yes","No") -> Yes | P46: =IF(N46>0,"Yes","No") -> No | Q46: =IF(N46<=30,"Yes","No") -> Yes | R46: =N46/I46 -> 0
A47: L1 | B47: Evelyn Gabler | C47: 45741 | D47: Writing | E47: Alphawrite | F47: Grade 5, Easy | H47: 0 | I47: 0 | J47: 0 | K47: 0 | L47: 0 | N47: 0 | O47: =IF(I47>0,"Yes","No") -> No | P47: =IF(N47>0,"Yes","No") -> No | Q47: =IF(N47<=30,"Yes","No") -> Yes | R47: =N47/I47 -> #DIV/0!
A48: L1 | B48: Hazel Salton | C48: 45741 | D48: Writing | E48: Alphawrite | F48: Grade 3, Easy | H48: 0 | I48: 1 | J48: 0 | K48: 18 | L48: 36 | M48: 0.5 | N48: 0 | O48: =IF(I48>0,"Yes","No") -> Yes | P48: =IF(N48>0,"Yes","No") -> No | Q48: =IF(N48<=30,"Yes","No") -> Yes | R48: =N48/I48 -> 0
A49: L1 | B49: Hazel Salton | C49: 45741 | D49: Writing | E49: Alphawrite | F49: Grade 4, Easy | H49: 0 | I49: 0 | J49: 0 | K49: 2 | L49: 4 | M49: 0.5 | N49: 0 | O49: =IF(I49>0,"Yes","No") -> No | P49: =IF(N49>0,"Yes","No") -> No | Q49: =IF(N49<=30,"Yes","No") -> Yes | R49: =N49/I49 -> #DIV/0!
A50: L1 | B50: Ian Mentgen | C50: 45741 | D50: Writing | E50: Alphawrite | F50: Grade 3, Easy | H50: 0 | I50: 1 | J50: 0 | K50: 30 | L50: 40 | M50: 0.75 | N50: 17.41 | O50: =IF(I50>0,"Yes","No") -> Yes | P50: =IF(N50>0,"Yes","No") -> Yes | Q50: =IF(N50<=30,"Yes","No") -> Yes | R50: =N50/I50 -> 17.41
A51: L1 | B51: Jaxon Siers | C51: 45741 | D51: Writing | E51: Alphawrite | F51: Grade 3, Easy | H51: 0 | I51: 1 | J51: 0 | K51: 14 | L51: 18 | M51: 0.77777778 | N51: 25.790001 | O51: =IF(I51>0,"Yes","No") -> Yes | P51: =IF(N51>0,"Yes","No") -> Yes | Q51: =IF(N51<=30,"Yes","No") -> Yes | R51: =N51/I51 -> 25.790001
A52: L1 | B52: Jaxon Siers | C52: 45741 | D52: Writing | E52: Alphawrite | F52: Grade 4, Easy | H52: 0 | I52: 0 | J52: 0 | K52: 13 | L52: 17 | M52: 0.76470588 | N52: 0 | O52: =IF(I52>0,"Yes","No") -> No | P52: =IF(N52>0,"Yes","No") -> No | Q52: =IF(N52<=30,"Yes","No") -> Yes | R52: =N52/I52 -> #DIV/0!
A53: L1 | B53: Juan Diego Ortega | C53: 45741 | D53: Writing | E53: Alphawrite | H53: 0 | J53: 0 | N53: 3.45 | O53: =IF(I53>0,"Yes","No") -> No | P53: =IF(N53>0,"Yes","No") -> Yes | Q53: =IF(N53<=30,"Yes","No") -> Yes | R53: =N53/I53 -> #DIV/0!
A54: L1 | B54: Logan Campbell | C54: 45741 | D54: Writing | E54: Alphawrite | F54: Grade 4, Easy | H54: 0 | I54: 0 | J54: 0 | K54: 4 | L54: 6 | M54: 0.66666667 | N54: 0 | O54: =IF(I54>0,"Yes","No") -> No | P54: =IF(N54>0,"Yes","No") -> No | Q54: =IF(N54<=30,"Yes","No") -> Yes | R54: =N54/I54 -> #DIV/0!
A55: L1 | B55: Luna Montagna | C55: 45741 | D55: Writing | E55: Alphawrite | F55: Grade 3, Easy | H55: 0 | I55: 0 | J55: 0 | K55: 4 | L55: 9 | M55: 0.44444444 | N55: 0 | O55: =IF(I55>0,"Yes","No") -> No | P55: =IF(N55>0,"Yes","No") -> No | Q55: =IF(N55<=30,"Yes","No") -> Yes | R55: =N55/I55 -> #DIV/0!
A56: L1 | B56: Max Vaughan | C56: 45741 | D56: Writing | E56: Alphawrite | F56: Grade 3, Easy | H56: 0 | I56: 0 | J56: 0 | K56: 0 | L56: 2 | M56: 0 | N56: 0 | O56: =IF(I56>0,"Yes","No") -> No | P56: =IF(N56>0,"Yes","No") -> No | Q56: =IF(N56<=30,"Yes","No") -> Yes | R56: =N56/I56 -> #DIV/0!
A57: L1 | B57: Nate Evans | C57: 45741 | D57: Writing | E57: Edulastic | H57: 0 | J57: 0 | N57: 34.5 | O57: =IF(I57>0,"Yes","No") -> No | P57: =IF(N57>0,"Yes","No") -> Yes | Q57: =IF(N57<=30,"Yes","No") -> No | R57: =N57/I57 -> #DIV/0!
A58: L1 | B58: Ramsey Levin | C58: 45741 | D58: Writing | E58: Alphawrite | F58: Grade 4, Easy | H58: 0 | I58: 1 | J58: 0 | K58: 26 | L58: 29 | M58: 0.89655172 | N58: 0 | O58: =IF(I58>0,"Yes","No") -> Yes | P58: =IF(N58>0,"Yes","No") -> No | Q58: =IF(N58<=30,"Yes","No") -> Yes | R58: =N58/I58 -> 0
A59: L1 | B59: Sarah Hunter | C59: 45741 | D59: Writing | E59: Alphawrite | F59: Grade 3, Easy | H59: 0 | I59: 2 | J59: 0 | K59: 43 | L59: 51 | M59: 0.84313726 | N59: 0 | O59: =IF(I59>0,"Yes","No") -> Yes | P59: =IF(N59>0,"Yes","No") -> No | Q59: =IF(N59<=30,"Yes","No") -> Yes | R59: =N59/I59 -> 0
A60: L1 | B60: Sophia Reicher | C60: 45741 | D60: Writing | E60: Alphawrite | F60: Grade 5, Easy | H60: 0 | I60: 1 | J60: 0 | K60: 8 | L60: 10 | M60: 0.8 | N60: 2.8699999 | O60: =IF(I60>0,"Yes","No") -> Yes | P60: =IF(N60>0,"Yes","No") -> Yes | Q60: =IF(N60<=30,"Yes","No") -> Yes | R60: =N60/I60 -> 2.8699999
A61: L1 | B61: Tate Price | C61: 45741 | D61: Writing | E61: Alphawrite | F61: Grade 5, Easy | H61: 0 | I61: 1 | J61: 0 | K61: 14 | L61: 14 | M61: 1 | N61: 0 | O61: =IF(I61>0,"Yes","No") -> Yes | P61: =IF(N61>0,"Yes","No") -> No | Q61: =IF(N61<=30,"Yes","No") -> Yes | R61: =N61/I61 -> 0
A62: L2 | B62: Aksel Jensen | C62: 45741 | D62: Writing | E62: Alphawrite | H62: 0 | J62: 0 | N62: 0.050000001 | O62: =IF(I62>0,"Yes","No") -> No | P62: =IF(N62>0,"Yes","No") -> Yes | Q62: =IF(N62<=30,"Yes","No") -> Yes | R62: =N62/I62 -> #DIV/0!
A63: L2 | B63: Asha Nagar | C63: 45741 | D63: Writing | E63: Alphawrite | F63: Grade 5, Easy | H63: 0 | I63: 0 | J63: 0 | K63: 0 | L63: 0 | N63: 1.38 | O63: =IF(I63>0,"Yes","No") -> No | P63: =IF(N63>0,"Yes","No") -> Yes | Q63: =IF(N63<=30,"Yes","No") -> Yes | R63: =N63/I63 -> #DIV/0!
A64: L2 | B64: Bella Barba | C64: 45741 | D64: Writing | E64: Alphawrite | F64: Grade 5, Easy | H64: 0 | I64: 3 | J64: 0 | K64: 46 | L64: 64 | M64: 0.71875 | N64: 30.85 | O64: =IF(I64>0,"Yes","No") -> Yes | P64: =IF(N64>0,"Yes","No") -> Yes | Q64: =IF(N64<=30,"Yes","No") -> No | R64: =N64/I64 -> 10.283333
A65: L2 | B65: Blake Flores | C65: 45741 | D65: Writing | E65: Alphawrite | F65: Grade 4, Easy | H65: 0 | I65: 0 | J65: 0 | K65: 0 | L65: 0 | N65: 0 | O65: =IF(I65>0,"Yes","No") -> No | P65: =IF(N65>0,"Yes","No") -> No | Q65: =IF(N65<=30,"Yes","No") -> Yes | R65: =N65/I65 -> #DIV/0!
A66: L2 | B66: Blake Flores | C66: 45741 | D66: Writing | E66: Alphawrite | F66: Grade 5, Easy | H66: 0 | I66: 0 | J66: 0 | K66: 11 | L66: 13 | M66: 0.84615385 | N66: 0 | O66: =IF(I66>0,"Yes","No") -> No | P66: =IF(N66>0,"Yes","No") -> No | Q66: =IF(N66<=30,"Yes","No") -> Yes | R66: =N66/I66 -> #DIV/0!
A67: L2 | B67: Brooklyn Allred | C67: 45741 | D67: Writing | E67: Alphawrite | F67: Grade 4, Easy | H67: 0 | I67: 0 | J67: 0 | K67: 2 | L67: 4 | M67: 0.5 | N67: 2.51 | O67: =IF(I67>0,"Yes","No") -> No | P67: =IF(N67>0,"Yes","No") -> Yes | Q67: =IF(N67<=30,"Yes","No") -> Yes | R67: =N67/I67 -> #DIV/0!
A68: L2 | B68: Connor Cason | C68: 45741 | D68: Writing | E68: Alphawrite | F68: Grade 3, Easy | H68: 0 | I68: 0 | J68: 0 | K68: 6 | L68: 6 | M68: 1 | N68: 6.6100001 | O68: =IF(I68>0,"Yes","No") -> No | P68: =IF(N68>0,"Yes","No") -> Yes | Q68: =IF(N68<=30,"Yes","No") -> Yes | R68: =N68/I68 -> #DIV/0!
A69: L2 | B69: Connor Cason | C69: 45741 | D69: Writing | E69: Alphawrite | F69: Grade 4, Easy | H69: 0 | I69: 0 | J69: 0 | K69: 0 | L69: 0 | N69: 0 | O69: =IF(I69>0,"Yes","No") -> No | P69: =IF(N69>0,"Yes","No") -> No | Q69: =IF(N69<=30,"Yes","No") -> Yes | R69: =N69/I69 -> #DIV/0!
A70: L2 | B70: Elena Mentgen | C70: 45741 | D70: Writing | E70: Alphawrite | F70: Grade 3, Easy | H70: 0 | I70: 0 | J70: 0 | K70: 6 | L70: 6 | M70: 1 | N70: 0 | O70: =IF(I70>0,"Yes","No") -> No | P70: =IF(N70>0,"Yes","No") -> No | Q70: =IF(N70<=30,"Yes","No") -> Yes | R70: =N70/I70 -> #DIV/0!
A71: L2 | B71: Elena Mentgen | C71: 45741 | D71: Writing | E71: Alphawrite | F71: Grade 5, Easy | H71: 0 | I71: 2 | J71: 0 | K71: 36 | L71: 40 | M71: 0.9 | N71: 11.92 | O71: =IF(I71>0,"Yes","No") -> Yes | P71: =IF(N71>0,"Yes","No") -> Yes | Q71: =IF(N71<=30,"Yes","No") -> Yes | R71: =N71/I71 -> 5.96
A72: L2 | B72: Jack Bromberg | C72: 45741 | D72: Writing | E72: Alphawrite | H72: 0 | J72: 0 | N72: 0.56 | O72: =IF(I72>0,"Yes","No") -> No | P72: =IF(N72>0,"Yes","No") -> Yes | Q72: =IF(N72<=30,"Yes","No") -> Yes | R72: =N72/I72 -> #DIV/0!
A73: L2 | B73: Jason Montagna | C73: 45741 | D73: Writing | E73: Alphawrite | F73: Grade 4, Easy | H73: 0 | I73: 0 | J73: 0 | K73: 14 | L73: 28 | M73: 0.5 | N73: 30.5 | O73: =IF(I73>0,"Yes","No") -> No | P73: =IF(N73>0,"Yes","No") -> Yes | Q73: =IF(N73<=30,"Yes","No") -> No | R73: =N73/I73 -> #DIV/0!
A74: L2 | B74: Kai Sticker | C74: 45741 | D74: Writing | E74: Alphawrite | F74: Grade 4, Easy | H74: 0 | I74: 0 | J74: 0 | K74: 2 | L74: 2 | M74: 1 | N74: 0 | O74: =IF(I74>0,"Yes","No") -> No | P74: =IF(N74>0,"Yes","No") -> No | Q74: =IF(N74<=30,"Yes","No") -> Yes | R74: =N74/I74 -> #DIV/0!
A75: L2 | B75: Kai Sticker | C75: 45741 | D75: Writing | E75: Alphawrite | F75: Grade 8, Easy | H75: 0 | I75: 1 | J75: 0 | K75: 24 | L75: 28 | M75: 0.85714286 | N75: 0 | O75: =IF(I75>0,"Yes","No") -> Yes | P75: =IF(N75>0,"Yes","No") -> No | Q75: =IF(N75<=30,"Yes","No") -> Yes | R75: =N75/I75 -> 0
A76: L2 | B76: Krish Bhakta | C76: 45741 | D76: Writing | E76: Alphawrite | H76: 0 | J76: 0 | N76: 0.27000001 | O76: =IF(I76>0,"Yes","No") -> No | P76: =IF(N76>0,"Yes","No") -> Yes | Q76: =IF(N76<=30,"Yes","No") -> Yes | R76: =N76/I76 -> #DIV/0!
A77: L2 | B77: Lavender Marrero | C77: 45741 | D77: Writing | E77: Alphawrite | F77: Grade 4, Easy | H77: 0 | I77: 0 | J77: 0 | K77: 4 | L77: 14 | M77: 0.28571429 | N77: 0 | O77: =IF(I77>0,"Yes","No") -> No | P77: =IF(N77>0,"Yes","No") -> No | Q77: =IF(N77<=30,"Yes","No") -> Yes | R77: =N77/I77 -> #DIV/0!
A78: L2 | B78: Lily Gray | C78: 45741 | D78: Writing | E78: Alphawrite | F78: Grade 5, Easy | H78: 0 | I78: 0 | J78: 0 | K78: 2 | L78: 6 | M78: 0.33333333 | N78: 0 | O78: =IF(I78>0,"Yes","No") -> No | P78: =IF(N78>0,"Yes","No") -> No | Q78: =IF(N78<=30,"Yes","No") -> Yes | R78: =N78/I78 -> #DIV/0!
A79: L2 | B79: Marcus Fuentes | C79: 45741 | D79: Writing | E79: Alphawrite | F79: Grade 3, Easy | H79: 0 | I79: 0 | J79: 0 | K79: 0 | L79: 0 | N79: 0 | O79: =IF(I79>0,"Yes","No") -> No | P79: =IF(N79>0,"Yes","No") -> No | Q79: =IF(N79<=30,"Yes","No") -> Yes | R79: =N79/I79 -> #DIV/0!
A80: L2 | B80: Mila Atamas | C80: 45741 | D80: Writing | E80: Alphawrite | H80: 0 | J80: 0 | N80: 1.09 | O80: =IF(I80>0,"Yes","No") -> No | P80: =IF(N80>0,"Yes","No") -> Yes | Q80: =IF(N80<=30,"Yes","No") -> Yes | R80: =N80/I80 -> #DIV/0!
A81: L2 | B81: Raegan Middleton | C81: 45741 | D81: Writing | E81: Alphawrite | F81: Grade 3, Easy | H81: 0 | I81: 0 | J81: 0 | K81: 22 | L81: 26 | M81: 0.84615385 | N81: 0.059999999 | O81: =IF(I81>0,"Yes","No") -> No | P81: =IF(N81>0,"Yes","No") -> Yes | Q81: =IF(N81<=30,"Yes","No") -> Yes | R81: =N81/I81 -> #DIV/0!
A82: L2 | B82: Rania Caberwal | C82: 45741 | D82: Writing | E82: Alphawrite | F82: Grade 5, Easy | H82: 0 | I82: 0 | J82: 0 | K82: 4 | L82: 6 | M82: 0.66666667 | N82: 3.23 | O82: =IF(I82>0,"Yes","No") -> No | P82: =IF(N82>0,"Yes","No") -> Yes | Q82: =IF(N82<=30,"Yes","No") -> Yes | R82: =N82/I82 -> #DIV/0!
A83: L2 | B83: Rocco Benetti | C83: 45741 | D83: Writing | E83: Alphawrite | F83: Grade 3, Easy | H83: 0 | I83: 0 | J83: 0 | K83: 14 | L83: 14 | M83: 1 | N83: 0 | O83: =IF(I83>0,"Yes","No") -> No | P83: =IF(N83>0,"Yes","No") -> No | Q83: =IF(N83<=30,"Yes","No") -> Yes | R83: =N83/I83 -> #DIV/0!
A84: L2 | B84: Xavier Siddall | C84: 45741 | D84: Writing | E84: Alphawrite | F84: Grade 3, Easy | H84: 0 | I84: 0 | J84: 0 | K84: 16 | L84: 21 | M84: 0.76190476 | N84: 23.559999 | O84: =IF(I84>0,"Yes","No") -> No | P84: =IF(N84>0,"Yes","No") -> Yes | Q84: =IF(N84<=30,"Yes","No") -> Yes | R84: =N84/I84 -> #DIV/0!
A85: L3 | B85: Bennett Morris | C85: 45741 | D85: Writing | E85: Alphawrite | F85: Grade 5, Easy | H85: 0 | I85: 1 | J85: 0 | K85: 32 | L85: 44 | M85: 0.72727273 | N85: 11.96 | O85: =IF(I85>0,"Yes","No") -> Yes | P85: =IF(N85>0,"Yes","No") -> Yes | Q85: =IF(N85<=30,"Yes","No") -> Yes | R85: =N85/I85 -> 11.96
A86: L3 | B86: Penny Marty | C86: 45741 | D86: Writing | E86: Alphawrite | F86: Grade 3, Easy | H86: 0 | I86: 2 | J86: 0 | K86: 36 | L86: 44 | M86: 0.81818182 | N86: 0 | O86: =IF(I86>0,"Yes","No") -> Yes | P86: =IF(N86>0,"Yes","No") -> No | Q86: =IF(N86<=30,"Yes","No") -> Yes | R86: =N86/I86 -> 0
A87: L3 | B87: Sydney Barba | C87: 45741 | D87: Writing | E87: Alphawrite | F87: Grade 5, Easy | H87: 0 | I87: 1 | J87: 0 | K87: 8 | L87: 8 | M87: 1 | N87: 14.3 | O87: =IF(I87>0,"Yes","No") -> Yes | P87: =IF(N87>0,"Yes","No") -> Yes | Q87: =IF(N87<=30,"Yes","No") -> Yes | R87: =N87/I87 -> 14.3
A88: L1 | B88: Aleina Boyce | C88: 45740 | D88: Writing | E88: Alphawrite | H88: 0 | J88: 0 | N88: 13.51 | O88: =IF(I88>0,"Yes","No") -> No | P88: =IF(N88>0,"Yes","No") -> Yes | Q88: =IF(N88<=30,"Yes","No") -> Yes | R88: =N88/I88 -> #DIV/0!
A89: L1 | B89: Alex Lekic Brajovic | C89: 45740 | D89: Writing | E89: Alphawrite | H89: 0 | J89: 0 | N89: 0.02 | O89: =IF(I89>0,"Yes","No") -> No | P89: =IF(N89>0,"Yes","No") -> Yes | Q89: =IF(N89<=30,"Yes","No") -> Yes | R89: =N89/I89 -> #DIV/0!
A90: L1 | B90: Alexander Wiebeck | C90: 45740 | D90: Writing | E90: Alphawrite | F90: Grade 3, Easy | H90: 0 | I90: 0 | J90: 0 | K90: 2 | L90: 2 | M90: 1 | N90: 3.5 | O90: =IF(I90>0,"Yes","No") -> No | P90: =IF(N90>0,"Yes","No") -> Yes | Q90: =IF(N90<=30,"Yes","No") -> Yes | R90: =N90/I90 -> #DIV/0!
A91: L1 | B91: Anaya Lenington | C91: 45740 | D91: Writing | E91: Alphawrite | F91: Grade 3, Easy | G91: ANTI | Working on non-recommended skills | H91: 1 | I91: 0 | J91: 0 | K91: 0 | L91: 0 | N91: 0 | O91: =IF(I91>0,"Yes","No") -> No | P91: =IF(N91>0,"Yes","No") -> No | Q91: =IF(N91<=30,"Yes","No") -> Yes | R91: =N91/I91 -> #DIV/0!
A92: L1 | B92: Anaya Lenington | C92: 45740 | D92: Writing | E92: Alphawrite | F92: Grade 4, Easy | G92: ANTI | Working on non-recommended skills | H92: 1 | I92: 1 | J92: 0 | K92: 27 | L92: 42 | M92: 0.64285714 | N92: 97.029999 | O92: =IF(I92>0,"Yes","No") -> Yes | P92: =IF(N92>0,"Yes","No") -> Yes | Q92: =IF(N92<=30,"Yes","No") -> No | R92: =N92/I92 -> 97.029999
A93: L1 | B93: Arjun Caberwal | C93: 45740 | D93: Writing | E93: Alphawrite | F93: Grade 4, Easy | G93: ANTI | Working on non-recommended skills | H93: 1 | I93: 0 | J93: 0 | K93: 16 | L93: 20 | M93: 0.8 | N93: 7.73 | O93: =IF(I93>0,"Yes","No") -> No | P93: =IF(N93>0,"Yes","No") -> Yes | Q93: =IF(N93<=30,"Yes","No") -> Yes | R93: =N93/I93 -> #DIV/0!
A94: L1 | B94: Arman Caberwal | C94: 45740 | D94: Writing | E94: Alphawrite | F94: Grade 4, Easy | G94: ANTI | Working on non-recommended skills | H94: 1 | I94: 1 | J94: 0 | K94: 44 | L94: 66 | M94: 0.66666667 | N94: 33.880001 | O94: =IF(I94>0,"Yes","No") -> Yes | P94: =IF(N94>0,"Yes","No") -> Yes | Q94: =IF(N94<=30,"Yes","No") -> No | R94: =N94/I94 -> 33.880001
A95: L1 | B95: Aubrey Curtis | C95: 45740 | D95: Writing | E95: Alphawrite | F95: Grade 4, Easy | G95: ANTI | Working on non-recommended skills | H95: 1 | I95: 0 | J95: 0 | K95: 6 | L95: 8 | M95: 0.75 | N95: 6.3699999 | O95: =IF(I95>0,"Yes","No") -> No | P95: =IF(N95>0,"Yes","No") -> Yes | Q95: =IF(N95<=30,"Yes","No") -> Yes | R95: =N95/I95 -> #DIV/0!
A96: L1 | B96: Brady York | C96: 45740 | D96: Writing | E96: Alphawrite | F96: Grade 3, Easy | G96: ANTI | Working on non-recommended skills | H96: 1 | I96: 1 | J96: 0 | K96: 30 | L96: 41 | M96: 0.73170732 | N96: 41.48 | O96: =IF(I96>0,"Yes","No") -> Yes | P96: =IF(N96>0,"Yes","No") -> Yes | Q96: =IF(N96<=30,"Yes","No") -> No | R96: =N96/I96 -> 41.48
A97: L1 | B97: Claudia Hobart | C97: 45740 | D97: Writing | E97: Alphawrite | F97: Grade 5, Easy | G97: ANTI | Working on non-recommended skills | H97: 1 | I97: 1 | J97: 0 | K97: 14 | L97: 17 | M97: 0.82352941 | N97: 9.8299999 | O97: =IF(I97>0,"Yes","No") -> Yes | P97: =IF(N97>0,"Yes","No") -> Yes | Q97: =IF(N97<=30,"Yes","No") -> Yes | R97: =N97/I97 -> 9.8299999
A98: L1 | B98: David Paul | C98: 45740 | D98: Writing | E98: Alphawrite | F98: Grade 3, Easy | G98: ANTI | Working on non-recommended skills | H98: 1 | I98: 1 | J98: 0 | K98: 34 | L98: 51 | M98: 0.66666667 | N98: 15.26 | O98: =IF(I98>0,"Yes","No") -> Yes | P98: =IF(N98>0,"Yes","No") -> Yes | Q98: =IF(N98<=30,"Yes","No") -> Yes | R98: =N98/I98 -> 15.26
A99: L1 | B99: David Paul | C99: 45740 | D99: Writing | E99: Alphawrite | F99: Grade 6, Easy | G99: ANTI | Working on non-recommended skills | H99: 1 | I99: 0 | J99: 0 | K99: 0 | L99: 0 | N99: 0 | O99: =IF(I99>0,"Yes","No") -> No | P99: =IF(N99>0,"Yes","No") -> No | Q99: =IF(N99<=30,"Yes","No") -> Yes | R99: =N99/I99 -> #DIV/0!
A100: L1 | B100: Donnie Moore | C100: 45740 | D100: Writing | E100: Alphawrite | F100: Grade 3, Easy | H100: 0 | I100: 1 | J100: 0 | K100: 24 | L100: 32 | M100: 0.75 | N100: 11.55 | O100: =IF(I100>0,"Yes","No") -> Yes | P100: =IF(N100>0,"Yes","No") -> Yes | Q100: =IF(N100<=30,"Yes","No") -> Yes | R100: =N100/I100 -> 11.55
A101: L1 | B101: Evelyn Gabler | C101: 45740 | D101: Writing | E101: Alphawrite | F101: Grade 4, Easy | H101: 0 | I101: 0 | J101: 0 | K101: 18 | L101: 26 | M101: 0.69230769 | N101: 13.78 | O101: =IF(I101>0,"Yes","No") -> No | P101: =IF(N101>0,"Yes","No") -> Yes | Q101: =IF(N101<=30,"Yes","No") -> Yes | R101: =N101/I101 -> #DIV/0!
A102: L1 | B102: Evelyn Gabler | C102: 45740 | D102: Writing | E102: Alphawrite | F102: Grade 5, Easy | H102: 0 | I102: 0 | J102: 0 | K102: 0 | L102: 0 | N102: 0 | O102: =IF(I102>0,"Yes","No") -> No | P102: =IF(N102>0,"Yes","No") -> No | Q102: =IF(N102<=30,"Yes","No") -> Yes | R102: =N102/I102 -> #DIV/0!
...

Sheet raw-aaa20250325
A1: Level | B1: Student | C1: Date | D1: Subject | E1: App | F1: Course | G1: Anti-patterns | H1: Anti-pattern count | I1: Lessons mastered | J1: Essential Lessons Mastered | K1: Correct Questions | L1: Total Questions | M1: Accuracy | N1: Minutes
A2: L1 | B2: Anaya Lenington | C2: 45741 | D2: Writing | E2: Alphawrite | F2: Grade 4, Easy | H2: 0 | I2: 1 | J2: 0 | K2: 16 | L2: 22 | M2: 0.72727273 | N2: 5.7199998
A3: L1 | B3: Arjun Caberwal | C3: 45741 | D3: Writing | E3: Alphawrite | F3: Grade 4, Easy | H3: 0 | I3: 1 | J3: 0 | K3: 13 | L3: 19 | M3: 0.68421053 | N3: 0
A4: L1 | B4: Arman Caberwal | C4: 45741 | D4: Writing | E4: Alphawrite | F4: Grade 4, Easy | H4: 0 | I4: 1 | J4: 0 | K4: 24 | L4: 38 | M4: 0.63157895 | N4: 12.41
A5: L1 | B5: Aubrey Curtis | C5: 45741 | D5: Writing | E5: Alphawrite | F5: Grade 4, Easy | H5: 0 | I5: 1 | J5: 0 | K5: 15 | L5: 25 | M5: 0.6 | N5: 0
A6: L1 | B6: Brady York | C6: 45741 | D6: Writing | E6: Alphawrite | F6: Grade 3, Easy | H6: 0 | I6: 1 | J6: 0 | K6: 15 | L6: 15 | M6: 1 | N6: 4
A7: L1 | B7: David Paul | C7: 45741 | D7: Writing | E7: Alphawrite | F7: Grade 3, Easy | H7: 0 | I7: 1 | J7: 0 | K7: 34 | L7: 59 | M7: 0.57627119 | N7: 8.2799997
A8: L1 | B8: Donnie Moore | C8: 45741 | D8: Writing | E8: Alphawrite | F8: Grade 3, Easy | H8: 0 | I8: 1 | J8: 0 | K8: 16 | L8: 16 | M8: 1 | N8: 0
A9: L1 | B9: Elaina Robertson | C9: 45741 | D9: Writing | E9: Alphawrite | F9: Grade 4, Easy | H9: 0 | I9: 1 | J9: 0 | K9: 58 | L9: 84 | M9: 0.69047619 | N9: 0
A10: L1 | B10: Evelyn Gabler | C10: 45741 | D10: Writing | E10: Alphawrite | F10: Grade 4, Easy | H10: 0 | I10: 1 | J10: 0 | K10: 50 | L10: 65 | M10: 0.76923077 | N10: 0
A11: L1 | B11: Evelyn Gabler | C11: 45741 | D11: Writing | E11: Alphawrite | F11: Grade 5, Easy | H11: 0 | I11: 0 | J11: 0 | K11: 0 | L11: 0 | N11: 0
A12: L1 | B12: Hazel Salton | C12: 45741 | D12: Writing | E12: Alphawrite | F12: Grade 3, Easy | H12: 0 | I12: 1 | J12: 0 | K12: 18 | L12: 36 | M12: 0.5 | N12: 0
A13: L1 | B13: Hazel Salton | C13: 45741 | D13: Writing | E13: Alphawrite | F13: Grade 4, Easy | H13: 0 | I13: 0 | J13: 0 | K13: 2 | L13: 4 | M13: 0.5 | N13: 0
A14: L1 | B14: Ian Mentgen | C14: 45741 | D14: Writing | E14: Alphawrite | F14: Grade 3, Easy | H14: 0 | I14: 1 | J14: 0 | K14: 30 | L14: 40 | M14: 0.75 | N14: 17.41
A15: L1 | B15: Jaxon Siers | C15: 45741 | D15: Writing | E15: Alphawrite | F15: Grade 3, Easy | H15: 0 | I15: 1 | J15: 0 | K15: 14 | L15: 18 | M15: 0.77777778 | N15: 25.790001
A16: L1 | B16: Jaxon Siers | C16: 45741 | D16: Writing | E16: Alphawrite | F16: Grade 4, Easy | H16: 0 | I16: 0 | J16: 0 | K16: 13 | L16: 17 | M16: 0.76470588 | N16: 0
A17: L1 | B17: Juan Diego Ortega | C17: 45741 | D17: Writing | E17: Alphawrite | H17: 0 | J17: 0 | N17: 3.45
A18: L1 | B18: Logan Campbell | C18: 45741 | D18: Writing | E18: Alphawrite | F18: Grade 4, Easy | H18: 0 | I18: 0 | J18: 0 | K18: 4 | L18: 6 | M18: 0.66666667 | N18: 0
A19: L1 | B19: Luna Montagna | C19: 45741 | D19: Writing | E19: Alphawrite | F19: Grade 3, Easy | H19: 0 | I19: 0 | J19: 0 | K19: 4 | L19: 9 | M19: 0.44444444 | N19: 0
A20: L1 | B20: Max Vaughan | C20: 45741 | D20: Writing | E20: Alphawrite | F20: Grade 3, Easy | H20: 0 | I20: 0 | J20: 0 | K20: 0 | L20: 2 | M20: 0 | N20: 0
A21: L1 | B21: Nate Evans | C21: 45741 | D21: Writing | E21: Edulastic | H21: 0 | J21: 0 | N21: 34.5
A22: L1 | B22: Ramsey Levin | C22: 45741 | D22: Writing | E22: Alphawrite | F22: Grade 4, Easy | H22: 0 | I22: 1 | J22: 0 | K22: 26 | L22: 29 | M22: 0.89655172 | N22: 0
A23: L1 | B23: Sarah Hunter | C23: 45741 | D23: Writing | E23: Alphawrite | F23: Grade 3, Easy | H23: 0 | I23: 2 | J23: 0 | K23: 43 | L23: 51 | M23: 0.84313726 | N23: 0
A24: L1 | B24: Sophia Reicher | C24: 45741 | D24: Writing | E24: Alphawrite | F24: Grade 5, Easy | H24: 0 | I24: 1 | J24: 0 | K24: 8 | L24: 10 | M24: 0.8 | N24: 2.8699999
A25: L1 | B25: Tate Price | C25: 45741 | D25: Writing | E25: Alphawrite | F25: Grade 5, Easy | H25: 0 | I25: 1 | J25: 0 | K25: 14 | L25: 14 | M25: 1 | N25: 0
A26: L2 | B26: Aksel Jensen | C26: 45741 | D26: Writing | E26: Alphawrite | H26: 0 | J26: 0 | N26: 0.050000001
A27: L2 | B27: Asha Nagar | C27: 45741 | D27: Writing | E27: Alphawrite | F27: Grade 5, Easy | H27: 0 | I27: 0 | J27: 0 | K27: 0 | L27: 0 | N27: 1.38
A28: L2 | B28: Bella Barba | C28: 45741 | D28: Writing | E28: Alphawrite | F28: Grade 5, Easy | H28: 0 | I28: 3 | J28: 0 | K28: 46 | L28: 64 | M28: 0.71875 | N28: 30.85
A29: L2 | B29: Blake Flores | C29: 45741 | D29: Writing | E29: Alphawrite | F29: Grade 4, Easy | H29: 0 | I29: 0 | J29: 0 | K29: 0 | L29: 0 | N29: 0
A30: L2 | B30: Blake Flores | C30: 45741 | D30: Writing | E30: Alphawrite | F30: Grade 5, Easy | H30: 0 | I30: 0 | J30: 0 | K30: 11 | L30: 13 | M30: 0.84615385 | N30: 0
A31: L2 | B31: Brooklyn Allred | C31: 45741 | D31: Writing | E31: Alphawrite | F31: Grade 4, Easy | H31: 0 | I31: 0 | J31: 0 | K31: 2 | L31: 4 | M31: 0.5 | N31: 2.51
A32: L2 | B32: Connor Cason | C32: 45741 | D32: Writing | E32: Alphawrite | F32: Grade 3, Easy | H32: 0 | I32: 0 | J32: 0 | K32: 6 | L32: 6 | M32: 1 | N32: 6.6100001
A33: L2 | B33: Connor Cason | C33: 45741 | D33: Writing | E33: Alphawrite | F33: Grade 4, Easy | H33: 0 | I33: 0 | J33: 0 | K33: 0 | L33: 0 | N33: 0
A34: L2 | B34: Elena Mentgen | C34: 45741 | D34: Writing | E34: Alphawrite | F34: Grade 3, Easy | H34: 0 | I34: 0 | J34: 0 | K34: 6 | L34: 6 | M34: 1 | N34: 0
A35: L2 | B35: Elena Mentgen | C35: 45741 | D35: Writing | E35: Alphawrite | F35: Grade 5, Easy | H35: 0 | I35: 2 | J35: 0 | K35: 36 | L35: 40 | M35: 0.9 | N35: 11.92
A36: L2 | B36: Jack Bromberg | C36: 45741 | D36: Writing | E36: Alphawrite | H36: 0 | J36: 0 | N36: 0.56
A37: L2 | B37: Jason Montagna | C37: 45741 | D37: Writing | E37: Alphawrite | F37: Grade 4, Easy | H37: 0 | I37: 0 | J37: 0 | K37: 14 | L37: 28 | M37: 0.5 | N37: 30.5
A38: L2 | B38: Kai Sticker | C38: 45741 | D38: Writing | E38: Alphawrite | F38: Grade 4, Easy | H38: 0 | I38: 0 | J38: 0 | K38: 2 | L38: 2 | M38: 1 | N38: 0
A39: L2 | B39: Kai Sticker | C39: 45741 | D39: Writing | E39: Alphawrite | F39: Grade 8, Easy | H39: 0 | I39: 1 | J39: 0 | K39: 24 | L39: 28 | M39: 0.85714286 | N39: 0
A40: L2 | B40: Krish Bhakta | C40: 45741 | D40: Writing | E40: Alphawrite | H40: 0 | J40: 0 | N40: 0.27000001
A41: L2 | B41: Lavender Marrero | C41: 45741 | D41: Writing | E41: Alphawrite | F41: Grade 4, Easy | H41: 0 | I41: 0 | J41: 0 | K41: 4 | L41: 14 | M41: 0.28571429 | N41: 0
A42: L2 | B42: Lily Gray | C42: 45741 | D42: Writing | E42: Alphawrite | F42: Grade 5, Easy | H42: 0 | I42: 0 | J42: 0 | K42: 2 | L42: 6 | M42: 0.33333333 | N42: 0
A43: L2 | B43: Marcus Fuentes | C43: 45741 | D43: Writing | E43: Alphawrite | F43: Grade 3, Easy | H43: 0 | I43: 0 | J43: 0 | K43: 0 | L43: 0 | N43: 0
A44: L2 | B44: Mila Atamas | C44: 45741 | D44: Writing | E44: Alphawrite | H44: 0 | J44: 0 | N44: 1.09
A45: L2 | B45: Raegan Middleton | C45: 45741 | D45: Writing | E45: Alphawrite | F45: Grade 3, Easy | H45: 0 | I45: 0 | J45: 0 | K45: 22 | L45: 26 | M45: 0.84615385 | N45: 0.059999999
A46: L2 | B46: Rania Caberwal | C46: 45741 | D46: Writing | E46: Alphawrite | F46: Grade 5, Easy | H46: 0 | I46: 0 | J46: 0 | K46: 4 | L46: 6 | M46: 0.66666667 | N46: 3.23
A47: L2 | B47: Rocco Benetti | C47: 45741 | D47: Writing | E47: Alphawrite | F47: Grade 3, Easy | H47: 0 | I47: 0 | J47: 0 | K47: 14 | L47: 14 | M47: 1 | N47: 0
A48: L2 | B48: Xavier Siddall | C48: 45741 | D48: Writing | E48: Alphawrite | F48: Grade 3, Easy | H48: 0 | I48: 0 | J48: 0 | K48: 16 | L48: 21 | M48: 0.76190476 | N48: 23.559999
A49: L3 | B49: Bennett Morris | C49: 45741 | D49: Writing | E49: Alphawrite | F49: Grade 5, Easy | H49: 0 | I49: 1 | J49: 0 | K49: 32 | L49: 44 | M49: 0.72727273 | N49: 11.96
A50: L3 | B50: Penny Marty | C50: 45741 | D50: Writing | E50: Alphawrite | F50: Grade 3, Easy | H50: 0 | I50: 2 | J50: 0 | K50: 36 | L50: 44 | M50: 0.81818182 | N50: 0
A51: L3 | B51: Sydney Barba | C51: 45741 | D51: Writing | E51: Alphawrite | F51: Grade 5, Easy | H51: 0 | I51: 1 | J51: 0 | K51: 8 | L51: 8 | M51: 1 | N51: 14.3
A52: L1 | B52: Aleina Boyce | C52: 45740 | D52: Writing | E52: Alphawrite | H52: 0 | J52: 0 | N52: 13.51
A53: L1 | B53: Alex Lekic Brajovic | C53: 45740 | D53: Writing | E53: Alphawrite | H53: 0 | J53: 0 | N53: 0.02
A54: L1 | B54: Alexander Wiebeck | C54: 45740 | D54: Writing | E54: Alphawrite | F54: Grade 3, Easy | H54: 0 | I54: 0 | J54: 0 | K54: 2 | L54: 2 | M54: 1 | N54: 3.5
A55: L1 | B55: Anaya Lenington | C55: 45740 | D55: Writing | E55: Alphawrite | F55: Grade 3, Easy | G55: ANTI | Working on non-recommended skills | H55: 1 | I55: 0 | J55: 0 | K55: 0 | L55: 0 | N55: 0
A56: L1 | B56: Anaya Lenington | C56: 45740 | D56: Writing | E56: Alphawrite | F56: Grade 4, Easy | G56: ANTI | Working on non-recommended skills | H56: 1 | I56: 1 | J56: 0 | K56: 27 | L56: 42 | M56: 0.64285714 | N56: 97.029999
A57: L1 | B57: Arjun Caberwal | C57: 45740 | D57: Writing | E57: Alphawrite | F57: Grade 4, Easy | G57: ANTI | Working on non-recommended skills | H57: 1 | I57: 0 | J57: 0 | K57: 16 | L57: 20 | M57: 0.8 | N57: 7.73
A58: L1 | B58: Arman Caberwal | C58: 45740 | D58: Writing | E58: Alphawrite | F58: Grade 4, Easy | G58: ANTI | Working on non-recommended skills | H58: 1 | I58: 1 | J58: 0 | K58: 44 | L58: 66 | M58: 0.66666667 | N58: 33.880001
A59: L1 | B59: Aubrey Curtis | C59: 45740 | D59: Writing | E59: Alphawrite | F59: Grade 4, Easy | G59: ANTI | Working on non-recommended skills | H59: 1 | I59: 0 | J59: 0 | K59: 6 | L59: 8 | M59: 0.75 | N59: 6.3699999
A60: L1 | B60: Brady York | C60: 45740 | D60: Writing | E60: Alphawrite | F60: Grade 3, Easy | G60: ANTI | Working on non-recommended skills | H60: 1 | I60: 1 | J60: 0 | K60: 30 | L60: 41 | M60: 0.73170732 | N60: 41.48
A61: L1 | B61: Claudia Hobart | C61: 45740 | D61: Writing | E61: Alphawrite | F61: Grade 5, Easy | G61: ANTI | Working on non-recommended skills | H61: 1 | I61: 1 | J61: 0 | K61: 14 | L61: 17 | M61: 0.82352941 | N61: 9.8299999
A62: L1 | B62: David Paul | C62: 45740 | D62: Writing | E62: Alphawrite | F62: Grade 3, Easy | G62: ANTI | Working on non-recommended skills | H62: 1 | I62: 1 | J62: 0 | K62: 34 | L62: 51 | M62: 0.66666667 | N62: 15.26
A63: L1 | B63: David Paul | C63: 45740 | D63: Writing | E63: Alphawrite | F63: Grade 6, Easy | G63: ANTI | Working on non-recommended skills | H63: 1 | I63: 0 | J63: 0 | K63: 0 | L63: 0 | N63: 0
A64: L1 | B64: Donnie Moore | C64: 45740 | D64: Writing | E64: Alphawrite | F64: Grade 3, Easy | H64: 0 | I64: 1 | J64: 0 | K64: 24 | L64: 32 | M64: 0.75 | N64: 11.55
A65: L1 | B65: Evelyn Gabler | C65: 45740 | D65: Writing | E65: Alphawrite | F65: Grade 4, Easy | H65: 0 | I65: 0 | J65: 0 | K65: 18 | L65: 26 | M65: 0.69230769 | N65: 13.78
A66: L1 | B66: Evelyn Gabler | C66: 45740 | D66: Writing | E66: Alphawrite | F66: Grade 5, Easy | H66: 0 | I66: 0 | J66: 0 | K66: 0 | L66: 0 | N66: 0
A67: L1 | B67: Hazel Salton | C67: 45740 | D67: Writing | E67: Alphawrite | F67: Grade 3, Easy | H67: 0 | I67: 2 | J67: 0 | K67: 29 | L67: 33 | M67: 0.87878788 | N67: 0
A68: L1 | B68: Hazel Salton | C68: 45740 | D68: Writing | E68: Alphawrite | F68: Grade 4, Easy | H68: 0 | I68: 0 | J68: 0 | K68: 10 | L68: 22 | M68: 0.45454545 | N68: 0
A69: L1 | B69: Ian Mentgen | C69: 45740 | D69: Writing | E69: Alphawrite | F69: Grade 3, Easy | G69: ANTI | Working on non-recommended skills | H69: 1 | I69: 3 | J69: 0 | K69: 58 | L69: 66 | M69: 0.87878788 | N69: 26.52
A70: L1 | B70: Jaxon Siers | C70: 45740 | D70: Writing | E70: Alphawrite | F70: Grade 3, Easy | G70: ANTI | Working on non-recommended skills | H70: 1 | I70: 3 | J70: 0 | K70: 53 | L70: 73 | M70: 0.7260274 | N70: 28.870001
A71: L1 | B71: Jaxon Siers | C71: 45740 | D71: Writing | E71: Alphawrite | F71: Grade 4, Easy | G71: ANTI | Working on non-recommended skills | H71: 1 | I71: 0 | J71: 0 | K71: 2 | L71: 7 | M71: 0.28571429 | N71: 0
A72: L1 | B72: Juan Diego Ortega | C72: 45740 | D72: Writing | E72: Alphawrite | H72: 0 | J72: 0 | N72: 0.079999998
A73: L1 | B73: Logan Campbell | C73: 45740 | D73: Writing | E73: Alphawrite | F73: Grade 4, Easy | G73: ANTI | Working on non-recommended skills | H73: 1 | I73: 0 | J73: 0 | K73: 8 | L73: 15 | M73: 0.53333333 | N73: 15.66
A74: L1 | B74: Lukas Siers | C74: 45740 | D74: Writing | E74: Alphawrite | F74: Grade 3, Easy | H74: 0 | I74: 0 | J74: 0 | K74: 1 | L74: 14 | M74: 0.071428571 | N74: 16.280001
A75: L1 | B75: Max Vaughan | C75: 45740 | D75: Writing | E75: Alphawrite | F75: Grade 3, Easy | G75: ANTI | Working on non-recommended skills | H75: 1 | I75: 0 | J75: 0 | K75: 2 | L75: 2 | M75: 1 | N75: 9.4700003
A76: L1 | B76: Sarah Hunter | C76: 45740 | D76: Writing | E76: Alphawrite | F76: Grade 3, Easy | G76: ANTI | Working on non-recommended skills | H76: 1 | I76: 1 | J76: 0 | K76: 26 | L76: 42 | M76: 0.61904762 | N76: 16.15
A77: L1 | B77: Sophia Reicher | C77: 45740 | D77: Writing | E77: Alphawrite | F77: Grade 5, Easy | G77: ANTI | Working on non-recommended skills | H77: 1 | I77: 0 | J77: 0 | K77: 14 | L77: 16 | M77: 0.875 | N77: 23.77
A78: L1 | B78: Tate Price | C78: 45740 | D78: Writing | E78: Alphawrite | F78: Grade 5, Easy | G78: ANTI | Working on non-recommended skills | H78: 1 | I78: 1 | J78: 0 | K78: 26 | L78: 34 | M78: 0.76470588 | N78: 40.139999
A79: L1 | B79: Zane Rogers | C79: 45740 | D79: Writing | E79: Alphawrite | F79: Grade 4, Easy | H79: 0 | I79: 0 | J79: 0 | K79: 0 | L79: 4 | M79: 0 | N79: 6.9400001
A80: L2 | B80: Blake Flores | C80: 45740 | D80: Writing | E80: Alphawrite | F80: Grade 5, Easy | H80: 0 | I80: 0 | J80: 0 | K80: 0 | L80: 0 | N80: 3.8499999
A81: L2 | B81: Brooklyn Allred | C81: 45740 | D81: Writing | E81: Alphawrite | F81: Grade 4, Easy | G81: ANTI | Working on non-recommended skills | H81: 1 | I81: 0 | J81: 0 | K81: 16 | L81: 26 | M81: 0.61538461 | N81: 12.2
A82: L2 | B82: Connor Cason | C82: 45740 | D82: Writing | E82: Alphawrite | F82: Grade 3, Easy | G82: ANTI | Working on non-recommended skills | H82: 1 | I82: 0 | J82: 0 | K82: 5 | L82: 15 | M82: 0.33333333 | N82: 19.870001
A83: L2 | B83: Connor Cason | C83: 45740 | D83: Writing | E83: Alphawrite | F83: Grade 4, Easy | G83: ANTI | Working on non-recommended skills | H83: 1 | I83: 0 | J83: 0 | K83: 4 | L83: 4 | M83: 1 | N83: 0
A84: L2 | B84: Elena Mentgen | C84: 45740 | D84: Writing | E84: Alphawrite | F84: Grade 3, Easy | G84: ANTI | Working on non-recommended skills | H84: 1 | I84: 0 | J84: 0 | K84: 17 | L84: 21 | M84: 0.80952381 | N84: 11.86
A85: L2 | B85: Ellen Meegan | C85: 45740 | D85: Writing | E85: Edulastic | H85: 0 | J85: 0 | N85: 9.96
A86: L2 | B86: Felix Cole | C86: 45740 | D86: Writing | E86: Alphawrite | F86: Grade 5, Easy | G86: ANTI | Working on non-recommended skills | H86: 1 | I86: 0 | J86: 0 | K86: 14 | L86: 22 | M86: 0.63636364 | N86: 30.9
A87: L2 | B87: Helio Ortiz | C87: 45740 | D87: Writing | E87: Alphawrite | F87: Grade 3, Easy | G87: ANTI | Working on non-recommended skills | H87: 1 | I87: 0 | J87: 0 | K87: 4 | L87: 12 | M87: 0.33333333 | N87: 9.6000004
A88: L2 | B88: Johnny Darcy | C88: 45740 | D88: Writing | E88: Alphawrite | F88: Grade 3, Easy | G88: ANTI | Working on non-recommended skills | H88: 1 | I88: 0 | J88: 0 | K88: 10 | L88: 12 | M88: 0.83333333 | N88: 3.6199999
A89: L2 | B89: Kaiden Szpitalak | C89: 45740 | D89: Writing | E89: Alphawrite | H89: 0 | J89: 0 | N89: 1.54
A90: L2 | B90: Lily Gray | C90: 45740 | D90: Writing | E90: Alphawrite | F90: Grade 5, Easy | G90: ANTI | Working on non-recommended skills | H90: 1 | I90: 0 | J90: 0 | K90: 10 | L90: 19 | M90: 0.52631579 | N90: 14.8
A91: L2 | B91: Marcus Fuentes | C91: 45740 | D91: Writing | E91: Alphawrite | H91: 0 | J91: 0 | N91: 16.379999
A92: L2 | B92: Orion Campbell | C92: 45740 | D92: Writing | E92: Alphawrite | F92: Grade 5, Easy | G92: ANTI | Working on non-recommended skills | H92: 1 | I92: 0 | J92: 0 | K92: 4 | L92: 7 | M92: 0.57142857 | N92: 18.040001
A93: L2 | B93: Raegan Middleton | C93: 45740 | D93: Writing | E93: Alphawrite | F93: Grade 3, Easy | H93: 0 | I93: 0 | J93: 0 | K93: 22 | L93: 29 | M93: 0.75862069 | N93: 16.92
A94: L2 | B94: Rocco Benetti | C94: 45740 | D94: Writing | E94: Alphawrite | F94: Grade 3, Easy | G94: ANTI | Working on non-recommended skills | H94: 1 | I94: 0 | J94: 0 | K94: 4 | L94: 8 | M94: 0.5 | N94: 8.6199999
A95: L2 | B95: Rocco Benetti | C95: 45740 | D95: Writing | E95: Alphawrite | F95: Grade 5, Easy | G95: ANTI | Working on non-recommended skills | H95: 1 | I95: 1 | J95: 0 | K95: 4 | L95: 4 | M95: 1 | N95: 0
A96: L2 | B96: Xavier Siddall | C96: 45740 | D96: Writing | E96: Alphawrite | F96: Grade 3, Easy | G96: ANTI | Working on non-recommended skills | H96: 1 | I96: 0 | J96: 0 | K96: 36 | L96: 69 | M96: 0.52173913 | N96: 86.949997
A97: L3 | B97: Bennett Morris | C97: 45740 | D97: Writing | E97: Alphawrite | F97: Grade 5, Easy | G97: ANTI | Working on non-recommended skills | H97: 1 | I97: 3 | J97: 0 | K97: 97 | L97: 127 | M97: 0.76377953 | N97: 43.75
A98: L1 | B98: Logan Campbell | C98: 45739 | D98: Writing | E98: Alphawrite | F98: Grade 4, Easy | H98: 0 | I98: 0 | J98: 0 | K98: 0 | L98: 0 | N98: 0
A99: L2 | B99: Elena Mentgen | C99: 45739 | D99: Writing | E99: Alphawrite | F99: Grade 3, Easy | G99: ANTI | Working on non-recommended skills | H99: 1 | I99: 1 | J99: 0 | K99: 22 | L99: 28 | M99: 0.78571429 | N99: 9.8500004
A100: L1 | B100: Alex Lekic Brajovic | C100: 45737 | D100: Writing | E100: Alphawrite | F100: Grade 4, Easy | H100: 0 | I100: 0 | J100: 0 | K100: 0 | L100: 0 | N100: 2.3900001
...

Sheet mastered-all
A1: student | B1: third_party_level_id | C1: app | D1: date | E1: activity_units_attempted | F1: activity_units_correct | G1: new grade | H1: new code
A2: Juan Diego Ortega | B2: 4.2.FRAGMENT_OR_SENTENCE | C2: Alphawrite | D2: 45746 | G2: =VLOOKUP(B2,'old-aw-skill-plan'!A:I,7,FALSE) -> 4 | H2: =VLOOKUP(B2,'old-aw-skill-plan'!A:I,9,FALSE) -> 4-1
A3: Juan Diego Ortega | B3: 4.2.MAKE_TOPIC_SENTENCES | C3: Alphawrite | D3: 45746 | G3: =VLOOKUP(B3,'old-aw-skill-plan'!A:I,7,FALSE) -> 7 | H3: =VLOOKUP(B3,'old-aw-skill-plan'!A:I,9,FALSE) -> 7-5
A4: Juan Diego Ortega | B4: 4.2.WRITE_SENTENCE_ABOUT_PICTURE | C4: Alphawrite | D4: 45746 | E4: 22 | F4: 16 | G4: =VLOOKUP(B4,'old-aw-skill-plan'!A:I,7,FALSE) -> 4 | H4: =VLOOKUP(B4,'old-aw-skill-plan'!A:I,9,FALSE) -> 4-6
A5: Elaina Robertson | B5: 4.2.FRAGMENT_OR_SENTENCE | C5: Alphawrite | D5: 45745 | E5: 15 | F5: 13 | G5: =VLOOKUP(B5,'old-aw-skill-plan'!A:I,7,FALSE) -> 4 | H5: =VLOOKUP(B5,'old-aw-skill-plan'!A:I,9,FALSE) -> 4-1
A6: Jaxon Siers | B6: 3.2.ELIMINATE_IRRELEVANT_SENTENCES | C6: Alphawrite | D6: 45745 | G6: =VLOOKUP(B6,'old-aw-skill-plan'!A:I,7,FALSE) -> 6 | H6: =VLOOKUP(B6,'old-aw-skill-plan'!A:I,9,FALSE) -> 6-4
A7: Jaxon Siers | B7: 3.2.FRAGMENT_OR_SENTENCE | C7: Alphawrite | D7: 45745 | G7: =VLOOKUP(B7,'old-aw-skill-plan'!A:I,7,FALSE) -> 3 | H7: =VLOOKUP(B7,'old-aw-skill-plan'!A:I,9,FALSE) -> 3-1
A8: Jaxon Siers | B8: 4.2.IDENTIFY_SENTENCE_TYPE | C8: Alphawrite | D8: 45745 | E8: 10 | F8: 10 | G8: =VLOOKUP(B8,'old-aw-skill-plan'!A:I,7,FALSE) -> 4 | H8: =VLOOKUP(B8,'old-aw-skill-plan'!A:I,9,FALSE) -> 4-3
A9: Juan Diego Ortega | B9: 4.2.WRITE_SENTENCE_ABOUT_PICTURE | C9: Alphawrite | D9: 45745 | E9: 4 | F9: 0 | G9: =VLOOKUP(B9,'old-aw-skill-plan'!A:I,7,FALSE) -> 4 | H9: =VLOOKUP(B9,'old-aw-skill-plan'!A:I,9,FALSE) -> 4-6
A10: Max Vaughan | B10: 3.2.CHANGE_SENTENCE_TYPE | C10: Alphawrite | D10: 45745 | E10: 14 | F10: 2 | G10: =VLOOKUP(B10,'old-aw-skill-plan'!A:I,7,FALSE) -> 3 | H10: =VLOOKUP(B10,'old-aw-skill-plan'!A:I,9,FALSE) -> 3-4
A11: Max Vaughan | B11: 3.2.FRAGMENT_OR_SENTENCE | C11: Alphawrite | D11: 45745 | E11: 10 | F11: 10 | G11: =VLOOKUP(B11,'old-aw-skill-plan'!A:I,7,FALSE) -> 3 | H11: =VLOOKUP(B11,'old-aw-skill-plan'!A:I,9,FALSE) -> 3-1
A12: Alessandra Green | B12: 3.2.FRAGMENT_OR_SENTENCE | C12: Alphawrite | D12: 45744 | E12: 18 | F12: 14 | G12: =VLOOKUP(B12,'old-aw-skill-plan'!A:I,7,FALSE) -> 3 | H12: =VLOOKUP(B12,'old-aw-skill-plan'!A:I,9,FALSE) -> 3-1
A13: Anaya Lenington | B13: 4.2.FRAGMENT_OR_SENTENCE | C13: Alphawrite | D13: 45744 | E13: 2 | F13: 0 | G13: =VLOOKUP(B13,'old-aw-skill-plan'!A:I,7,FALSE) -> 4 | H13: =VLOOKUP(B13,'old-aw-skill-plan'!A:I,9,FALSE) -> 4-1
A14: Anaya Lenington | B14: 4.2.UNSCRAMBLE_SENTENCES | C14: Alphawrite | D14: 45744 | E14: 16 | F14: 16 | G14: =VLOOKUP(B14,'old-aw-skill-plan'!A:I,7,FALSE) -> 4 | H14: =VLOOKUP(B14,'old-aw-skill-plan'!A:I,9,FALSE) -> 4-2
A15: Arjun Caberwal | B15: 4.2.IDENTIFY_SENTENCE_TYPE | C15: Alphawrite | D15: 45744 | E15: 14 | F15: 14 | G15: =VLOOKUP(B15,'old-aw-skill-plan'!A:I,7,FALSE) -> 4 | H15: =VLOOKUP(B15,'old-aw-skill-plan'!A:I,9,FALSE) -> 4-3
A16: Arman Caberwal | B16: 4.2.UNSCRAMBLE_SENTENCES | C16: Alphawrite | D16: 45744 | E16: 12 | F16: 12 | G16: =VLOOKUP(B16,'old-aw-skill-plan'!A:I,7,FALSE) -> 4 | H16: =VLOOKUP(B16,'old-aw-skill-plan'!A:I,9,FALSE) -> 4-2
A17: Asher Hazard | B17: 3.2.FRAGMENT_OR_SENTENCE | C17: Alphawrite | D17: 45744 | E17: 11 | F17: 6 | G17: =VLOOKUP(B17,'old-aw-skill-plan'!A:I,7,FALSE) -> 3 | H17: =VLOOKUP(B17,'old-aw-skill-plan'!A:I,9,FALSE) -> 3-1
A18: Asher Hazard | B18: 3.2.WRITE_SENTENCE_ABOUT_PICTURE | C18: Alphawrite | D18: 45744 | G18: =VLOOKUP(B18,'old-aw-skill-plan'!A:I,7,FALSE) -> 3 | H18: =VLOOKUP(B18,'old-aw-skill-plan'!A:I,9,FALSE) -> 3-6
A19: Bella Barba | B19: 5.2.CHANGE_SENTENCE_TYPE | C19: Alphawrite | D19: 45744 | E19: 57 | F19: 45 | G19: =VLOOKUP(B19,'old-aw-skill-plan'!A:I,7,FALSE) -> 5 | H19: =VLOOKUP(B19,'old-aw-skill-plan'!A:I,9,FALSE) -> 5-4
A20: Bennett Morris | B20: 5.2.FRAGMENT_OR_SENTENCE | C20: Alphawrite | D20: 45744 | E20: 39 | F20: 29 | G20: =VLOOKUP(B20,'old-aw-skill-plan'!A:I,7,FALSE) -> 5 | H20: =VLOOKUP(B20,'old-aw-skill-plan'!A:I,9,FALSE) -> 5-1
A21: Brady York | B21: 3.2.UNSCRAMBLE_SENTENCES | C21: Alphawrite | D21: 45744 | E21: 12 | F21: 12 | G21: =VLOOKUP(B21,'old-aw-skill-plan'!A:I,7,FALSE) -> 3 | H21: =VLOOKUP(B21,'old-aw-skill-plan'!A:I,9,FALSE) -> 3-2
A22: Connor Cason | B22: 3.2.FRAGMENT_OR_SENTENCE | C22: Alphawrite | D22: 45744 | G22: =VLOOKUP(B22,'old-aw-skill-plan'!A:I,7,FALSE) -> 3 | H22: =VLOOKUP(B22,'old-aw-skill-plan'!A:I,9,FALSE) -> 3-1
A23: David Paul | B23: 3.2.UNSCRAMBLE_SENTENCES | C23: Alphawrite | D23: 45744 | E23: 12 | F23: 12 | G23: =VLOOKUP(B23,'old-aw-skill-plan'!A:I,7,FALSE) -> 3 | H23: =VLOOKUP(B23,'old-aw-skill-plan'!A:I,9,FALSE) -> 3-2
A24: Elena Mentgen | B24: 3.2.COMBINE_SENTENCES | C24: Alphawrite | D24: 45744 | G24: =VLOOKUP(B24,'old-aw-skill-plan'!A:I,7,FALSE) -> 3 | H24: =VLOOKUP(B24,'old-aw-skill-plan'!A:I,9,FALSE) -> 3-9
A25: Elena Mentgen | B25: 3.2.IDENTIFY_APPOSITIVES | C25: Alphawrite | D25: 45744 | E25: 15 | F25: 13 | G25: =VLOOKUP(B25,'old-aw-skill-plan'!A:I,7,FALSE) -> 3 | H25: =VLOOKUP(B25,'old-aw-skill-plan'!A:I,9,FALSE) -> 3-7
A26: Elena Mentgen | B26: 3.2.WRITE_APPOSITIVES | C26: Alphawrite | D26: 45744 | E26: 32 | F26: 24 | G26: =VLOOKUP(B26,'old-aw-skill-plan'!A:I,7,FALSE) -> 3 | H26: =VLOOKUP(B26,'old-aw-skill-plan'!A:I,9,FALSE) -> 3-8
A27: Elena Mentgen | B27: 3.2.WRITE_SENTENCE_ABOUT_PICTURE | C27: Alphawrite | D27: 45744 | E27: 15 | F27: 13 | G27: =VLOOKUP(B27,'old-aw-skill-plan'!A:I,7,FALSE) -> 3 | H27: =VLOOKUP(B27,'old-aw-skill-plan'!A:I,9,FALSE) -> 3-6
A28: Ellen Meegan | B28: 5.2.FRAGMENT_OR_SENTENCE | C28: Alphawrite | D28: 45744 | G28: =VLOOKUP(B28,'old-aw-skill-plan'!A:I,7,FALSE) -> 5 | H28: =VLOOKUP(B28,'old-aw-skill-plan'!A:I,9,FALSE) -> 5-1
A29: Hazel Salton | B29: 3.2.IDENTIFY_SENTENCE_TYPE | C29: Alphawrite | D29: 45744 | E29: 16 | F29: 14 | G29: =VLOOKUP(B29,'old-aw-skill-plan'!A:I,7,FALSE) -> 3 | H29: =VLOOKUP(B29,'old-aw-skill-plan'!A:I,9,FALSE) -> 3-3
A30: Hazel Salton | B30: 3.2.WRITE_SENTENCE_ABOUT_PICTURE | C30: Alphawrite | D30: 45744 | E30: 7 | F30: 6 | G30: =VLOOKUP(B30,'old-aw-skill-plan'!A:I,7,FALSE) -> 3 | H30: =VLOOKUP(B30,'old-aw-skill-plan'!A:I,9,FALSE) -> 3-6
A31: Ian Mentgen | B31: 3.2.FRAGMENT_OR_SENTENCE | C31: Alphawrite | D31: 45744 | E31: 6 | F31: 0 | G31: =VLOOKUP(B31,'old-aw-skill-plan'!A:I,7,FALSE) -> 3 | H31: =VLOOKUP(B31,'old-aw-skill-plan'!A:I,9,FALSE) -> 3-1
A32: Jaiden Bhakta | B32: 5.2.CHANGE_SENTENCE_TYPE | C32: Alphawrite | D32: 45744 | E32: 14 | F32: 8 | G32: =VLOOKUP(B32,'old-aw-skill-plan'!A:I,7,FALSE) -> 5 | H32: =VLOOKUP(B32,'old-aw-skill-plan'!A:I,9,FALSE) -> 5-4
A33: Jaiden Bhakta | B33: 5.2.IDENTIFY_SENTENCE_TYPE | C33: Alphawrite | D33: 45744 | E33: 13 | F33: 13 | G33: =VLOOKUP(B33,'old-aw-skill-plan'!A:I,7,FALSE) -> 5 | H33: =VLOOKUP(B33,'old-aw-skill-plan'!A:I,9,FALSE) -> 5-3
A34: Jason Montagna | B34: 4.2.CHANGE_SENTENCE_TYPE | C34: Alphawrite | D34: 45744 | E34: 24 | F34: 16 | G34: =VLOOKUP(B34,'old-aw-skill-plan'!A:I,7,FALSE) -> 4 | H34: =VLOOKUP(B34,'old-aw-skill-plan'!A:I,9,FALSE) -> 4-4
A35: Jason Montagna | B35: 4.2.IDENTIFY_SENTENCE_TYPE | C35: Alphawrite | D35: 45744 | E35: 22 | F35: 18 | G35: =VLOOKUP(B35,'old-aw-skill-plan'!A:I,7,FALSE) -> 4 | H35: =VLOOKUP(B35,'old-aw-skill-plan'!A:I,9,FALSE) -> 4-3
A36: Jason Montagna | B36: 4.2.UNSCRAMBLE_SENTENCES | C36: Alphawrite | D36: 45744 | E36: 12 | F36: 10 | G36: =VLOOKUP(B36,'old-aw-skill-plan'!A:I,7,FALSE) -> 4 | H36: =VLOOKUP(B36,'old-aw-skill-plan'!A:I,9,FALSE) -> 4-2
A37: Jason Montagna | B37: 4.2.WRITE_SENTENCE_TYPE | C37: Alphawrite | D37: 45744 | G37: =VLOOKUP(B37,'old-aw-skill-plan'!A:I,7,FALSE) -> 4 | H37: =VLOOKUP(B37,'old-aw-skill-plan'!A:I,9,FALSE) -> 4-5
A38: Juan Diego Ortega | B38: 4.2.FRAGMENT_OR_SENTENCE | C38: Alphawrite | D38: 45744 | G38: =VLOOKUP(B38,'old-aw-skill-plan'!A:I,7,FALSE) -> 4 | H38: =VLOOKUP(B38,'old-aw-skill-plan'!A:I,9,FALSE) -> 4-1
A39: Juan Diego Ortega | B39: 4.2.WRITE_SENTENCE_ABOUT_PICTURE | C39: Alphawrite | D39: 45744 | E39: 31 | F39: 14 | G39: =VLOOKUP(B39,'old-aw-skill-plan'!A:I,7,FALSE) -> 4 | H39: =VLOOKUP(B39,'old-aw-skill-plan'!A:I,9,FALSE) -> 4-6
A40: Kai Sticker | B40: 4.2.TURN_PARAGRAPH_INTO_SPO | C40: Alphawrite | D40: 45744 | E40: 8 | F40: 6 | G40: =VLOOKUP(B40,'old-aw-skill-plan'!A:I,7,FALSE) -> 7 | H40: =VLOOKUP(B40,'old-aw-skill-plan'!A:I,9,FALSE) -> 7-7
A41: Kai Sticker | B41: 4.2.WRITE_SENTENCE_ABOUT_PICTURE | C41: Alphawrite | D41: 45744 | E41: 18 | F41: 14 | G41: =VLOOKUP(B41,'old-aw-skill-plan'!A:I,7,FALSE) -> 4 | H41: =VLOOKUP(B41,'old-aw-skill-plan'!A:I,9,FALSE) -> 4-6
A42: Krish Bhakta | B42: 5.2.CHANGE_SENTENCE_TYPE | C42: Alphawrite | D42: 45744 | E42: 20 | F42: 4 | G42: =VLOOKUP(B42,'old-aw-skill-plan'!A:I,7,FALSE) -> 5 | H42: =VLOOKUP(B42,'old-aw-skill-plan'!A:I,9,FALSE) -> 5-4
A43: Krish Bhakta | B43: 5.2.FRAGMENT_OR_SENTENCE | C43: Alphawrite | D43: 45744 | E43: 28 | F43: 24 | G43: =VLOOKUP(B43,'old-aw-skill-plan'!A:I,7,FALSE) -> 5 | H43: =VLOOKUP(B43,'old-aw-skill-plan'!A:I,9,FALSE) -> 5-1
A44: Krish Bhakta | B44: 5.2.IDENTIFY_SENTENCE_TYPE | C44: Alphawrite | D44: 45744 | E44: 16 | F44: 14 | G44: =VLOOKUP(B44,'old-aw-skill-plan'!A:I,7,FALSE) -> 5 | H44: =VLOOKUP(B44,'old-aw-skill-plan'!A:I,9,FALSE) -> 5-3
A45: Krish Bhakta | B45: 5.2.UNSCRAMBLE_SENTENCES | C45: Alphawrite | D45: 45744 | E45: 10 | F45: 10 | G45: =VLOOKUP(B45,'old-aw-skill-plan'!A:I,7,FALSE) -> 5 | H45: =VLOOKUP(B45,'old-aw-skill-plan'!A:I,9,FALSE) -> 5-2
A46: Luna Montagna | B46: 3.2.FRAGMENT_OR_SENTENCE | C46: Alphawrite | D46: 45744 | E46: 11 | F46: 4 | G46: =VLOOKUP(B46,'old-aw-skill-plan'!A:I,7,FALSE) -> 3 | H46: =VLOOKUP(B46,'old-aw-skill-plan'!A:I,9,FALSE) -> 3-1
A47: Omar Ibarra | B47: 4.2.FRAGMENT_OR_SENTENCE | C47: Alphawrite | D47: 45744 | G47: =VLOOKUP(B47,'old-aw-skill-plan'!A:I,7,FALSE) -> 4 | H47: =VLOOKUP(B47,'old-aw-skill-plan'!A:I,9,FALSE) -> 4-1
A48: Penny Marty | B48: 3.2.CHANGE_SENTENCE_TYPE | C48: Alphawrite | D48: 45744 | E48: 40 | F48: 30 | G48: =VLOOKUP(B48,'old-aw-skill-plan'!A:I,7,FALSE) -> 3 | H48: =VLOOKUP(B48,'old-aw-skill-plan'!A:I,9,FALSE) -> 3-4
A49: Raegan Middleton | B49: 3.2.FRAGMENT_OR_SENTENCE | C49: Alphawrite | D49: 45744 | E49: 2 | F49: 2 | G49: =VLOOKUP(B49,'old-aw-skill-plan'!A:I,7,FALSE) -> 3 | H49: =VLOOKUP(B49,'old-aw-skill-plan'!A:I,9,FALSE) -> 3-1
A50: Raegan Middleton | B50: 3.2.UNSCRAMBLE_SENTENCES | C50: Alphawrite | D50: 45744 | E50: 12 | F50: 12 | G50: =VLOOKUP(B50,'old-aw-skill-plan'!A:I,7,FALSE) -> 3 | H50: =VLOOKUP(B50,'old-aw-skill-plan'!A:I,9,FALSE) -> 3-2
A51: Rocco Benetti | B51: 3.2.UNSCRAMBLE_SENTENCES | C51: Alphawrite | D51: 45744 | E51: 12 | F51: 12 | G51: =VLOOKUP(B51,'old-aw-skill-plan'!A:I,7,FALSE) -> 3 | H51: =VLOOKUP(B51,'old-aw-skill-plan'!A:I,9,FALSE) -> 3-2
A52: Rocco Benetti | B52: 5.2.IDENTIFY_SENTENCE_TYPE | C52: Alphawrite | D52: 45744 | E52: 14 | F52: 14 | G52: =VLOOKUP(B52,'old-aw-skill-plan'!A:I,7,FALSE) -> 5 | H52: =VLOOKUP(B52,'old-aw-skill-plan'!A:I,9,FALSE) -> 5-3
A53: Rocco Benetti | B53: 5.2.IDENTIFY_TS_AND_SEQUENCE_DETAILS | C53: Alphawrite | D53: 45744 | G53: =VLOOKUP(B53,'old-aw-skill-plan'!A:I,7,FALSE) -> #N/A | H53: =VLOOKUP(B53,'old-aw-skill-plan'!A:I,9,FALSE) -> #N/A
A54: Rocco Benetti | B54: 5.2.WRITE_APPOSITIVES | C54: Alphawrite | D54: 45744 | E54: 10 | F54: 6 | G54: =VLOOKUP(B54,'old-aw-skill-plan'!A:I,7,FALSE) -> 5 | H54: =VLOOKUP(B54,'old-aw-skill-plan'!A:I,9,FALSE) -> 5-8
A55: Rocco Benetti | B55: 5.2.WRITE_SENTENCE_ABOUT_PICTURE | C55: Alphawrite | D55: 45744 | E55: 19 | F55: 17 | G55: =VLOOKUP(B55,'old-aw-skill-plan'!A:I,7,FALSE) -> 5 | H55: =VLOOKUP(B55,'old-aw-skill-plan'!A:I,9,FALSE) -> 5-6
A56: Xavier Siddall | B56: 3.2.FRAGMENT_OR_SENTENCE | C56: Alphawrite | D56: 45744 | E56: 10 | F56: 4 | G56: =VLOOKUP(B56,'old-aw-skill-plan'!A:I,7,FALSE) -> 3 | H56: =VLOOKUP(B56,'old-aw-skill-plan'!A:I,9,FALSE) -> 3-1
A57: Alessandra Green | B57: 3.2.UNSCRAMBLE_SENTENCES | C57: Alphawrite | D57: 45743 | E57: 21 | F57: 19 | G57: =VLOOKUP(B57,'old-aw-skill-plan'!A:I,7,FALSE) -> 3 | H57: =VLOOKUP(B57,'old-aw-skill-plan'!A:I,9,FALSE) -> 3-2
A58: Arjun Caberwal | B58: 4.2.FRAGMENT_OR_SENTENCE | C58: Alphawrite | D58: 45743 | E58: 19 | F58: 8 | G58: =VLOOKUP(B58,'old-aw-skill-plan'!A:I,7,FALSE) -> 4 | H58: =VLOOKUP(B58,'old-aw-skill-plan'!A:I,9,FALSE) -> 4-1
A59: Arjun Caberwal | B59: 4.2.UNSCRAMBLE_SENTENCES | C59: Alphawrite | D59: 45743 | E59: 12 | F59: 12 | G59: =VLOOKUP(B59,'old-aw-skill-plan'!A:I,7,FALSE) -> 4 | H59: =VLOOKUP(B59,'old-aw-skill-plan'!A:I,9,FALSE) -> 4-2
A60: Arman Caberwal | B60: 4.2.FRAGMENT_OR_SENTENCE | C60: Alphawrite | D60: 45743 | E60: 13 | F60: 8 | G60: =VLOOKUP(B60,'old-aw-skill-plan'!A:I,7,FALSE) -> 4 | H60: =VLOOKUP(B60,'old-aw-skill-plan'!A:I,9,FALSE) -> 4-1
A61: Arman Caberwal | B61: 4.2.WRITE_SENTENCE_ABOUT_PICTURE | C61: Alphawrite | D61: 45743 | E61: 17 | F61: 13 | G61: =VLOOKUP(B61,'old-aw-skill-plan'!A:I,7,FALSE) -> 4 | H61: =VLOOKUP(B61,'old-aw-skill-plan'!A:I,9,FALSE) -> 4-6
A62: Asha Nagar | B62: 5.2.FRAGMENT_OR_SENTENCE | C62: Alphawrite | D62: 45743 | E62: 2 | F62: 0 | G62: =VLOOKUP(B62,'old-aw-skill-plan'!A:I,7,FALSE) -> 5 | H62: =VLOOKUP(B62,'old-aw-skill-plan'!A:I,9,FALSE) -> 5-1
A63: Bella Barba | B63: 5.2.FRAGMENT_OR_SENTENCE | C63: Alphawrite | D63: 45743 | E63: 18 | F63: 16 | G63: =VLOOKUP(B63,'old-aw-skill-plan'!A:I,7,FALSE) -> 5 | H63: =VLOOKUP(B63,'old-aw-skill-plan'!A:I,9,FALSE) -> 5-1
A64: Bella Barba | B64: 5.2.IDENTIFY_SENTENCE_TYPE | C64: Alphawrite | D64: 45743 | E64: 17 | F64: 15 | G64: =VLOOKUP(B64,'old-aw-skill-plan'!A:I,7,FALSE) -> 5 | H64: =VLOOKUP(B64,'old-aw-skill-plan'!A:I,9,FALSE) -> 5-3
A65: Bella Barba | B65: 5.2.UNSCRAMBLE_SENTENCES | C65: Alphawrite | D65: 45743 | E65: 22 | F65: 18 | G65: =VLOOKUP(B65,'old-aw-skill-plan'!A:I,7,FALSE) -> 5 | H65: =VLOOKUP(B65,'old-aw-skill-plan'!A:I,9,FALSE) -> 5-2
A66: Bennett Morris | B66: 5.2.FRAGMENT_OR_SENTENCE | C66: Alphawrite | D66: 45743 | E66: 19 | F66: 6 | G66: =VLOOKUP(B66,'old-aw-skill-plan'!A:I,7,FALSE) -> 5 | H66: =VLOOKUP(B66,'old-aw-skill-plan'!A:I,9,FALSE) -> 5-1
A67: Blake Flores | B67: 5.2.CHANGE_SENTENCE_TYPE | C67: Alphawrite | D67: 45743 | G67: =VLOOKUP(B67,'old-aw-skill-plan'!A:I,7,FALSE) -> 5 | H67: =VLOOKUP(B67,'old-aw-skill-plan'!A:I,9,FALSE) -> 5-4
A68: Blake Flores | B68: 5.2.IDENTIFY_SENTENCE_TYPE | C68: Alphawrite | D68: 45743 | E68: 16 | F68: 14 | G68: =VLOOKUP(B68,'old-aw-skill-plan'!A:I,7,FALSE) -> 5 | H68: =VLOOKUP(B68,'old-aw-skill-plan'!A:I,9,FALSE) -> 5-3
A69: Blake Flores | B69: 5.2.UNSCRAMBLE_SENTENCES | C69: Alphawrite | D69: 45743 | E69: 19 | F69: 15 | G69: =VLOOKUP(B69,'old-aw-skill-plan'!A:I,7,FALSE) -> 5 | H69: =VLOOKUP(B69,'old-aw-skill-plan'!A:I,9,FALSE) -> 5-2
A70: Brady York | B70: 3.2.FRAGMENT_OR_SENTENCE | C70: Alphawrite | D70: 45743 | E70: 57 | F70: 44 | G70: =VLOOKUP(B70,'old-aw-skill-plan'!A:I,7,FALSE) -> 3 | H70: =VLOOKUP(B70,'old-aw-skill-plan'!A:I,9,FALSE) -> 3-1
A71: Claudia Hobart | B71: 5.2.FRAGMENT_OR_SENTENCE | C71: Alphawrite | D71: 45743 | E71: 16 | F71: 14 | G71: =VLOOKUP(B71,'old-aw-skill-plan'!A:I,7,FALSE) -> 5 | H71: =VLOOKUP(B71,'old-aw-skill-plan'!A:I,9,FALSE) -> 5-1
A72: Claudia Hobart | B72: 5.2.UNSCRAMBLE_SENTENCES | C72: Alphawrite | D72: 45743 | E72: 12 | F72: 12 | G72: =VLOOKUP(B72,'old-aw-skill-plan'!A:I,7,FALSE) -> 5 | H72: =VLOOKUP(B72,'old-aw-skill-plan'!A:I,9,FALSE) -> 5-2
A73: David Paul | B73: 3.2.FRAGMENT_OR_SENTENCE | C73: Alphawrite | D73: 45743 | E73: 18 | F73: 14 | G73: =VLOOKUP(B73,'old-aw-skill-plan'!A:I,7,FALSE) -> 3 | H73: =VLOOKUP(B73,'old-aw-skill-plan'!A:I,9,FALSE) -> 3-1
A74: Elaina Robertson | B74: 4.2.FRAGMENT_OR_SENTENCE | C74: Alphawrite | D74: 45743 | E74: 21 | F74: 17 | G74: =VLOOKUP(B74,'old-aw-skill-plan'!A:I,7,FALSE) -> 4 | H74: =VLOOKUP(B74,'old-aw-skill-plan'!A:I,9,FALSE) -> 4-1
A75: Elena Mentgen | B75: 3.2.CHANGE_SENTENCE_TYPE | C75: Alphawrite | D75: 45743 | E75: 29 | F75: 23 | G75: =VLOOKUP(B75,'old-aw-skill-plan'!A:I,7,FALSE) -> 3 | H75: =VLOOKUP(B75,'old-aw-skill-plan'!A:I,9,FALSE) -> 3-4
A76: Elena Mentgen | B76: 3.2.FRAGMENT_OR_SENTENCE | C76: Alphawrite | D76: 45743 | E76: 16 | F76: 14 | G76: =VLOOKUP(B76,'old-aw-skill-plan'!A:I,7,FALSE) -> 3 | H76: =VLOOKUP(B76,'old-aw-skill-plan'!A:I,9,FALSE) -> 3-1
A77: Elena Mentgen | B77: 3.2.IDENTIFY_SENTENCE_TYPE | C77: Alphawrite | D77: 45743 | E77: 15 | F77: 15 | G77: =VLOOKUP(B77,'old-aw-skill-plan'!A:I,7,FALSE) -> 3 | H77: =VLOOKUP(B77,'old-aw-skill-plan'!A:I,9,FALSE) -> 3-3
A78: Elena Mentgen | B78: 3.2.UNSCRAMBLE_SENTENCES | C78: Alphawrite | D78: 45743 | E78: 18 | F78: 14 | G78: =VLOOKUP(B78,'old-aw-skill-plan'!A:I,7,FALSE) -> 3 | H78: =VLOOKUP(B78,'old-aw-skill-plan'!A:I,9,FALSE) -> 3-2
A79: Elena Mentgen | B79: 3.2.WRITE_SENTENCE_TYPE | C79: Alphawrite | D79: 45743 | E79: 18 | F79: 16 | G79: =VLOOKUP(B79,'old-aw-skill-plan'!A:I,7,FALSE) -> 3 | H79: =VLOOKUP(B79,'old-aw-skill-plan'!A:I,9,FALSE) -> 3-5
... A81: Evelyn Gabler | B81: 4.2.UNSCRAMBLE_SENTENCES | C81: Alphawrite | D81: 45743 | E81: 4 | F81: 4 | G81: =VLOOKUP(B81,'old-aw-skill-plan'!A:I,7,FALSE) -> 4 | H81: =VLOOKUP(B81,'old-aw-skill-plan'!A:I,9,FALSE) -> 4-2
A82: Evelyn Gabler | B82: 5.2.FRAGMENT_OR_SENTENCE | C82: Alphawrite | D82: 45743 | G82: =VLOOKUP(B82,'old-aw-skill-plan'!A:I,7,FALSE) -> 5 | H82: =VLOOKUP(B82,'old-aw-skill-plan'!A:I,9,FALSE) -> 5-1
A83: Hazel Salton | B83: 3.2.BASIC_CONJUNCTIONS | C83: Alphawrite | D83: 45743 | E83: 24 | F83: 22 | G83: =VLOOKUP(B83,'old-aw-skill-plan'!A:I,7,FALSE) -> 3 | H83: =VLOOKUP(B83,'old-aw-skill-plan'!A:I,9,FALSE) -> 3-10
A84: Hazel Salton | B84: 3.2.CHANGE_SENTENCE_TYPE | C84: Alphawrite | D84: 45743 | G84: =VLOOKUP(B84,'old-aw-skill-plan'!A:I,7,FALSE) -> 3 | H84: =VLOOKUP(B84,'old-aw-skill-plan'!A:I,9,FALSE) -> 3-4
A85: Hazel Salton | B85: 4.2.FRAGMENT_OR_SENTENCE | C85: Alphawrite | D85: 45743 | G85: =VLOOKUP(B85,'old-aw-skill-plan'!A:I,7,FALSE) -> 4 | H85: =VLOOKUP(B85,'old-aw-skill-plan'!A:I,9,FALSE) -> 4-1
A86: Helio Ortiz | B86: 3.2.FRAGMENT_OR_SENTENCE | C86: Alphawrite | D86: 45743 | E86: 17 | F86: 9 | G86: =VLOOKUP(B86,'old-aw-skill-plan'!A:I,7,FALSE) -> 3 | H86: =VLOOKUP(B86,'old-aw-skill-plan'!A:I,9,FALSE) -> 3-1
A87: Ian Mentgen | B87: 3.2.CHANGE_SENTENCE_TYPE | C87: Alphawrite | D87: 45743 | E87: 35 | F87: 28 | G87: =VLOOKUP(B87,'old-aw-skill-plan'!A:I,7,FALSE) -> 3 | H87: =VLOOKUP(B87,'old-aw-skill-plan'!A:I,9,FALSE) -> 3-4
A88: Jaiden Bhakta | B88: 5.2.FRAGMENT_OR_SENTENCE | C88: Alphawrite | D88: 45743 | E88: 38 | F88: 27 | G88: =VLOOKUP(B88,'old-aw-skill-plan'!A:I,7,FALSE) -> 5 | H88: =VLOOKUP(B88,'old-aw-skill-plan'!A:I,9,FALSE) -> 5-1
A89: Jaiden Bhakta | B89: 5.2.UNSCRAMBLE_SENTENCES | C89: Alphawrite | D89: 45743 | E89: 40 | F89: 35 | G89: =VLOOKUP(B89,'old-aw-skill-plan'!A:I,7,FALSE) -> 5 | H89: =VLOOKUP(B89,'old-aw-skill-plan'!A:I,9,FALSE) -> 5-2
A90: Jason Montagna | B90: 4.2.FRAGMENT_OR_SENTENCE | C90: Alphawrite | D90: 45743 | E90: 12 | F90: 12 | G90: =VLOOKUP(B90,'old-aw-skill-plan'!A:I,7,FALSE) -> 4 | H90: =VLOOKUP(B90,'old-aw-skill-plan'!A:I,9,FALSE) -> 4-1
A91: Jason Montagna | B91: 4.2.UNSCRAMBLE_SENTENCES | C91: Alphawrite | D91: 45743 | E91: 5 | F91: 3 | G91: =VLOOKUP(B91,'old-aw-skill-plan'!A:I,7,FALSE) -> 4 | H91: =VLOOKUP(B91,'old-aw-skill-plan'!A:I,9,FALSE) -> 4-2
A92: Jaxon Siers | B92: 4.2.FRAGMENT_OR_SENTENCE | C92: Alphawrite | D92: 45743 | G92: =VLOOKUP(B92,'old-aw-skill-plan'!A:I,7,FALSE) -> 4 | H92: =VLOOKUP(B92,'old-aw-skill-plan'!A:I,9,FALSE) -> 4-1
A93: Jaxon Siers | B93: 5.2.IDENTIFY_SENTENCE_TYPE | C93: Alphawrite | D93: 45743 | E93: 14 | F93: 14 | G93: =VLOOKUP(B93,'old-aw-skill-plan'!A:I,7,FALSE) -> 5 | H93: =VLOOKUP(B93,'old-aw-skill-plan'!A:I,9,FALSE) -> 5-3
A94: Kai Sticker | B94: 5.2.FRAGMENT_OR_SENTENCE | C94: Alphawrite | D94: 45743 | E94: 12 | F94: 8 | G94: =VLOOKUP(B94,'old-aw-skill-plan'!A:I,7,FALSE) -> 5 | H94: =VLOOKUP(B94,'old-aw-skill-plan'!A:I,9,FALSE) -> 5-1
A95: Kai Sticker | B95: 7.2.IDENTIFY_TS_AND_SEQUENCE_DETAILS | C95: Alphawrite | D95: 45743 | E95: 6 | F95: 0 | G95: =VLOOKUP(B95,'old-aw-skill-plan'!A:I,7,FALSE) -> #N/A | H95: =VLOOKUP(B95,'old-aw-skill-plan'!A:I,9,FALSE) -> #N/A
A96: Kai Sticker | B96: 8.2.TOPIC_BRAINSTORM | C96: Alphawrite | D96: 45743 | G96: =VLOOKUP(B96,'old-aw-skill-plan'!A:I,7,FALSE) -> #N/A | H96: =VLOOKUP(B96,'old-aw-skill-plan'!A:I,9,FALSE) -> #N/A
A97: Krish Bhakta | B97: 5.2.FRAGMENT_OR_SENTENCE | C97: Alphawrite | D97: 45743 | E97: 24 | F97: 9 | G97: =VLOOKUP(B97,'old-aw-skill-plan'!A:I,7,FALSE) -> 5 | H97: =VLOOKUP(B97,'old-aw-skill-plan'!A:I,9,FALSE) -> 5-1
A98: Lily Gray | B98: 5.2.FRAGMENT_OR_SENTENCE | C98: Alphawrite | D98: 45743 | E98: 10 | F98: 8 | G98: =VLOOKUP(B98,'old-aw-skill-plan'!A:I,7,FALSE) -> 5 | H98: =VLOOKUP(B98,'old-aw-skill-plan'!A:I,9,FALSE) -> 5-1
A99: Marcus Fuentes | B99: 3.2.FRAGMENT_OR_SENTENCE | C99: Alphawrite | D99: 45743 | E99: 19 | F99: 13 | G99: =VLOOKUP(B99,'old-aw-skill-plan'!A:I,7,FALSE) -> 3 | H99: =VLOOKUP(B99,'old-aw-skill-plan'!A:I,9,FALSE) -> 3-1
A100: Max Vaughan | B100: 3.2.IDENTIFY_SENTENCE_TYPE | C100: Alphawrite | D100: 45743 | E100: 22 | F100: 14 | G100: =VLOOKUP(B100,'old-aw-skill-plan'!A:I,7,FALSE) -> 3 | H100: =VLOOKUP(B100,'old-aw-skill-plan'!A:I,9,FALSE) -> 3-3
A101: Max Vaughan | B101: 3.2.UNSCRAMBLE_SENTENCES | C101: Alphawrite | D101: 45743 | G101: =VLOOKUP(B101,'old-aw-skill-plan'!A:I,7,FALSE) -> 3 | H101: =VLOOKUP(B101,'old-aw-skill-plan'!A:I,9,FALSE) -> 3-2
...

Sheet new-aw-skill-plan 2025
A1: skill_id | B1: name | C1: QS_ID | D1: app | E1: order | F1: grade | G1: Course | H1: URL | I1: Activity Description
A2: alphawrite-sentences-i-fragment-or-sentence | B2: Fragment or Sentence? | C2: 3.2.FRAGMENT_OR_SENTENCE | D2: Alphawrite | E2: 1 | F2: 3 | G2: Sentences G3 | H2: https://alphawrite.alpha.school/practice/3/2/fragment-or-sentence | I2: Student task: Decide whether a word group is a complete sentence or a fragment; if it is a fragment, revise it into a complete sentence. Student produces: (1) a label—Sentence or Fragment—and (2) a corrected sentence when needed. Skills taught: identify subject + predicate (complete thought); fix fragments by adding missing subject/verb/idea; apply capitalization and end punctuation. Checks for correctness: corrected version expresses a complete thought, uses standard word order, and ends with correct punctuation.
A3: alphawrite-sentences-i-unscramble-sentences | B3: Unscramble Sentences | C3: 3.2.UNSCRAMBLE_SENTENCES | D3: Alphawrite | E3: 2 | F3: 3 | G3: Sentences G3 | H3: https://alphawrite.alpha.school/practice/3/2/unscramble-sentences | I3: Student task: Rearrange a set of jumbled words into a grammatical sentence. Student produces: one correctly ordered sentence with appropriate capitalization and end punctuation. Skills taught: English word order (subject–verb–object/modifiers); recognizing parts of speech; forming complete sentences; basic conventions. Checks for correctness: sentence reads naturally, includes a subject and verb, and uses correct capitalization/punctuation.
A4: alphawrite-sentences-i-identify-sentence-type | B4: Identify the Sentence Type | C4: 3.2.IDENTIFY_SENTENCE_TYPE | D4: Alphawrite | E4: 3 | F4: 3 | G4: Sentences G3 | H4: https://alphawrite.alpha.school/practice/3/2/identify-sentence-type | I4: Student task: Read a sentence and identify its type (declarative/statement, interrogative/question, imperative/command, or exclamatory/exclamation). Student produces: a label for the sentence type (and may justify using punctuation/purpose). Skills taught: connect sentence purpose to punctuation and structure; recognize question forms and commands; distinguish statement vs exclamation. Checks for correctness: chosen type matches the sentence’s purpose and punctuation (e.g., ? for questions, ! for exclamations).
A5: alphawrite-sentences-i-change-sentence-to-question | B5: Change Sentences into Questions | C5: 3.2.CHANGE_SENTENCE_INTO_QUESTION | D5: Alphawrite | E5: 4 | F5: 3 | G5: Sentences G3 | H5: https://alphawrite.alpha.school/practice/3/2/change-sentence-into-question | I5: Student task: Rewrite a statement (or another sentence type) as an interrogative sentence (a question). Student produces: one question that matches the original idea/topic and ends with a question mark. Skills taught: form questions (use question words or auxiliary verbs such as do/does/did when needed); adjust word order; punctuation. Checks for correctness: the revision is clearly a question, preserves the intended meaning, and uses correct capitalization and a question mark.
A6: alphawrite-sentences-i-change-sentence-type | B6: Change the Sentence Type | C6: 3.2.CHANGE_SENTENCE_TYPE | D6: Alphawrite | E6: 5 | F6: 3 | G6: Sentences G3 | H6: https://alphawrite.alpha.school/practice/3/2/change-sentence-type | I6: Student task: Rewrite a sentence as a different sentence type (e.g., turn a statement into a question or command) while keeping the core meaning/topic. Student produces: a revised sentence in the requested type with correct punctuation. Skills taught: manipulate sentence structure for purpose; use correct punctuation for each type; maintain meaning while revising. Checks for correctness: revised sentence matches the requested type (structure + punctuation) and still communicates the intended idea.
A7: alphawrite-sentences-i-use-sentence-types | B7: Write the Sentence Type | C7: 3.2.USE_SENTENCE_TYPES | D7: Alphawrite | E7: 6 | F7: 3 | G7: Sentences G3 | H7: https://alphawrite.alpha.school/practice/3/2/write-sentence-type | I7: Student task: Given a topic word/idea, write one example of each sentence type: statement, question, command, and exclamation. Student produces: four sentences, each correctly labeled or clearly showing its type. Skills taught: generate varied sentence types on purpose; control punctuation and structure; expand ideas within constraints. Checks for correctness: each sentence matches its type (purpose + punctuation) and is a complete, grammatically correct sentence.
A8: alphawrite-sentences-i-write-sentence-about-picture | B8: Write Questions About a Picture | C8: 3.2.WRITE_SENTENCE_ABOUT_PICTURE | D8: Alphawrite | E8: 7 | F8: 3 | G8: Sentences G3 | H8: https://alphawrite.alpha.school/practice/3/2/write-sentence-about-picture | I8: Student task: Examine a picture and generate thoughtful questions using question words (who/what/when/where/why/how). Student produces: one or more well-formed questions that relate to what is visible or implied in the image. Skills taught: question formation; observation and inference; using WH-words; capitalization and question marks. Checks for correctness: each question is grammatical, clearly refers to the image, and is punctuated correctly.
A9: alphawrite-sentences-i-basic-conjunctions | B9: Because, But, So | C9: 3.2.BASIC_CONJUNCTIONS | D9: Alphawrite | E9: 8 | F9: 3 | G9: Sentences G3 | H9: https://alphawrite.alpha.school/practice/3/2/basic-conjunctions | I9: Student task: Complete a sentence stem three different ways using the conjunctions because, but, and so. Student produces: three complete sentences: (1) cause/reason (because), (2) contrast/complication (but), (3) result/consequence (so). Skills taught: express logical relationships (cause, contrast, result); write complex/compound sentences; use commas appropriately with conjunctions. Checks for correctness: each conjunction creates the intended logical relationship and the sentence is complete and correctly punctuated.
A10: alphawrite-sentences-i-identify-appositives | B10: Identify Appositives | C10: 3.2.IDENTIFY_APPOSITIVES | D10: Alphawrite | E10: 9 | F10: 3 | G10: Sentences G3 | H10: https://alphawrite.alpha.school/practice/3/2/identify-appositives | I10: Student task: Find the appositive (a noun or noun phrase that renames another noun) in a sentence/short text and mark where commas should go. Student produces: the identified appositive and a corrected sentence with proper comma punctuation (if missing). Skills taught: recognize renaming phrases; punctuate nonessential appositives with commas; read for grammatical structure. Checks for correctness: appositive correctly renames a noun and commas accurately set it off when nonessential.
A11: alphawrite-sentences-i-write-appositives | B11: Write Appositives | C11: 3.2.WRITE_APPOSITIVES | D11: Alphawrite | E11: 10 | F11: 3 | G11: Sentences G3 | H11: https://alphawrite.alpha.school/practice/3/2/write-appositives | I11: Student task: Add an appositive phrase to a sentence to provide extra information about a noun. Student produces: an expanded sentence that includes a correctly punctuated appositive. Skills taught: sentence expansion for precision/detail; appositive structure; comma rules for nonessential information. Checks for correctness: appositive clearly renames the noun and commas (or no commas, if essential) are used correctly.
A12: alphawrite-sentences-i-subordinating-conjunctions | B12: Complete Subordinative Conjunctions | C12: 3.2.SUBORDINATING_CONJUNCTIONS | D12: Alphawrite | E12: 11 | F12: 3 | G12: Sentences G3 | H12: https://alphawrite.alpha.school/practice/3/2/subordinating-conjunctions | I12: Student task: Use a subordinating conjunction (e.g., although, since, when, because, if) to complete a sentence so it becomes a logical complex sentence. Student produces: a complete complex sentence with a dependent clause + independent clause. Skills taught: connect ideas with subordinate clauses; choose conjunctions that match meaning (time/cause/condition/contrast); comma rules for dependent clauses. Checks for correctness: sentence includes both clauses, meaning is logical, and punctuation is correct for the clause order.
A13: alphawrite-sentences-i-combine-sentences | B13: Combine Sentences | C13: 3.2.COMBINE_SENTENCES | D13: Alphawrite | E13: 12 | F13: 3 | G13: Sentences G3 | H13: https://alphawrite.alpha.school/practice/3/2/combine-sentences | I13: Student task: Combine two or more related sentences into one stronger sentence without losing meaning. Student produces: one combined sentence (often using conjunctions, embedding, or other combining techniques) with correct punctuation. Skills taught: sentence combining to show relationships; avoid run-ons and fragments; punctuation with conjunctions/clauses; vary sentence structure. Checks for correctness: combined sentence is grammatical, preserves all key information, and uses punctuation appropriately.
... A176: AW-COMPOSITIONS-G8 | B176: Essays G8 | C176: 8.2.POLISH | D176: Alphawrite | E176: 5 | F176: 8 | G176: Essays G8 | H176: alphawrite:compositions:essays-g8:essay-1-wynq:stage-polish:resource | I176: Student task: Edit the final draft for conventions and presentation. Student produces: a polished essay with corrected grammar, spelling, punctuation, and sentence-level errors. Skills taught: editing and proofreading; fix fragments/run-ons; vary sentence structure; apply standard conventions. Checks for correctness: writing is error-minimized, formatting is consistent, and sentences are clear and correct.

Sheet old-aw-skill-plan
A1: skill_id | B1: name | C1: app | D1: grade | E1: level | F1: code | G1: new grade | H1: order | I1: new code
A2: 3.2.FRAGMENT_OR_SENTENCE | B2: 3.2 Fragment or Sentence? | C2: Alphawrite | D2: 3 | E2: easy | F2: =LEFT(A2,3) -> 3.2 | G2: 3 | H2: 1 | I2: =CONCATENATE(G2,"-",H2) -> 3-1
A3: 3.2.UNSCRAMBLE_SENTENCES | B3: 3.2 Unscramble Sentences | C3: Alphawrite | D3: 3 | E3: easy | F3: =LEFT(A3,3) -> 3.2 | G3: 3 | H3: 2 | I3: =CONCATENATE(G3,"-",H3) -> 3-2
A4: 3.2.IDENTIFY_SENTENCE_TYPE | B4: 3.2 Identify the Sentence Type | C4: Alphawrite | D4: 3 | E4: easy | F4: =LEFT(A4,3) -> 3.2 | G4: 3 | H4: 3 | I4: =CONCATENATE(G4,"-",H4) -> 3-3
A5: 3.2.CHANGE_SENTENCE_TYPE | B5: 3.2 Change the Sentence Type | C5: Alphawrite | D5: 3 | E5: easy | F5: =LEFT(A5,3) -> 3.2 | G5: 3 | H5: 4 | I5: =CONCATENATE(G5,"-",H5) -> 3-4
A6: 3.2.WRITE_SENTENCE_TYPE | B6: 3.2 Write the Sentence Type | C6: Alphawrite | D6: 3 | E6: easy | F6: =LEFT(A6,3) -> 3.2 | G6: 3 | H6: 5 | I6: =CONCATENATE(G6,"-",H6) -> 3-5
A7: 3.2.WRITE_SENTENCE_ABOUT_PICTURE | B7: 3.2 Write Questions About a Picture | C7: Alphawrite | D7: 3 | E7: easy | F7: =LEFT(A7,3) -> 3.2 | G7: 3 | H7: 6 | I7: =CONCATENATE(G7,"-",H7) -> 3-6
A8: 3.2.IDENTIFY_APPOSITIVES | B8: 3.2 Identify Appositives | C8: Alphawrite | D8: 3 | E8: easy | F8: =LEFT(A8,3) -> 3.2 | G8: 3 | H8: 7 | I8: =CONCATENATE(G8,"-",H8) -> 3-7
A9: 3.2.WRITE_APPOSITIVES | B9: 3.2 Write Appositives | C9: Alphawrite | D9: 3 | E9: easy | F9: =LEFT(A9,3) -> 3.2 | G9: 3 | H9: 8 | I9: =CONCATENATE(G9,"-",H9) -> 3-8
A10: 3.2.COMBINE_SENTENCES | B10: 3.2 Combine Sentences | C10: Alphawrite | D10: 3 | E10: easy | F10: =LEFT(A10,3) -> 3.2 | G10: 3 | H10: 9 | I10: =CONCATENATE(G10,"-",H10) -> 3-9
A11: 3.2.BASIC_CONJUNCTIONS | B11: 3.2 Because, But, So | C11: Alphawrite | D11: 3 | E11: easy | F11: =LEFT(A11,3) -> 3.2 | G11: 3 | H11: 10 | I11: =CONCATENATE(G11,"-",H11) -> 3-10
A12: 3.2.KERNEL_EXPANSION | B12: 3.2 Kernel Expansion | C12: Alphawrite | D12: 3 | E12: easy | F12: =LEFT(A12,3) -> 3.2 | G12: 3 | H12: 11 | I12: =CONCATENATE(G12,"-",H12) -> 3-11
A13: 3.2.SUBORDINATING_CONJUNCTIONS | B13: 3.2 Complete Subordinating Conjunctions | C13: Alphawrite | D13: 3 | E13: easy | F13: =LEFT(A13,3) -> 3.2 | G13: 3 | H13: 12 | I13: =CONCATENATE(G13,"-",H13) -> 3-12
... A217: 5.2.WRITE_FREEFORM_PARAGRAPH | B217: 5.2 Write a Free-Form Paragraph | C217: Alphawrite | D217: 5 | E217: hard | F217: =LEFT(A217,3) -> 5.2 | G217: 8 | H217: 12 | I217: =CONCATENATE(G217,"-",H217) -> 8-12
